Workbook

Sheet Select (2)
A2: STATE | B2: TollShare (S) | C2: Workers Who Live Out of State (O) | D2: Percent Federal Land | E2: TollShare in Neighboring States | F2: Residents Who Work Out of State | G2: TollMile1963 | H2: Freeways, Expwy, Interstates 1995 Miles
A3: ALABAMA | B3: 0 | C3: 0.023851877 | D3: 0.03281 | E3: 0.016641465 | F3: 0.035998518 | G3: 0 | H3: 925
A4: ARIZONA | B4: 0 | C4: 0.011207188 | D4: 0.41534 | E4: 0.021735556 | F4: 0.015804395 | G4: 0 | H4: 1250
A5: ARKANSAS | B5: 0 | C5: 0.040294187 | D5: 0.08266 | E5: 0.020268432 | F5: 0.03229638 | G5: 0 | H5: 646
A6: CALIFORNIA | B6: 0.021141521 | C6: 0.0045230302 | D6: 0.44598 | E6: 0.046286746 | F6: 0.003689812 | G6: 0 | H6: 3750
A7: COLORADO | B7: 0.0029577777 | C7: 0.0079445411 | D7: 0.35954 | E7: 0.038557176 | F7: 0.010250283 | G7: 17.3 | H7: 1170
A8: CONNECTICUT | B8: 0.00025988579 | C8: 0.045612423 | D8: 0.00238 | E8: 0.26023043 | F8: 0.047445028 | G8: 193.9 | H8: 542
A9: DELAWARE | B9: 0.25259005 | C9: 0.13832888 | D9: 0.02219 | E9: 0.11872671 | F9: 0.095045716 | G9: 11.2 | H9: 51
A10: FLORIDA | B10: 0.077833555 | C10: 0.0079942105 | D10: 0.07562 | E10: 0.062671969 | F10: 0.009986905 | G10: 206.6 | H10: 1861
A11: GEORGIA | B11: 0.0041858291 | C11: 0.028137824 | D11: 0.03892 | E11: 0.02061609 | F11: 0.023891522 | G11: 11.1 | H11: 1413
A12: HAWAII | B12: 0 | C12: 0.0095240957 | D12: 0.08548 | E12: 0.035368224 | F12: 0.0046752296 | G12: 0 | H12: 77
A13: IDAHO | B13: 0 | C13: 0.026148588 | D13: 0.60588 | E13: 0.025523251 | F13: 0.039782418 | G13: 0 | H13: 613
A14: ILLINOIS | B14: 0.092502027 | C14: 0.028193774 | D14: 0.01266 | E14: 0.013967169 | F14: 0.02868334 | G14: 185.3 | H14: 2245
... A51: WYOMING | B51: 0 | C51: 0.025620995 | D51: 0.48452 | E51: 0.011513892 | F51: 0.020060442 | G51: 0 | H51: 916

Sheet LAND_ALL
A1: SUMMARY OUTPUT = TOLL SHARE
A3: Regression Statistics
A4: Multiple R | B4: 0.30177658
A5: R Square | B5: 0.091069107
A6: Adjusted R Square | B6: 0.072133046
A7: Standard Error | B7: 0.069811443
A8: Observations | B8: 50
A10: ANOVA
B11: df | C11: SS | D11: MS | E11: F | F11: Significance F
A12: Regression | B12: 1 | C12: 0.023438763 | D12: 0.023438763 | E12: 4.8092953 | F12: 0.033184676
A13: Residual | B13: 48 | C13: 0.23393461 | D13: 0.0048736376
A14: Total | B14: 49 | C14: 0.25737337
B16: Coefficients | C16: Standard Error | D16: t Stat | E16: P-value | F16: Lower 95% | G16: Upper 95% | H16: Lower 95.0% | I16: Upper 95.0%
A17: Intercept | B17: 0.068596656 | C17: 0.015935773 | D17: 4.3045704 | E17: 8.2014384e-05 | F17: 0.036555656 | G17: 0.10063766 | H17: 0.036555656 | I17: 0.10063766
A18: Land | B18: -4.6245325e-07 | C18: 2.1087598e-07 | D18: -2.1930106 | E18: 0.033184676 | F18: -8.8644757e-07 | G18: -3.8458925e-08 | H18: -8.8644757e-07 | I18: -3.8458925e-08
A20: note; Excluding Alaska

Sheet LAND_TOLLSTATES
A1: SUMMARY OUTPUT = TOLLSHARE
A3: Regression Statistics
A4: Multiple R | B4: 0.32039386
A5: R Square | B5: 0.10265222
A6: Adjusted R Square | B6: 0.074610105
A7: Standard Error | B7: 0.07809766
A8: Observations | B8: 34
A10: ANOVA
B11: df | C11: SS | D11: MS | E11: F | F11: Significance F
A12: Regression | B12: 1 | C12: 0.022327165 | D12: 0.022327165 | E12: 3.6606444 | F12: 0.064694973
A13: Residual | B13: 32 | C13: 0.19517582 | D13: 0.0060992445
A14: Total | B14: 33 | C14: 0.21750299
B16: Coefficients | C16: Standard Error | D16: t Stat | E16: P-value | F16: Lower 95% | G16: Upper 95% | H16: Lower 95.0% | I16: Upper 95.0%
A17: Intercept | B17: 0.089767616 | C17: 0.020318011 | D17: 4.4181301 | E17: 0.0001067953 | F17: 0.048381217 | G17: 0.13115401 | H17: 0.048381217 | I17: 0.13115401
A18: Land | B18: -5.2988934e-07 | C18: 2.7695321e-07 | D18: -1.9132811 | E18: 0.064694973 | F18: -1.0940241e-06 | G18: 3.4245419e-08 | H18: -1.0940241e-06 | I18: 3.4245419e-08

Sheet LANDPOP_TOLL STATES
A1: SUMMARY OUTPUT = TOLLSHARE
A3: Regression Statistics
A4: Multiple R | B4: 0.52576629
A5: R Square | B5: 0.27643019
A6: Adjusted R Square | B6: 0.22474663
A7: Standard Error | B7: 0.072871138
A8: Observations | B8: 31
A10: ANOVA
B11: df | C11: SS | D11: MS | E11: F | F11: Significance F
A12: Regression | B12: 2 | C12: 0.056803379 | D12: 0.02840169 | E12: 5.3485132 | F12: 0.010782665
A13: Residual | B13: 28 | C13: 0.14868568 | D13: 0.0053102028
A14: Total | B14: 30 | C14: 0.20548906
B16: Coefficients | C16: Standard Error | D16: t Stat | E16: P-value | F16: Lower 95% | G16: Upper 95% | H16: Lower 95.0% | I16: Upper 95.0%
A17: Intercept | B17: 0.084518127 | C17: 0.021197003 | D17: 3.9872678 | E17: 0.00043479502 | F17: 0.041097987 | G17: 0.12793827 | H17: 0.041097987 | I17: 0.12793827
A18: Land | B18: -9.8951041e-07 | C18: 3.1070623e-07 | D18: -3.1847138 | E18: 0.0035393176 | F18: -1.625964e-06 | G18: -3.5305684e-07 | H18: -1.625964e-06 | I18: -3.5305684e-07
A19: Population | B19: 5.5009846e-09 | C19: 2.3677663e-09 | D19: 2.3232802 | E19: 0.027649236 | F19: 6.5082967e-10 | G19: 1.035114e-08 | H19: 6.5082967e-10 | I19: 1.035114e-08

Sheet NOTLOG-NOTLOG
A1: SUMMARY OUTPUT = TOLLSHARE
A3: Regression Statistics
A4: Multiple R | B4: 0.52524528
A5: R Square | B5: 0.27588261
A6: Adjusted R Square | B6: 0.22865756
A7: Standard Error | B7: 0.063651315
A8: Observations | B8: 50
A10: ANOVA
B11: df | C11: SS | D11: MS | E11: F | F11: Significance F
A12: Regression | B12: 3 | C12: 0.071004836 | D12: 0.023668279 | E12: 5.8418704 | F12: 0.0018128071
A13: Residual | B13: 46 | C13: 0.18636853 | D13: 0.0040514899
A14: Total | B14: 49 | C14: 0.25737337
B16: Coefficients | C16: Standard Error | D16: t Stat | E16: P-value | F16: Lower 95% | G16: Upper 95% | H16: Lower 95.0% | I16: Upper 95.0%
A17: Intercept | B17: 0.060379361 | C17: 0.016619183 | D17: 3.6331125 | E17: 0.00070284463 | F17: 0.026926713 | G17: 0.093832009 | H17: 0.026926713 | I17: 0.093832009
A18: Land | B18: -5.5036323e-07 | C18: 2.7299915e-07 | D18: -2.0159888 | E18: 0.049663348 | F18: -1.0998815e-06 | G18: -8.4496983e-10 | H18: -1.0998815e-06 | I18: -8.4496983e-10
A19: Population | B19: 6.8127914e-09 | C19: 2.1458802e-09 | D19: 3.1748237 | E19: 0.0026747285 | F19: 2.4933626e-09 | G19: 1.113222e-08 | H19: 2.4933626e-09 | I19: 1.113222e-08
A20: (Miles ) | B20: -2.8583114e-07 | C20: 3.1061193e-07 | D20: -0.92021945 | E20: 0.36225889 | F20: -9.1105993e-07 | G20: 3.3939765e-07 | H20: -9.1105993e-07 | I20: 3.3939765e-07

Sheet LOG-LOG
A1: SUMMARY OUTPUT = LOG(TOLLSHARE+1)
A3: Regression Statistics
A4: Multiple R | B4: 0.43702648
A5: R Square | B5: 0.19099214
A6: Adjusted R Square | B6: 0.13823076
A7: Standard Error | B7: 0.05989135
A8: Observations | B8: 50
A10: ANOVA
B11: df | C11: SS | D11: MS | E11: F | F11: Significance F
A12: Regression | B12: 3 | C12: 0.038953708 | D12: 0.012984569 | E12: 3.6199231 | F12: 0.019860649
A13: Residual | B13: 46 | C13: 0.1650008 | D13: 0.0035869738
A14: Total | B14: 49 | C14: 0.2039545
B16: Coefficients | C16: Standard Error | D16: t Stat | E16: P-value | F16: Lower 95% | G16: Upper 95% | H16: Lower 95.0% | I16: Upper 95.0%
A17: Intercept | B17: -0.13536874 | C17: 0.12818269 | D17: -1.056061 | E17: 0.29645534 | F17: -0.39338688 | G17: 0.12264939 | H17: -0.39338688 | I17: 0.12264939
A18: Log(Land) | B18: -0.010065957 | C18: 0.014199601 | D18: -0.70889014 | E18: 0.48197008 | F18: -0.038648243 | G18: 0.018516329 | H18: -0.038648243 | I18: 0.018516329
A19: Log(Pop) | B19: 0.028572082 | C19: 0.012859039 | D19: 2.2219454 | E19: 0.031246069 | F19: 0.0026882042 | G19: 0.054455959 | H19: 0.0026882042 | I19: 0.054455959
A20: Log(Miles) | B20: -0.013657511 | C20: 0.024184801 | D20: -0.56471462 | E20: 0.57501158 | F20: -0.062338945 | G20: 0.035023923 | H20: -0.062338945 | I20: 0.035023923

Sheet LOG-NOTLOG
A1: SUMMARY OUTPUT = LOG(TOLLSHARE+1)
A3: Regression Statistics
A4: Multiple R | B4: 0.53002648
A5: R Square | B5: 0.28092807
A6: Adjusted R Square | B6: 0.23403207
A7: Standard Error | B7: 0.056464294
A8: Observations | B8: 50
A10: ANOVA
B11: df | C11: SS | D11: MS | E11: F | F11: Significance F
A12: Regression | B12: 3 | C12: 0.057296545 | D12: 0.019098848 | E12: 5.990449 | F12: 0.0015557225
A13: Residual | B13: 46 | C13: 0.14665796 | D13: 0.0031882165
A14: Total | B14: 49 | C14: 0.2039545
B16: Coefficients | C16: Standard Error | D16: t Stat | E16: P-value | F16: Lower 95% | G16: Upper 95% | H16: Lower 95.0% | I16: Upper 95.0%
A17: Intercept | B17: 0.055374647 | C17: 0.014742671 | D17: 3.7560796 | E17: 0.00048430801 | F17: 0.025699217 | G17: 0.085050077 | H17: 0.025699217 | I17: 0.085050077
A18: Land | B18: -5.0618435e-07 | C18: 2.4217417e-07 | D18: -2.0901666 | E18: 0.042158531 | F18: -9.9365521e-07 | G18: -1.87135e-08 | H18: -9.9365521e-07 | I18: -1.87135e-08
A19: Population | B19: 6.0565939e-09 | C19: 1.9035838e-09 | D19: 3.1816797 | E19: 0.0026234891 | F19: 2.2248821e-09 | G19: 9.8883058e-09 | H19: 2.2248821e-09 | I19: 9.8883058e-09
A20: (Miles ) | B20: -2.4248485e-07 | C20: 2.7554e-07 | D20: -0.88003502 | E20: 0.38341494 | F20: -7.9711758e-07 | G20: 3.1214788e-07 | H20: -7.9711758e-07 | I20: 3.1214788e-07

Sheet NOTLOG-LOG
A1: SUMMARY OUTPUT = TOLLSHARE
A3: Regression Statistics
A4: Multiple R | B4: 0.43070297
A5: R Square | B5: 0.18550505
A6: Adjusted R Square | B6: 0.13238581
A7: Standard Error | B7: 0.067506732
A8: Observations | B8: 50
A10: ANOVA
B11: df | C11: SS | D11: MS | E11: F | F11: Significance F
A12: Regression | B12: 3 | C12: 0.04774406 | D12: 0.015914687 | E12: 3.4922387 | F12: 0.022925023
A13: Residual | B13: 46 | C13: 0.20962931 | D13: 0.0045571589
A14: Total | B14: 49 | C14: 0.25737337
B16: Coefficients | C16: Standard Error | D16: t Stat | E16: P-value | F16: Lower 95% | G16: Upper 95% | H16: Lower 95.0% | I16: Upper 95.0%
A17: Intercept | B17: -0.14970517 | C17: 0.14448154 | D17: -1.0361543 | E17: 0.30554661 | F17: -0.44053116 | G17: 0.14112082 | H17: -0.44053116 | I17: 0.14112082
A18: Log(Land) | B18: -0.011001857 | C18: 0.016005127 | D18: -0.68739581 | E18: 0.49528472 | F18: -0.043218475 | G18: 0.021214761 | H18: -0.043218475 | I18: 0.021214761
A19: Log(Pop) | B19: 0.031678732 | C19: 0.014494108 | D19: 2.1856283 | E19: 0.033971306 | F19: 0.0025036342 | G19: 0.06085383 | H19: 0.0025036342 | I19: 0.06085383
A20: Log(Miles) | B20: -0.015437662 | C20: 0.027259978 | D20: -0.56631234 | E20: 0.57393419 | F20: -0.0703091 | G20: 0.039433776 | H20: -0.0703091 | I20: 0.039433776

Sheet LOG-NL=f(L,P,O)
A1: SUMMARY OUTPUT=LOG(TOLLSHARE)
A3: Regression Statistics
A4: Multiple R | B4: 0.57832753
A5: R Square | B5: 0.33446273
A6: Adjusted R Square | B6: 0.29009358
A7: Standard Error | B7: 0.054721227
A8: Observations | B8: 49
A10: ANOVA
B11: df | C11: SS | D11: MS | E11: F | F11: Significance F
A12: Regression | B12: 3 | C12: 0.067717281 | D12: 0.022572427 | E12: 7.5381818 | F12: 0.00034402839
A13: Residual | B13: 45 | C13: 0.13474857 | D13: 0.0029944126
A14: Total | B14: 48 | C14: 0.20246585
B16: Coefficients | C16: Standard Error | D16: t Stat | E16: P-value | F16: Lower 95% | G16: Upper 95% | H16: Lower 95.0% | I16: Upper 95.0%
A17: Intercept | B17: -0.037036339 | C17: 0.048108705 | D17: -0.76984693 | E17: 0.44541332 | F17: -0.13393224 | G17: 0.059859563 | H17: -0.13393224 | I17: 0.059859563
A18: Land | B18: -3.9473742e-07 | C18: 2.2906913e-07 | D18: -1.723224 | E18: 0.091713944 | F18: -8.5610631e-07 | G18: 6.6631465e-08 | H18: -8.5610631e-07 | I18: 6.6631465e-08
A19: Population | B19: 5.5368747e-09 | C19: 1.4927896e-09 | D19: 3.7090792 | E19: 0.00056917187 | F19: 2.5302423e-09 | G19: 8.5435071e-09 | H19: 2.5302423e-09 | I19: 8.5435071e-09
A20: Out of State Visitors | B20: 0.11494298 | C20: 0.058845997 | D20: 1.9532846 | E20: 0.057020591 | F20: -0.0035789366 | G20: 0.2334649 | H20: -0.0035789366 | I20: 0.2334649

Sheet LOG-NL=f(L,P,O,O')
A1: SUMMARY OUTPUT DEP=LOG(TOLLSHARE)
A3: Regression Statistics
A4: Multiple R | B4: 0.58777682
A5: R Square | B5: 0.34548159
A6: Adjusted R Square | B6: 0.28597992
A7: Standard Error | B7: 0.054879543
A8: Observations | B8: 49
A10: ANOVA
B11: df | C11: SS | D11: MS | E11: F | F11: Significance F
A12: Regression | B12: 4 | C12: 0.069948225 | D12: 0.017487056 | E12: 5.8062501 | F12: 0.00076702496
A13: Residual | B13: 44 | C13: 0.13251763 | D13: 0.0030117642
A14: Total | B14: 48 | C14: 0.20246585
B16: Coefficients | C16: Standard Error | D16: t Stat | E16: P-value | F16: Lower 95% | G16: Upper 95% | H16: Lower 95.0% | I16: Upper 95.0%
A17: Intercept | B17: -0.048123306 | C17: 0.049937976 | D17: -0.96366151 | E17: 0.34048224 | F17: -0.14876668 | G17: 0.052520069 | H17: -0.14876668 | I17: 0.052520069
A18: Land | B18: -3.618394e-07 | C18: 2.328901e-07 | D18: -1.5536917 | E18: 0.12742211 | F18: -8.3119854e-07 | G18: 1.0751973e-07 | H18: -8.3119854e-07 | I18: 1.0751973e-07
A19: Population | B19: 5.3266576e-09 | C19: 1.516902e-09 | D19: 3.5115371 | E19: 0.0010427503 | F19: 2.2695427e-09 | G19: 8.3837725e-09 | H19: 2.2695427e-09 | I19: 8.3837725e-09
A20: Out of State Visitors | B20: 0.043732698 | C20: 0.1016298 | D20: 0.43031374 | E20: 0.66906788 | F20: -0.16108869 | G20: 0.24855409 | H20: -0.16108869 | I20: 0.24855409
A21: Residents Out-of-State Trips | B21: 0.08954556 | C21: 0.10404237 | D21: 0.86066439 | E21: 0.39408866 | F21: -0.12013804 | G21: 0.29922916 | H21: -0.12013804 | I21: 0.29922916

Sheet NL-NL=f(L,P,O,J)
A1: SUMMARY OUTPUT DEP=(TOLLSHARE)
A3: Regression Statistics
A4: Multiple R | B4: 0.61208541
A5: R Square | B5: 0.37464854
A6: Adjusted R Square | B6: 0.31779841
A7: Standard Error | B7: 0.060277301
A8: Observations | B8: 49
A10: ANOVA
B11: df | C11: SS | D11: MS | E11: F | F11: Significance F
A12: Regression | B12: 4 | C12: 0.095776764 | D12: 0.023944191 | E12: 6.5901086 | F12: 0.00030235015
A13: Residual | B13: 44 | C13: 0.15986753 | D13: 0.003633353
A14: Total | B14: 48 | C14: 0.2556443
B16: Coefficients | C16: Standard Error | D16: t Stat | E16: P-value | F16: Lower 95% | G16: Upper 95% | H16: Lower 95.0% | I16: Upper 95.0%
A17: Intercept | B17: -0.051365023 | C17: 0.053171063 | D17: -0.96603341 | E17: 0.3393074 | F17: -0.15852425 | G17: 0.055794209 | H17: -0.15852425 | I17: 0.055794209
A18: Land | B18: -3.0042324e-07 | C18: 2.6253547e-07 | D18: -1.1443149 | E18: 0.25868016 | F18: -8.2952869e-07 | G18: 2.2868221e-07 | H18: -8.2952869e-07 | I18: 2.2868221e-07
A19: Population | B19: 6.1151379e-09 | C19: 1.6446592e-09 | D19: 3.7181793 | E19: 0.00056455578 | F19: 2.8005452e-09 | G19: 9.4297307e-09 | H19: 2.8005452e-09 | I19: 9.4297307e-09
A20: Out of State Visitors | B20: 0.092976745 | C20: 0.06767362 | D20: 1.3738994 | E20: 0.17643211 | F20: -0.04341047 | G20: 0.22936396 | H20: -0.04341047 | I20: 0.22936396
A21: JTW-OOSRATIO | B21: 0.51157019 | C21: 0.27945719 | D21: 1.8305851 | E21: 0.073940601 | F21: -0.051638758 | G21: 1.0747791 | H21: -0.051638758 | I21: 1.0747791

Sheet LOG-NL=f(L,P,O,J)
A1: SUMMARY OUTPUT DEP=LOG(TOLLSHARE)
A3: Regression Statistics
A4: Multiple R | B4: 0.62304808
A5: R Square | B5: 0.38818891
A6: Adjusted R Square | B6: 0.33256972
A7: Standard Error | B7: 0.053058898
A8: Observations | B8: 49
A10: ANOVA
B11: df | C11: SS | D11: MS | E11: F | F11: Significance F
A12: Regression | B12: 4 | C12: 0.078594997 | D12: 0.019648749 | E12: 6.9794059 | F12: 0.00019281336
A13: Residual | B13: 44 | C13: 0.12387085 | D13: 0.0028152467
A14: Total | B14: 48 | C14: 0.20246585
B16: Coefficients | C16: Standard Error | D16: t Stat | E16: P-value | F16: Lower 95% | G16: Upper 95% | H16: Lower 95.0% | I16: Upper 95.0%
A17: Intercept | B17: -0.044551253 | C17: 0.046803655 | D17: -0.95187552 | E17: 0.34636001 | F17: -0.13887782 | G17: 0.049775312 | H17: -0.13887782 | I17: 0.049775312
A18: Land | B18: -2.6929885e-07 | C18: 2.3109599e-07 | D18: -1.1653116 | E18: 0.25017153 | F18: -7.3504219e-07 | G18: 1.964445e-07 | H18: -7.3504219e-07 | I18: 1.964445e-07
A19: Population | B19: 5.4824786e-09 | C19: 1.4477059e-09 | D19: 3.7870112 | E19: 0.00045870171 | F19: 2.5648191e-09 | G19: 8.4001381e-09 | H19: 2.5648191e-09 | I19: 8.4001381e-09
A20: Out of State Visitors | B20: 0.081303803 | C20: 0.059569484 | D20: 1.3648566 | E20: 0.17923728 | F20: -0.038750599 | G20: 0.2013582 | H20: -0.038750599 | I20: 0.2013582
A21: JTW-OOSRATIO | B21: 0.48353771 | C21: 0.24599128 | D21: 1.9656701 | E21: 0.055667483 | F21: -0.01222513 | G21: 0.97930055 | H21: -0.01222513 | I21: 0.97930055

Sheet LOG-NL=f(P,O,J)
A1: SUMMARY OUTPUT DEP=LOG(TOLLSHARE)
A3: Regression Statistics
A4: Multiple R | B4: 0.60770624
A5: R Square | B5: 0.36930687
A6: Adjusted R Square | B6: 0.32726066
A7: Standard Error | B7: 0.053269508
A8: Observations | B8: 49
A10: ANOVA
B11: df | C11: SS | D11: MS | E11: F | F11: Significance F
A12: Regression | B12: 3 | C12: 0.074772029 | D12: 0.02492401 | E12: 8.7833572 | F12: 0.00010722492
A13: Residual | B13: 45 | C13: 0.12769382 | D13: 0.0028376405
A14: Total | B14: 48 | C14: 0.20246585
B16: Coefficients | C16: Standard Error | D16: t Stat | E16: P-value | F16: Lower 95% | G16: Upper 95% | H16: Lower 95.0% | I16: Upper 95.0%
A17: Intercept | B17: -0.083768024 | C17: 0.032656433 | D17: -2.5651309 | E17: 0.013718193 | F17: -0.14954145 | G17: -0.017994595 | H17: -0.14954145 | I17: -0.017994595
A18: Population | B18: 5.231133e-09 | C18: 1.4372306e-09 | D18: 3.6397312 | E18: 0.0007011007 | F18: 2.3364021e-09 | G18: 8.1258639e-09 | H18: 2.3364021e-09 | I18: 8.1258639e-09
A19: Out of State Visitors | B19: 0.11537827 | C19: 0.052105024 | D19: 2.2143406 | E19: 0.031913523 | F19: 0.010433367 | G19: 0.22032317 | H19: 0.010433367 | I19: 0.22032317
A20: JTW-OOSRATIO | B20: 0.56269481 | C20: 0.23736503 | D20: 2.3705885 | E20: 0.022103944 | F20: 0.084617125 | G20: 1.0407725 | H20: 0.084617125 | I20: 1.0407725

Sheet LAND=f(P,O,J)
A1: SUMMARY OUTPUT | C1: DEP=LAND
A3: Regression Statistics
A4: Multiple R | B4: 0.70905336
A5: R Square | B5: 0.50275667
A6: Adjusted R Square | B6: 0.46960711
A7: Standard Error | B7: 34226.269
A8: Observations | B8: 49
A10: ANOVA
B11: df | C11: SS | D11: MS | E11: F | F11: Significance F
A12: Regression | B12: 3 | C12: 5.3299177e+10 | D12: 1.7766392e+10 | E12: 15.166317 | F12: 5.8618249e-07
A13: Residual | B13: 45 | C13: 5.2714687e+10 | D13: 1.1714375e+09
A14: Total | B14: 48 | C14: 1.0601386e+11
B16: Coefficients | C16: Standard Error | D16: t Stat | E16: P-value | F16: Lower 95% | G16: Upper 95% | H16: Lower 95.0% | I16: Upper 95.0%
A17: Intercept | B17: 145625.47 | C17: 20982.132 | D17: 6.9404515 | E17: 1.2488141e-08 | F17: 103365.29 | G17: 187885.65 | H17: 103365.29 | I17: 187885.65
A18: Population | B18: 0.00093333345 | C18: 0.00092343712 | D18: 1.0107168 | E18: 0.31755591 | F18: -0.0009265643 | G18: 0.0027932312 | H18: -0.0009265643 | I18: 0.0027932312
A19: Out of State Visitors | B19: -126530.3 | C19: 33478.074 | D19: -3.7794976 | E19: 0.00045980175 | F19: -193958.6 | G19: -59102.002 | H19: -193958.6 | I19: -59102.002
A20: JTW-OOSRATIO | B20: -293937.76 | C20: 152509.75 | D20: -1.9273375 | E20: 0.060264622 | F20: -601108.15 | G20: 13232.625 | H20: -601108.15 | I20: 13232.625

Sheet LOG-NL-f(P,O,J,Neigh)
A1: SUMMARY OUTPUT
A3: Regression Statistics
A4: Multiple R | B4: 0.61564034
A5: R Square | B5: 0.37901302
A6: Adjusted R Square | B6: 0.32255966
A7: Standard Error | B7: 0.053455303
A8: Observations | B8: 49
A10: ANOVA
B11: df | C11: SS | D11: MS | E11: F | F11: Significance F
A12: Regression | B12: 4 | C12: 0.076737194 | D12: 0.019184299 | E12: 6.7137371 | F12: 0.00026186774
A13: Residual | B13: 44 | C13: 0.12572866 | D13: 0.0028574694
A14: Total | B14: 48 | C14: 0.20246585
B16: Coefficients | C16: Standard Error | D16: t Stat | E16: P-value | F16: Lower 95% | G16: Upper 95% | H16: Lower 95.0% | I16: Upper 95.0%
A17: Intercept | B17: -0.073043671 | C17: 0.035229658 | D17: -2.0733573 | E17: 0.044025531 | F17: -0.14404438 | G17: -0.0020429618 | H17: -0.14404438 | I17: -0.0020429618
A18: Population | B18: 4.3473785e-09 | C18: 1.7932428e-09 | D18: 2.4243112 | E18: 0.019513824 | F18: 7.3333526e-10 | G18: 7.9614217e-09 | H18: 7.3333526e-10 | I18: 7.9614217e-09
A19: Out of State Visitors | B19: 0.094089328 | C19: 0.058248716 | D19: 1.615303 | E19: 0.11339411 | F19: -0.023303241 | G19: 0.2114819 | H19: -0.023303241 | I19: 0.2114819
A20: JTW-OOSRATIO | B20: 0.57005613 | C20: 0.23835826 | D20: 2.3915938 | E20: 0.021115966 | F20: 0.08967664 | G20: 1.0504356 | H20: 0.08967664 | I20: 1.0504356
A21: Neighbor | B21: 0.087477707 | C21: 0.10548451 | D21: 0.82929436 | E21: 0.41141438 | F21: -0.12511234 | G21: 0.30006776 | H21: -0.12511234 | I21: 0.30006776

Sheet LOG-NL-f(P,Ov,Ow,Ro)
A1: SUMMARY OUTPUT
A3: Regression Statistics
A4: Multiple R | B4: 0.66672354
A5: R Square | B5: 0.44452028
A6: Adjusted R Square | B6: 0.39402212
A7: Standard Error | B7: 0.050557275
A8: Observations | B8: 49
A10: ANOVA
B11: df | C11: SS | D11: MS | E11: F | F11: Significance F
A12: Regression | B12: 4 | C12: 0.090000176 | D12: 0.022500044 | E12: 8.8027032 | F12: 2.6019384e-05
A13: Residual | B13: 44 | C13: 0.11246567 | D13: 0.002556038
A14: Total | B14: 48 | C14: 0.20246585
B16: Coefficients | C16: Standard Error | D16: t Stat | E16: P-value | F16: Lower 95% | G16: Upper 95% | H16: Lower 95.0% | I16: Upper 95.0%
A17: Intercept | B17: -0.079348132 | C17: 0.030949124 | D17: -2.5638248 | E17: 0.013844973 | F17: -0.14172199 | G17: -0.016974273 | H17: -0.14172199 | I17: -0.016974273
A18: Population | B18: 5.3836885e-09 | C18: 1.3654139e-09 | D18: 3.9428987 | E18: 0.00028502217 | F18: 2.6318778e-09 | G18: 8.1354992e-09 | H18: 2.6318778e-09 | I18: 8.1354992e-09
A19: Out of State Visitors - ATS | B19: 0.073414122 | C19: 0.05210132 | D19: 1.4090645 | E19: 0.1658445 | F19: -0.031589186 | G19: 0.17841743 | H19: -0.031589186 | I19: 0.17841743
A20: Workers Who Live OOS (JTW) | B20: 1.0552674 | C20: 0.45852086 | D20: 2.30146 | E20: 0.026159921 | F20: 0.1311794 | G20: 1.9793555 | H20: 0.1311794 | I20: 1.9793555
A21: Residents Who Work OOS - JTW | B21: 0.12568122 | C21: 0.2944636 | D21: 0.42681413 | E21: 0.67159595 | F21: -0.46777114 | G21: 0.71913359 | H21: -0.46777114 | I21: 0.71913359

Sheet LOG-NL-f(P,Ow)
A1: SUMMARY OUTPUT
A3: Regression Statistics
A4: Multiple R | B4: 0.64488023
A5: R Square | B5: 0.41587051
A6: Adjusted R Square | B6: 0.39047357
A7: Standard Error | B7: 0.050705088
A8: Observations | B8: 49
A10: ANOVA
B11: df | C11: SS | D11: MS | E11: F | F11: Significance F
A12: Regression | B12: 2 | C12: 0.084199576 | D12: 0.042099788 | E12: 16.374831 | F12: 4.2629483e-06
A13: Residual | B13: 46 | C13: 0.11826627 | D13: 0.002571006
A14: Total | B14: 48 | C14: 0.20246585
B16: Coefficients | C16: Standard Error | D16: t Stat | E16: P-value | F16: Lower 95% | G16: Upper 95% | H16: Lower 95.0% | I16: Upper 95.0%
A17: Intercept | B17: -0.041368367 | C17: 0.01583121 | D17: -2.6130895 | E17: 0.012083475 | F17: -0.07323491 | G17: -0.0095018253 | H17: -0.07323491 | I17: -0.0095018253
A18: Population | B18: 4.8138207e-09 | C18: 1.3130456e-09 | D18: 3.6661489 | E18: 0.00063626459 | F18: 2.1707995e-09 | G18: 7.4568419e-09 | H18: 2.1707995e-09 | I18: 7.4568419e-09
A19: Workers Who Live OOS (JTW) | B19: 1.4673608 | C19: 0.28182092 | D19: 5.2067136 | E19: 4.379022e-06 | F19: 0.90008527 | G19: 2.0346364 | H19: 0.90008527 | I19: 2.0346364

Sheet LOG-NL-f(D,Ow)
A1: SUMMARY OUTPUT
A3: Regression Statistics
A4: Multiple R | B4: 0.61969375
A5: R Square | B5: 0.38402034
A6: Adjusted R Square | B6: 0.35723861
A7: Standard Error | B7: 0.052069111
A8: Observations | B8: 49
A10: ANOVA
B11: df | C11: SS | D11: MS | E11: F | F11: Significance F
A12: Regression | B12: 2 | C12: 0.077751004 | D12: 0.038875502 | E12: 14.338895 | F12: 1.4455282e-05
A13: Residual | B13: 46 | C13: 0.12471485 | D13: 0.0027111923
A14: Total | B14: 48 | C14: 0.20246585
B16: Coefficients | C16: Standard Error | D16: t Stat | E16: P-value | F16: Lower 95% | G16: Upper 95% | H16: Lower 95.0% | I16: Upper 95.0%
A17: Intercept | B17: -0.010652988 | C17: 0.012881278 | D17: -0.82701323 | E17: 0.41249914 | F17: -0.036581631 | G17: 0.015275656 | H17: -0.036581631 | I17: 0.015275656
A18: Density | B18: 0.00011010313 | C18: 3.4195534e-05 | D18: 3.2198102 | E18: 0.0023550126 | F18: 4.1271156e-05 | G18: 0.0001789351 | H18: 4.1271156e-05 | I18: 0.0001789351
A19: Workers Who Live OOS (JTW) | B19: 0.81456094 | C19: 0.30302 | D19: 2.6881425 | E19: 0.0099709095 | F19: 0.20461391 | G19: 1.424508 | H19: 0.20461391 | I19: 1.424508

Sheet LOG-NL-f(D,P,Ow)
A1: SUMMARY OUTPUT
A3: Regression Statistics
A4: Multiple R | B4: 0.69321191
A5: R Square | B5: 0.48054275
A6: Adjusted R Square | B6: 0.44591226
A7: Standard Error | B7: 0.048344218
A8: Observations | B8: 49
A10: ANOVA
B11: df | C11: SS | D11: MS | E11: F | F11: Significance F
A12: Regression | B12: 3 | C12: 0.097293495 | D12: 0.032431165 | E12: 13.876293 | F12: 1.5349295e-06
A13: Residual | B13: 45 | C13: 0.10517235 | D13: 0.0023371634
A14: Total | B14: 48 | C14: 0.20246585
B16: Coefficients | C16: Standard Error | D16: t Stat | E16: P-value | F16: Lower 95% | G16: Upper 95% | H16: Lower 95.0% | I16: Upper 95.0%
A17: Intercept | B17: -0.037662652 | C17: 0.015175073 | D17: -2.4818762 | E17: 0.016869097 | F17: -0.068226817 | G17: -0.0070984873 | H17: -0.068226817 | I17: -0.0070984873
A18: Density | B18: 7.9273204e-05 | C18: 3.3491617e-05 | D18: 2.3669566 | E18: 0.022297099 | F18: 1.1817627e-05 | G18: 0.00014672878 | H18: 1.1817627e-05 | I18: 0.00014672878
A19: Population | B19: 3.8187444e-09 | C19: 1.3206118e-09 | D19: 2.891648 | E19: 0.005882994 | F19: 1.1588958e-09 | G19: 6.4785929e-09 | H19: 1.1588958e-09 | I19: 6.4785929e-09
A20: Workers Who Live OOS (JTW) | B20: 1.1374718 | C20: 0.30269448 | D20: 3.7578213 | E20: 0.00049110568 | F20: 0.52781383 | G20: 1.7471297 | H20: 0.52781383 | I20: 1.7471297

Sheet LOG-NL-f(D,P,Ow,Ov)
A1: SUMMARY OUTPUT
A3: Regression Statistics
A4: Multiple R | B4: 0.6941583
A5: R Square | B5: 0.48185574
A6: Adjusted R Square | B6: 0.43475172
A7: Standard Error | B7: 0.04882867
A8: Observations | B8: 49
A10: ANOVA
B11: df | C11: SS | D11: MS | E11: F | F11: Significance F
A12: Regression | B12: 4 | C12: 0.097559332 | D12: 0.024389833 | E12: 10.229609 | F12: 6.0590444e-06
A13: Residual | B13: 44 | C13: 0.10490652 | D13: 0.002384239
A14: Total | B14: 48 | C14: 0.20246585
B16: Coefficients | C16: Standard Error | D16: t Stat | E16: P-value | F16: Lower 95% | G16: Upper 95% | H16: Lower 95.0% | I16: Upper 95.0%
A17: Intercept | B17: -0.047997591 | C17: 0.034538227 | D17: -1.3896947 | E17: 0.17161361 | F17: -0.11760481 | G17: 0.021609628 | H17: -0.11760481 | I17: 0.021609628
A18: Density | B18: 7.246396e-05 | C18: 3.9498457e-05 | D18: 1.8346023 | E18: 0.073331566 | F18: -7.1399471e-06 | G18: 0.00015206787 | H18: -7.1399471e-06 | I18: 0.00015206787
A19: Population | B19: 4.0498836e-09 | C19: 1.5027661e-09 | D19: 2.6949527 | E19: 0.0099315742 | F19: 1.0212576e-09 | G19: 7.0785096e-09 | H19: 1.0212576e-09 | I19: 7.0785096e-09
A20: Workers Who Live OOS (JTW) | B20: 1.0923672 | C20: 0.33423923 | D20: 3.2682194 | E20: 0.0021040148 | F20: 0.41875227 | G20: 1.765982 | H20: 0.41875227 | I20: 1.765982
A21: Out of State Visitors - ATS | B21: 0.019565337 | C21: 0.058594235 | D21: 0.33391232 | E21: 0.74003199 | F21: -0.09852358 | G21: 0.13765425 | H21: -0.09852358 | I21: 0.13765425

Sheet LOG-NL-f(D,P,Ow,Ro)
A1: SUMMARY OUTPUT
A3: Regression Statistics
A4: Multiple R | B4: 0.69339961
A5: R Square | B5: 0.48080302
A6: Adjusted R Square | B6: 0.4336033
A7: Standard Error | B7: 0.048878248
A8: Observations | B8: 49
A10: ANOVA
B11: df | C11: SS | D11: MS | E11: F | F11: Significance F
A12: Regression | B12: 4 | C12: 0.097346192 | D12: 0.024336548 | E12: 10.186564 | F12: 6.3230773e-06
A13: Residual | B13: 44 | C13: 0.10511966 | D13: 0.0023890831
A14: Total | B14: 48 | C14: 0.20246585
B16: Coefficients | C16: Standard Error | D16: t Stat | E16: P-value | F16: Lower 95% | G16: Upper 95% | H16: Lower 95.0% | I16: Upper 95.0%
A17: Intercept | B17: -0.037451132 | C17: 0.015408664 | D17: -2.4305242 | E17: 0.019222282 | F17: -0.068505253 | G17: -0.0063970105 | H17: -0.068505253 | I17: -0.0063970105
A18: Density | B18: 8.0831709e-05 | C18: 3.5450329e-05 | D18: 2.2801399 | E18: 0.027500464 | F18: 9.3862695e-06 | G18: 0.00015227715 | H18: 9.3862695e-06 | I18: 0.00015227715
A19: Population | B19: 3.7910009e-09 | C19: 1.3482039e-09 | D19: 2.8118899 | E19: 0.0073296023 | F19: 1.0738746e-09 | G19: 6.5081273e-09 | H19: 1.0738746e-09 | I19: 6.5081273e-09
A20: Workers Who Live OOS (JTW) | B20: 1.178937 | C20: 0.41425746 | D20: 2.8459042 | E20: 0.006701026 | F20: 0.34405603 | G20: 2.0138181 | H20: 0.34405603 | I20: 2.0138181
A21: Residents Who Work OOS - JTW | B21: -0.044142266 | C21: 0.29721992 | D21: -0.14851719 | E21: 0.8826132 | F21: -0.64314962 | G21: 0.55486509 | H21: -0.64314962 | I21: 0.55486509

Sheet Log-NL-f(D,P,Ow,Ro,Ov,Nj)
A1: SUMMARY OUTPUT
A3: Regression Statistics
A4: Multiple R | B4: 0.74475203
A5: R Square | B5: 0.55465559
A6: Adjusted R Square | B6: 0.49103496
A7: Standard Error | B7: 0.046333942
A8: Observations | B8: 49
A10: ANOVA
B11: df | C11: SS | D11: MS | E11: F | F11: Significance F
A12: Regression | B12: 6 | C12: 0.11229881 | D12: 0.018716469 | E12: 8.7181718 | F12: 3.5108352e-06
A13: Residual | B13: 42 | C13: 0.090167035 | D13: 0.0021468342
A14: Total | B14: 48 | C14: 0.20246585
B16: Coefficients | C16: Standard Error | D16: t Stat | E16: P-value | F16: Lower 95% | G16: Upper 95% | H16: Lower 95.0% | I16: Upper 95.0%
A17: Intercept | B17: -0.02904958 | C17: 0.033823018 | D17: -0.85887013 | E17: 0.39528762 | F17: -0.097307214 | G17: 0.039208055 | H17: -0.097307214 | I17: 0.039208055
A18: Density | B18: 1.8545931e-05 | C18: 4.459039e-05 | D18: 0.41591766 | E18: 0.67958784 | F18: -7.1441147e-05 | G18: 0.00010853301 | H18: -7.1441147e-05 | I18: 0.00010853301
A19: Population | B19: 3.8687293e-09 | C19: 1.4538804e-09 | D19: 2.660968 | E19: 0.010989171 | F19: 9.3467889e-10 | G19: 6.8027798e-09 | H19: 9.3467889e-10 | I19: 6.8027798e-09
A20: Workers Who Live OOS (JTW) | B20: 1.1162651 | C20: 0.42140516 | D20: 2.6489119 | E20: 0.011329534 | F20: 0.26583483 | G20: 1.9666954 | H20: 0.26583483 | I20: 1.9666954
A21: Residents Who Work OOS - JTW | B21: -0.32908195 | C21: 0.30259918 | D21: -1.0875176 | E21: 0.28300983 | F21: -0.93975202 | G21: 0.28158812 | H21: -0.93975202 | I21: 0.28158812
A22: Out of State Visitors - ATS | B22: -0.0037189413 | C22: 0.056512721 | D22: -0.065807154 | E22: 0.94784361 | F22: -0.11776627 | G22: 0.11032838 | H22: -0.11776627 | I22: 0.11032838
A23: Neighbors-JTW | B23: 5.4318737 | C23: 2.0359046 | D23: 2.6680395 | E23: 0.010793936 | F23: 1.3232507 | G23: 9.5404967 | H23: 1.3232507 | I23: 9.5404967

Sheet L-NL-f(D,P,Ow,Rw,Ov,Nj,Lf)
A1: SUMMARY OUTPUT
A3: Regression Statistics
A4: Multiple R | B4: 0.74868186
A5: R Square | B5: 0.56052453
A6: Adjusted R Square | B6: 0.48549214
A7: Standard Error | B7: 0.046585556
A8: Observations | B8: 49
A10: ANOVA
B11: df | C11: SS | D11: MS | E11: F | F11: Significance F
A12: Regression | B12: 7 | C12: 0.11348708 | D12: 0.016212439 | E12: 7.4704335 | F12: 8.6642401e-06
A13: Residual | B13: 41 | C13: 0.088978774 | D13: 0.002170214
A14: Total | B14: 48 | C14: 0.20246585
B16: Coefficients | C16: Standard Error | D16: t Stat | E16: P-value | F16: Lower 95% | G16: Upper 95% | H16: Lower 95.0% | I16: Upper 95.0%
A17: Intercept | B17: -0.026296431 | C17: 0.034209629 | D17: -0.76868508 | E17: 0.44648571 | F17: -0.095384216 | G17: 0.042791354 | H17: -0.095384216 | I17: 0.042791354
A18: Density | B18: 9.6398283e-06 | C18: 4.6420061e-05 | D18: 0.20766514 | E18: 0.83651851 | F18: -8.4107437e-05 | G18: 0.00010338709 | H18: -8.4107437e-05 | I18: 0.00010338709
A19: Population | B19: 3.8749615e-09 | C19: 1.4617999e-09 | D19: 2.6508152 | E19: 0.011359921 | F19: 9.2279506e-10 | G19: 6.827128e-09 | H19: 9.2279506e-10 | I19: 6.827128e-09
A20: Workers Who Live OOS (JTW) | B20: 1.0593974 | C20: 0.43060728 | D20: 2.4602404 | E20: 0.018187677 | F20: 0.18976791 | G20: 1.929027 | H20: 0.18976791 | I20: 1.929027
A21: Residents Who Work OOS - JTW | B21: -0.3466039 | C21: 0.30516256 | D21: -1.1358009 | E21: 0.26263578 | F21: -0.96289253 | G21: 0.26968473 | H21: -0.96289253 | I21: 0.26968473
A22: Out of State Visitors - ATS | B22: 0.0044704354 | C22: 0.05788744 | D22: 0.077226344 | E22: 0.93881913 | F22: -0.11243569 | G22: 0.12137656 | H22: -0.11243569 | I22: 0.12137656
A23: Neighbors-JTW | B23: 5.5563259 | C23: 2.0538584 | D23: 2.705311 | E23: 0.0098954408 | F23: 1.4084723 | G23: 9.7041794 | H23: 1.4084723 | I23: 9.7041794
A24: Percent Federal | B24: -0.028311512 | C24: 0.03826118 | D24: -0.73995397 | E24: 0.46354414 | F24: -0.10558158 | G24: 0.048958551 | H24: -0.10558158 | I24: 0.048958551

Sheet L-NL-f-(P,Ow,Ro,Nj,Lf)
A1: SUMMARY OUTPUT
A3: Regression Statistics
A4: Multiple R | B4: 0.74814738
A5: R Square | B5: 0.5597245
A6: Adjusted R Square | B6: 0.50852967
A7: Standard Error | B7: 0.045530658
A8: Observations | B8: 49
A10: ANOVA
B11: df | C11: SS | D11: MS | E11: F | F11: Significance F
A12: Regression | B12: 5 | C12: 0.1133251 | D12: 0.022665019 | E12: 10.933224 | F12: 7.8770322e-07
A13: Residual | B13: 43 | C13: 0.089140754 | D13: 0.0020730408
A14: Total | B14: 48 | C14: 0.20246585
B16: Coefficients | C16: Standard Error | D16: t Stat | E16: P-value | F16: Lower 95% | G16: Upper 95% | H16: Lower 95.0% | I16: Upper 95.0%
A17: Intercept | B17: -0.023586513 | C17: 0.017214247 | D17: -1.3701739 | E17: 0.17774436 | F17: -0.058302328 | G17: 0.011129302 | H17: -0.058302328 | I17: 0.011129302
A18: Population | B18: 3.9172032e-09 | C18: 1.2195433e-09 | D18: 3.2120246 | E18: 0.0024974218 | F18: 1.4577614e-09 | G18: 6.3766451e-09 | H18: 1.4577614e-09 | I18: 6.3766451e-09
A19: Workers Who Live OOS (JTW) | B19: 1.0758968 | C19: 0.38872897 | D19: 2.76773 | E19: 0.0082925499 | F19: 0.29195068 | G19: 1.859843 | H19: 0.29195068 | I19: 1.859843
A20: Residents Who Work OOS - JTW | B20: -0.34893738 | C20: 0.29570026 | D20: -1.1800374 | E20: 0.24447246 | F20: -0.94527338 | G20: 0.24739863 | H20: -0.94527338 | I20: 0.24739863
A21: Neighbors-JTW | B21: 5.8924428 | C21: 1.6062202 | D21: 3.6685149 | E21: 0.00066790363 | F21: 2.6531932 | G21: 9.1316924 | H21: 2.6531932 | I21: 9.1316924
A22: Percent Federal Land | B22: -0.029736997 | C22: 0.035946478 | D22: -0.82725758 | E22: 0.41265854 | F22: -0.10222993 | G22: 0.042755936 | H22: -0.10222993 | I22: 0.042755936

Sheet N-N-f(P,Ow,Ro,Nj,Lf)
A1: SUMMARY OUTPUT
A3: Regression Statistics
A4: Multiple R | B4: 0.74843093
A5: R Square | B5: 0.56014886
A6: Adjusted R Square | B6: 0.50900338
A7: Standard Error | B7: 0.05113717
A8: Observations | B8: 49
A10: ANOVA
B11: df | C11: SS | D11: MS | E11: F | F11: Significance F
A12: Regression | B12: 5 | C12: 0.14319886 | D12: 0.028639772 | E12: 10.952069 | F12: 7.7234931e-07
A13: Residual | B13: 43 | C13: 0.11244544 | D13: 0.0026150101
A14: Total | B14: 48 | C14: 0.2556443
B16: Coefficients | C16: Standard Error | D16: t Stat | E16: P-value | F16: Lower 95% | G16: Upper 95% | H16: Lower 95.0% | I16: Upper 95.0%
A17: Intercept | B17: -0.027846753 | C17: 0.01933396 | D17: -1.4403027 | E17: 0.15702362 | F17: -0.066837372 | G17: 0.011143865 | H17: -0.066837372 | I17: 0.011143865
A18: Population | B18: 4.3506032e-09 | C18: 1.3697144e-09 | D18: 3.176285 | E18: 0.0027595373 | F18: 1.5883129e-09 | G18: 7.1128936e-09 | H18: 1.5883129e-09 | I18: 7.1128936e-09
A19: Workers Who Live OOS (JTW) | B19: 1.2514925 | C19: 0.43659592 | D19: 2.8664777 | E19: 0.0064018293 | F19: 0.37101348 | G19: 2.1319715 | H19: 0.37101348 | I19: 2.1319715
A20: Residents Who Work OOS - JTW | B20: -0.45580694 | C20: 0.33211193 | D20: -1.3724498 | E20: 0.17704032 | F20: -1.125574 | G20: 0.21396013 | H20: -1.125574 | I20: 0.21396013
A21: Neighbors-JTW | B21: 6.8059469 | C21: 1.8040055 | D21: 3.7726863 | E21: 0.00048919416 | F21: 3.1678256 | G21: 10.444068 | H21: 3.1678256 | I21: 10.444068
A22: Percent Federal Land | B22: -0.031074295 | C22: 0.040372823 | D22: -0.76968348 | E22: 0.44569546 | F22: -0.1124938 | G22: 0.050345206 | H22: -0.1124938 | I22: 0.050345206

Sheet FINAL-1
A1: SUMMARY OUTPUT
A3: Regression Statistics
A4: Multiple R | B4: 0.80929777
A5: R Square | B5: 0.65496287
A6: Adjusted R Square | B6: 0.60567186
A7: Standard Error | B7: 0.045827517
A8: Observations | B8: 49
A10: ANOVA
B11: df | C11: SS | D11: MS | E11: F | F11: Significance F
A12: Regression | B12: 6 | C12: 0.16743752 | D12: 0.027906254 | E12: 13.287672 | F12: 2.2465024e-08
A13: Residual | B13: 42 | C13: 0.088206774 | D13: 0.0021001613
A14: Total | B14: 48 | C14: 0.2556443
B16: Coefficients | C16: Standard Error | D16: t Stat | E16: P-value | F16: Lower 95% | G16: Upper 95% | H16: Lower 95.0% | I16: Upper 95.0%
A17: Intercept | B17: -0.032232115 | C17: 0.017374503 | D17: -1.8551388 | E17: 0.070604392 | F17: -0.067295292 | G17: 0.0028310628 | H17: -0.067295292 | I17: 0.0028310628
A18: Population | B18: 3.6887339e-09 | C18: 1.2428596e-09 | D18: 2.9679409 | E18: 0.0049337146 | F18: 1.1805408e-09 | G18: 6.1969269e-09 | H18: 1.1805408e-09 | I18: 6.1969269e-09
A19: Workers Who Live OOS (JTW) | B19: 1.0094547 | C19: 0.39769709 | D19: 2.5382502 | E19: 0.014937372 | F19: 0.20686926 | G19: 1.8120402 | H19: 0.20686926 | I19: 1.8120402
A20: Residents Who Work OOS - JTW | B20: -0.35220966 | C20: 0.29918634 | D20: -1.1772251 | E20: 0.24573404 | F20: -0.95599234 | G20: 0.25157301 | H20: -0.95599234 | I20: 0.25157301
A21: Neighbors-JTW | B21: 3.0300498 | C21: 1.9618943 | D21: 1.5444511 | E21: 0.12998133 | F21: -0.92921434 | G21: 6.989314 | H21: -0.92921434 | I21: 6.989314
A22: Percent Federal Land | B22: -0.0011164502 | C22: 0.037239971 | D22: -0.029979889 | E22: 0.9762251 | F22: -0.076269777 | G22: 0.074036877 | H22: -0.076269777 | I22: 0.074036877
A23: OldTollMileRatio | B23: 0.28837827 | C23: 0.084885699 | D23: 3.3972539 | E23: 0.0014999034 | F23: 0.11707194 | G23: 0.4596846 | H23: 0.11707194 | I23: 0.4596846

Sheet Sheet3
A1: SUMMARY OUTPUT
A3: Regression Statistics
A4: Multiple R | B4: 0.8092932
A5: R Square | B5: 0.65495549
A6: Adjusted R Square | B6: 0.61483404
A7: Standard Error | B7: 0.045291988
A8: Observations | B8: 49
A10: ANOVA
B11: df | C11: SS | D11: MS | E11: F | F11: Significance F
A12: Regression | B12: 5 | C12: 0.16743564 | D12: 0.033487127 | E12: 16.324321 | F12: 5.1946687e-09
A13: Residual | B13: 43 | C13: 0.088208661 | D13: 0.0020513642
A14: Total | B14: 48 | C14: 0.2556443
B16: Coefficients | C16: Standard Error | D16: t Stat | E16: P-value | F16: Lower 95% | G16: Upper 95% | H16: Lower 95.0% | I16: Upper 95.0%
A17: Intercept | B17: -0.032508894 | C17: 0.014546723 | D17: -2.2347916 | E17: 0.030679435 | F17: -0.061845136 | G17: -0.0031726516 | H17: -0.061845136 | I17: -0.0031726516
A18: Population | B18: 3.6930513e-09 | C18: 1.2200621e-09 | D18: 3.0269371 | E18: 0.0041626729 | F18: 1.2325633e-09 | G18: 6.1535394e-09 | H18: 1.2325633e-09 | I18: 6.1535394e-09
A19: Workers Who Live OOS (JTW) | B19: 1.010389 | C19: 0.39184127 | D19: 2.578567 | E19: 0.013427768 | F19: 0.22016627 | G19: 1.8006117 | H19: 0.22016627 | I19: 1.8006117
A20: Neighbors-JTW | B20: 3.0225883 | C20: 1.9233024 | D20: 1.5715616 | E20: 0.1233824 | F20: -0.85611811 | G20: 6.9012946 | H20: -0.85611811 | I20: 6.9012946
A21: OldTollMileRatio | B21: 0.28898088 | C21: 0.081507771 | D21: 3.5454396 | E21: 0.00096037513 | F21: 0.12460491 | G21: 0.45335685 | H21: 0.12460491 | I21: 0.45335685
A22: Residents Who Work OOS - JTW | B22: -0.35104428 | C22: 0.29318377 | D22: -1.1973524 | E22: 0.23772837 | F22: -0.94230529 | G22: 0.24021673 | H22: -0.94230529 | I22: 0.24021673

Sheet Sheet8
A1: SUMMARY OUTPUT
A3: Regression Statistics
A4: Multiple R | B4: 0.80111602
A5: R Square | B5: 0.64178687
A6: Adjusted R Square | B6: 0.59061357
A7: Standard Error | B7: 0.046694331
A8: Observations | B8: 49
A10: ANOVA
B11: df | C11: SS | D11: MS | E11: F | F11: Significance F
A12: Regression | B12: 6 | C12: 0.16406915 | D12: 0.027344859 | E12: 12.541439 | F12: 4.7520166e-08
A13: Residual | B13: 42 | C13: 0.091575144 | D13: 0.0021803606
A14: Total | B14: 48 | C14: 0.2556443
B16: Coefficients | C16: Standard Error | D16: t Stat | E16: P-value | F16: Lower 95% | G16: Upper 95% | H16: Lower 95.0% | I16: Upper 95.0%
A17: Intercept | B17: -0.038801562 | C17: 0.017547604 | D17: -2.2112172 | E17: 0.0325181 | F17: -0.074214071 | G17: -0.0033890534 | H17: -0.074214071 | I17: -0.0033890534
A18: Population | B18: 3.6072544e-09 | C18: 1.2834578e-09 | D18: 2.8105751 | E18: 0.0074806042 | F18: 1.017131e-09 | G18: 6.1973779e-09 | H18: 1.017131e-09 | I18: 6.1973779e-09
A19: OldTollMileRatio | B19: 0.30730054 | C19: 0.095654802 | D19: 3.2125992 | E19: 0.0025266029 | F19: 0.11426128 | G19: 0.50033981 | H19: 0.11426128 | I19: 0.50033981
A20: Workers Who Live OOS (JTW) | B20: 0.98450068 | C20: 0.40634343 | D20: 2.4228291 | E20: 0.01979143 | F20: 0.16446618 | G20: 1.8045352 | H20: 0.16446618 | I20: 1.8045352
A21: AVG-Neighbor-2 | B21: 0.14181836 | C21: 0.16346134 | D21: 0.86759576 | E21: 0.39054586 | F21: -0.18806007 | G21: 0.4716968 | H21: -0.18806007 | I21: 0.4716968
A22: Residents Who Work OOS - JTW | B22: -0.149297 | C22: 0.27830043 | D22: -0.53645983 | E22: 0.59447109 | F22: -0.71093019 | G22: 0.41233619 | H22: -0.71093019 | I22: 0.41233619
A23: Percent Federal Land | B23: 0.0051962971 | C23: 0.03765486 | D23: 0.13799805 | E23: 0.89090146 | F23: -0.070794311 | G23: 0.081186905 | H23: -0.070794311 | I23: 0.081186905

Sheet Ro=f(L,D)
A1: SUMMARY OUTPUT | C1: dep=residents who work of jurisdiction
A3: Regression Statistics
A4: Multiple R | B4: 0.56537565
A5: R Square | B5: 0.31964963
A6: Adjusted R Square | B6: 0.29006918
A7: Standard Error | B7: 0.032531977
A8: Observations | B8: 49
A10: ANOVA
B11: df | C11: SS | D11: MS | E11: F | F11: Significance F
A12: Regression | B12: 2 | C12: 0.022872852 | D12: 0.011436426 | E12: 10.806111 | F12: 0.0001421839
A13: Residual | B13: 46 | C13: 0.048683158 | D13: 0.0010583295
A14: Total | B14: 48 | C14: 0.07155601
B16: Coefficients | C16: Standard Error | D16: t Stat | E16: P-value | F16: Lower 95% | G16: Upper 95% | H16: Lower 95.0% | I16: Upper 95.0%
A17: Intercept | B17: 0.054607413 | C17: 0.010513105 | D17: 5.1942233 | E17: 4.5680971e-06 | F17: 0.033445651 | G17: 0.075769174 | H17: 0.033445651 | I17: 0.075769174
A18: Land | B18: -3.2107613e-07 | C18: 1.1386428e-07 | D18: -2.8198144 | E18: 0.0070661387 | F18: -5.5027282e-07 | G18: -9.187945e-08 | H18: -5.5027282e-07 | I18: -9.187945e-08
A19: Density | B19: 4.240699e-05 | C19: 2.242714e-05 | D19: 1.8908782 | E19: 0.064948512 | F19: -2.7364585e-06 | G19: 8.7550439e-05 | H19: -2.7364585e-06 | I19: 8.7550439e-05

Sheet N-N-f(P,M,Ow,RoxN2^4)
A1: XLSTAT - Regression / Started on 11/18/98 at 1:12:35 PM
A2: Input data :
A3: Y variable : Workbook = Levinson-stat.xls / Sheet = Select / Range = $C$3:$C$52
A4: Numerical variables : Workbook = Levinson-stat.xls / Sheet = Select / Range = $M$3:$P$52
A5: Categorical variables : None
B8: Mean | C8: Std. dev. | D8: Min | E8: Max
A9: TollShare | B9: 0.042004283 | C9: 0.072978921 | D9: 0 | E9: 0.33182204
A10: Population | B10: 5338722.4 | C10: 5779174.7 | D10: 480184 | E10: 31589153
A11: OldTollMileRatio | B11: 0.074880138 | C11: 0.11461002 | D11: 0 | E11: 0.42472527
A12: Workers Who Live OOS (JTW) | B12: 0.037239314 | C12: 0.026926035 | D12: 0.0045230302 | E12: 0.13832888
A13: AVG-Neighbor-2 | B13: 2.1584088e-08 | C13: 1.3232308e-07 | D13: 1.3511322e-16 | E13: 9.261788e-07
A16: Correlation coefficient r : 0.8093
A17: Determination coefficient r² : 0.6549
A18: Adjusted determination coefficient : 0.6235
A21: Evaluating significance of information carried by variables (H0 = Y=Mean(Y)):
B23: DF | C23: Sum of squares | D23: Mean of squares | E23: Fisher's F | F23: Pr > F
A24: Model | B24: 4 | C24: 0.16742144 | D24: 0.041855361 | E24: 20.874817 | F24: 0.0001
A25: Residuals | B25: 44 | C25: 0.088222852 | D25: 0.0020050648
A26: Total | B26: 48 | C26: 0.2556443
A29: Model analysis (Type I SS) :
A31: Source | B31: DF | C31: Type I SS | D31: Mean Square | E31: Fisher's F | F31: Pr. >F
A32: Population | B32: 1 | C32: 0.018182342 | D32: 0.018182342 | E32: 9.0682064 | F32: 0.0042980641
A33: OldTollMileRatio | B33: 1 | C33: 0.12632283 | D33: 0.12632283 | E33: 63.00187 | F33: 0.0001
A34: Workers Who Live OOS (JTW) | B34: 1 | C34: 0.017078413 | D34: 0.017078413 | E34: 8.5176362 | F34: 0.0055234705
A35: AVG-Neighbor-2 | B35: 1 | C35: 0.0058378567 | D35: 0.0058378567 | E35: 2.9115551 | F35: 0.094996934
A38: Regression parameters and corresponding statistics :
B40: Value | C40: Std dev. | D40: Student's t | E40: Corresponding probability | F40: Lower 95% bound | G40: Upper 95% bound
A41: Intercept | B41: -0.034466014 | C41: 0.014231442 | D41: -2.4218217 | E41: 0.019631758 | F41: -0.063147598 | G41: -0.0057844288
A42: Population | B42: 3.8296086e-09 | C42: 1.1981435e-09 | D42: 3.1962855 | E42: 0.0025774017 | F42: 1.4149092e-09 | G42: 6.2443081e-09
A43: OldTollMileRatio | B43: 0.29964411 | C43: 0.072469895 | D43: 4.1347391 | E43: 0.00015714171 | F43: 0.15359064 | G43: 0.44569758
A44: Workers Who Live OOS (JTW) | B44: 0.84697193 | C44: 0.28925856 | D44: 2.9280791 | E44: 0.0053833613 | F44: 0.26400963 | G44: 1.4299342
A45: AVG-Neighbor-2^4 | B45: 94839.933 | C45: 55581.304 | D45: 1.706328 | E45: 0.094996934 | F45: -17176.82 | G45: 206856.69

Sheet Sheet1
A1: XLSTAT - Regression / Started on 11/24/98 at 10:43:32 AM
A2: Input data :
A3: Y variable : Workbook = Levinson-stat.xls / Sheet = Select / Range = $C$3:$C$52
A4: Numerical variables : Workbook = Levinson-stat.xls / Sheet = Select / Range = $M$3:$P$52
A5: Categorical variables : None
B8: Mean | C8: Std. dev. | D8: Min | E8: Max
A9: TollShare | B9: 0.029757828 | C9: 0.068399474 | D9: 0 | E9: 0.33182204
A10: Population | B10: 4649000.5 | C10: 3539126.2 | D10: 480184 | E10: 31589153
A11: OldTollMileRatio | B11: 0.04455473 | C11: 0.11195769 | D11: 0 | E11: 0.42472527
A12: Workers Who Live OOS (JTW) | B12: 0.03286254 | C12: 0.021499074 | D12: 0.0045230302 | E12: 0.13832888
A13: N1^4 | B13: 6.0124712e-08 | C13: 2.3157569e-07 | D13: 2.5762505e-14 | E13: 9.7857405e-07
A16: Correlation coefficient r : 0.9803
A17: Determination coefficient r² : 0.9609
A18: Adjusted determination coefficient : 0.9609
A21: Evaluating significance of information carried by variables (H0 = Y=Mean(Y)):
B23: DF | C23: Sum of squares | D23: Mean of squares | E23: Fisher's F | F23: Pr > F
A24: Model | B24: 4 | C24: 28.93175 | D24: 7.2329375 | E24: 39555.079 | F24: 0.0001
A25: Residuals | B25: 6431.3637 | C25: 1.1760222 | D25: 0.00018285737
A26: Total | B26: 6435.3637 | C26: 30.107772
A29: Model analysis (Type I SS) :
A31: Source | B31: DF | C31: Type I SS | D31: Mean Square | E31: Fisher's F | F31: Pr. >F
A32: Population | B32: 1 | C32: 3.0908722 | D32: 3.0908722 | E32: 16903.187 | F32: 0.0001
A33: OldTollMileRatio | B33: 1 | C33: 24.55254 | D33: 24.55254 | E33: 134271.54 | F33: 0.0001
A34: Workers Who Live OOS (JTW) | B34: 1 | C34: 0.55686054 | D34: 0.55686054 | E34: 3045.3274 | F34: 0.0001
A35: N1^4 | B35: 1 | C35: 0.73147761 | D35: 0.73147761 | E35: 4000.2633 | F35: 0.0001
A38: Regression parameters and corresponding statistics :
B40: Value | C40: Std dev. | D40: Student's t | E40: Corresponding probability | F40: Lower 95% bound | G40: Upper 95% bound
A41: Intercept | B41: -0.023353064 | C41: 0.00052629701 | D41: -44.372404 | E41: 0.0001 | F41: -0.024384782 | G41: -0.022321346
A42: Population | B42: 2.7335222e-09 | C42: 5.9479334e-11 | D42: 45.957511 | E42: 0.0001 | F42: 2.6169228e-09 | G42: 2.8501215e-09
A43: OldTollMileRatio | B43: 0.33608254 | C43: 0.0033523891 | D43: 100.25165 | E43: 0.0001 | F43: 0.32951074 | G43: 0.34265435
A44: Workers Who Live OOS (JTW) | B44: 0.60665934 | C44: 0.010899014 | D44: 55.661856 | E44: 0.0001 | F44: 0.58529363 | G44: 0.62802505
A45: N1^4 | B45: 91348.655 | C45: 1444.3015 | D45: 63.247635 | E45: 0.0001 | F45: 88517.341 | G45: 94179.968
A48: Residuals analysis :
A50: Observation | B50: Weight | C50: Population | D50: TollShare | E50: predicted TollShare | F50: Residuals | G50: Reduced residuals | H50: Lower value (95% confidence range) | I50: Upper value (95% confidence range)
A51: 1 | B51: 492.23816 | C51: 4252982 | D51: 0 | E51: 0.0027426265 | F51: -0.0027426265 | G51: -0.083896849 | H51: -0.023768561 | I51: 0.029253814
A52: 2 | B52: 113.65499 | C52: 4217940 | D52: 0 | E52: -0.0050241499 | F52: 0.0050241499 | G52: 0.09495006 | H52: -0.031537727 | I52: 0.021489427
A53: 3 | B53: 109.13923 | C53: 2483769 | D53: 0 | E53: 0.007881299 | F53: -0.007881299 | G53: -0.20222595 | H53: -0.018630631 | I53: 0.034393229
A54: 4 | B54: 14.439643 | C54: 31589153 | D54: 0.021141521 | E54: 0.06574063 | F54: -0.044599109 | G54: -1.0477333 | H54: 0.039066321 | I54: 0.092414939
A55: 5 | B55: 84.069065 | C55: 3746585 | D55: 0.0029577777 | E55: -0.0033225748 | F55: 0.0062803524 | G55: 0.12387685 | H55: -0.029838314 | I55: 0.023193165
A56: 6 | B56: 7.9400339 | C56: 3274662 | D56: 0.00025988579 | E56: 0.13595066 | F56: -0.13569078 | G56: -3.145317 | H56: 0.10935748 | I56: 0.16254385
A57: 7 | B57: 10.031359 | C57: 717197 | D57: 0.25259005 | E57: 0.13819655 | F57: 0.1143935 | G57: 2.6134171 | H57: 0.11161173 | I57: 0.16478136
A58: 8 | B58: 55.530833 | C58: 14165570 | D58: 0.077833555 | E58: 0.057529332 | F58: 0.020304223 | G58: 0.44680696 | H58: 0.030999533 | I58: 0.08405913
A59: 9 | B59: 66.158812 | C59: 7200882 | D59: 0.0041858291 | E59: 0.01604101 | F59: -0.011855181 | G59: -0.29373322 | H59: -0.010471855 | I59: 0.042553875
A60: 10 | B60: 45.809187 | C60: 1186815 | D60: 0 | E60: -0.014327236 | F60: 0.014327236 | G60: 0.30917383 | H60: -0.040846599 | I60: 0.012192128
A61: 11 | B61: 127.20826 | C61: 1163261 | D61: 0 | E61: -0.004309822 | F61: 0.004309822 | G61: 0.078501108 | H61: -0.030823613 | I61: 0.022203969
A62: 12 | B62: 30.245568 | C62: 11829940 | D62: 0.092502027 | E62: 0.053828283 | F62: 0.038673744 | G62: 0.86980511 | H62: 0.027305862 | I62: 0.080350705
... A99: 49 | B99: 91.540482 | C99: 480184 | D99: 0 | E99: -0.0064972352 | F99: 0.0064972352 | G99: 0.12887105 | H99: -0.033012416 | I99: 0.020017946
A101: Durbin-Watson Dw statistic : 2.3192
A103: Results interpretation:
A105: The selected X variables explain 96.09% of the variability of Y which is a very good result.
A106: Try to find another set of explanatory variables to replace or to add to the selected ones.
A108: You would take an only 0.01% risk when rejecting the hypothesis that a constant model would be better than your model,
A109: so the selected variables bring significant information to the model.
A111: The variable that weights the most in the model is : Intercept.

Sheet Final-2
A1: XLSTAT - Regression / Started on 11/18/98 at 4:10:42 PM
A2: Input data :
A3: Y variable : Workbook = Levinson-stat.xls / Sheet = Select / Range = $C$3:$C$52
A4: Numerical variables : Workbook = Levinson-stat.xls / Sheet = Select / Range = $M$3:$P$52
A5: Categorical variables : None
B8: Mean | C8: Std. dev. | D8: Min | E8: Max
A9: TollShare | B9: 0.042004283 | C9: 0.072978921 | D9: 0 | E9: 0.33182204
A10: Population | B10: 5338722.4 | C10: 5779174.7 | D10: 480184 | E10: 31589153
A11: OldTollMileRatio | B11: 0.074880138 | C11: 0.11461002 | D11: 0 | E11: 0.42472527
A12: Workers Who Live OOS (JTW) | B12: 0.037239314 | C12: 0.026926035 | D12: 0.0045230302 | E12: 0.13832888
A13: N1^4 | B13: 2.3050017e-08 | C13: 1.3983592e-07 | D13: 2.5762505e-14 | E13: 9.7857405e-07
A16: Correlation coefficient r : 0.8093
A17: Determination coefficient r² : 0.6549
A18: Adjusted determination coefficient : 0.6235
A21: Evaluating significance of information carried by variables (H0 = Y=Mean(Y)):
B23: DF | C23: Sum of squares | D23: Mean of squares | E23: Fisher's F | F23: Pr > F
A24: Model | B24: 4 | C24: 0.16741939 | D24: 0.041854847 | E24: 20.874074 | F24: 0.0001
A25: Residuals | B25: 44 | C25: 0.088224908 | D25: 0.0020051115
A26: Total | B26: 48 | C26: 0.2556443
A29: Model analysis (Type I SS) :
A31: Source | B31: DF | C31: Type I SS | D31: Mean Square | E31: Fisher's F | F31: Pr. >F
A32: Population | B32: 1 | C32: 0.018182342 | D32: 0.018182342 | E32: 9.0679951 | F32: 0.0042984747
A33: OldTollMileRatio | B33: 1 | C33: 0.12632283 | D33: 0.12632283 | E33: 63.000402 | F33: 0.0001
A34: Workers Who Live OOS (JTW) | B34: 1 | C34: 0.017078413 | D34: 0.017078413 | E34: 8.5174378 | F34: 0.0055239737
A35: N1^4 | B35: 1 | C35: 0.0058358015 | D35: 0.0058358015 | E35: 2.9104623 | F35: 0.095057047
A38: Regression parameters and corresponding statistics :
B40: Value | C40: Std dev. | D40: Student's t | E40: Corresponding probability | F40: Lower 95% bound | G40: Upper 95% bound
A41: Intercept | B41: -0.03443583 | C41: 0.014233036 | D41: -2.4194296 | E41: 0.019745682 | F41: -0.063120628 | G41: -0.0057510309
A42: Population | B42: 3.83059e-09 | C42: 1.1981497e-09 | D42: 3.197088 | E42: 0.0025716043 | F42: 1.4158781e-09 | G42: 6.245302e-09
A43: OldTollMileRatio | B43: 0.29938505 | C43: 0.072537536 | D43: 4.1273121 | E43: 0.00016083649 | F43: 0.15319526 | G43: 0.44557484
A44: Workers Who Live OOS (JTW) | B44: 0.84588027 | C44: 0.28925903 | D44: 2.9243003 | E44: 0.0054382243 | F44: 0.26291703 | G44: 1.4288435
A45: N1^4 | B45: 89876.772 | C45: 52682.513 | D45: 1.7060077 | E45: 0.095057047 | F45: -16297.851 | G45: 196051.4

Sheet Ow=f(L,D)
A1: SUMMARY OUTPUT | C1: dep=Workers who live out of jurisdiction
A3: Regression Statistics
A4: Multiple R | B4: 0.52836965
A5: R Square | B5: 0.27917449
A6: Adjusted R Square | B6: 0.24783425
A7: Standard Error | B7: 0.023352274
A8: Observations | B8: 49
A10: ANOVA
B11: df | C11: SS | D11: MS | E11: F | F11: Significance F
A12: Regression | B12: 2 | C12: 0.0097154246 | D12: 0.0048577123 | E12: 8.9078607 | F12: 0.00053714732
A13: Residual | B13: 46 | C13: 0.025085121 | D13: 0.00054532872
A14: Total | B14: 48 | C14: 0.034800546
B16: Coefficients | C16: Standard Error | D16: t Stat | E16: P-value | F16: Lower 95% | G16: Upper 95% | H16: Lower 95.0% | I16: Upper 95.0%
A17: Intercept | B17: 0.047792862 | C17: 0.0075465719 | D17: 6.3330559 | E17: 9.1567688e-08 | F17: 0.032602415 | G17: 0.062983309 | H17: 0.032602415 | I17: 0.062983309
A18: Land | B18: -2.3584376e-07 | C18: 8.1734653e-08 | D18: -2.8854806 | E18: 0.0059312955 | F18: -4.0036693e-07 | G18: -7.1320594e-08 | H18: -4.0036693e-07 | I18: -7.1320594e-08
A19: Density | B19: 2.1238643e-05 | C19: 1.6098768e-05 | D19: 1.3192714 | E19: 0.19360779 | F19: -1.1166464e-05 | G19: 5.3643751e-05 | H19: -1.1166464e-05 | I19: 5.3643751e-05

Sheet Chart1

Sheet L-L
A1: SUMMARY OUTPUT
A3: Regression Statistics
A4: Multiple R | B4: 0.76590337
A5: R Square | B5: 0.58660797
A6: Adjusted R Square | B6: 0.54902688
A7: Standard Error | B7: 0.04361447
A8: Observations | B8: 49
A10: ANOVA
B11: df | C11: SS | D11: MS | E11: F | F11: Significance F
A12: Regression | B12: 4 | C12: 0.11876808 | D12: 0.029692021 | E12: 15.609125 | F12: 5.0483424e-08
A13: Residual | B13: 44 | C13: 0.083697768 | D13: 0.001902222
A14: Total | B14: 48 | C14: 0.20246585
B16: Coefficients | C16: Standard Error | D16: t Stat | E16: P-value | F16: Lower 95% | G16: Upper 95% | H16: Lower 95.0% | I16: Upper 95.0%
A17: Intercept | B17: -0.060622599 | C17: 0.10496975 | D17: -0.57752445 | E17: 0.56652898 | F17: -0.27217523 | G17: 0.15093003 | H17: -0.27217523 | I17: 0.15093003
A18: LN(POP) | B18: 0.011626831 | C18: 0.006937455 | D18: 1.6759504 | E18: 0.10084079 | F18: -0.0023546908 | G18: 0.025608352 | H18: -0.0023546908 | I18: 0.025608352
A19: LN(OLDMILES+1) | B19: 0.35694687 | C19: 0.086481262 | D19: 4.1274475 | E19: 0.00016076841 | F19: 0.18265534 | G19: 0.53123839 | H19: 0.18265534 | I19: 0.53123839
A20: LN(Ow) | B20: 0.0077926212 | C20: 0.010065617 | D20: 0.77418217 | E20: 0.44296327 | F20: -0.012493296 | G20: 0.028078539 | H20: -0.012493296 | I20: 0.028078539
A21: LN(N1^4) | B21: 0.0028160177 | C21: 0.002085214 | D21: 1.3504694 | E21: 0.18377085 | F21: -0.0013864548 | G21: 0.0070184902 | H21: -0.0013864548 | I21: 0.0070184902

Sheet NL-L
A1: SUMMARY OUTPUT
A3: Regression Statistics
A4: Multiple R | B4: 0.75590611
A5: R Square | B5: 0.57139405
A6: Adjusted R Square | B6: 0.53242987
A7: Standard Error | B7: 0.049902329
A8: Observations | B8: 49
A10: ANOVA
B11: df | C11: SS | D11: MS | E11: F | F11: Significance F
A12: Regression | B12: 4 | C12: 0.14607363 | D12: 0.036518407 | E12: 14.664599 | F12: 1.091143e-07
A13: Residual | B13: 44 | C13: 0.10957067 | D13: 0.0024902425
A14: Total | B14: 48 | C14: 0.2556443
B16: Coefficients | C16: Standard Error | D16: t Stat | E16: P-value | F16: Lower 95% | G16: Upper 95% | H16: Lower 95.0% | I16: Upper 95.0%
A17: Intercept | B17: -0.066541498 | C17: 0.12010315 | D17: -0.55403625 | E17: 0.58235905 | F17: -0.30859348 | G17: 0.17551049 | H17: -0.30859348 | I17: 0.17551049
A18: LN(POP) | B18: 0.012956463 | C18: 0.0079376217 | D18: 1.6322852 | E18: 0.10975678 | F18: -0.003040762 | G18: 0.028953688 | H18: -0.003040762 | I18: 0.028953688
A19: LN(OLDMILES+1) | B19: 0.39248128 | C19: 0.098949189 | D19: 3.9664932 | E19: 0.00026504563 | F19: 0.1930623 | G19: 0.59190026 | H19: 0.1930623 | I19: 0.59190026
A20: LN(Ow) | B20: 0.0090230454 | C20: 0.011516768 | D20: 0.78347027 | E20: 0.43754812 | F20: -0.014187475 | G20: 0.032233565 | H20: -0.014187475 | I20: 0.032233565
A21: LN(N1^4) | B21: 0.0031727336 | C21: 0.0023858374 | D21: 1.3298197 | E21: 0.19043065 | F21: -0.0016356056 | G21: 0.0079810727 | H21: -0.0016356056 | I21: 0.0079810727

Sheet NL-NL
A1: SUMMARY OUTPUT
A3: Regression Statistics
A4: Multiple R | B4: 0.80925394
A5: R Square | B5: 0.65489194
A6: Adjusted R Square | B6: 0.62351848
A7: Standard Error | B7: 0.044778472
A8: Observations | B8: 49
A10: ANOVA
B11: df | C11: SS | D11: MS | E11: F | F11: Significance F
A12: Regression | B12: 4 | C12: 0.16741939 | D12: 0.041854847 | E12: 20.874074 | F12: 1.0537751e-09
A13: Residual | B13: 44 | C13: 0.088224908 | D13: 0.0020051115
A14: Total | B14: 48 | C14: 0.2556443
B16: Coefficients | C16: Standard Error | D16: t Stat | E16: P-value | F16: Lower 95% | G16: Upper 95% | H16: Lower 95.0% | I16: Upper 95.0%
A17: Intercept | B17: -0.03443583 | C17: 0.014233036 | D17: -2.4194296 | E17: 0.019745682 | F17: -0.063120628 | G17: -0.0057510309 | H17: -0.063120628 | I17: -0.0057510309
A18: Population | B18: 3.83059e-09 | C18: 1.1981497e-09 | D18: 3.197088 | E18: 0.0025716043 | F18: 1.4158781e-09 | G18: 6.245302e-09 | H18: 1.4158781e-09 | I18: 6.245302e-09
A19: OldTollMileRatio | B19: 0.29938505 | C19: 0.072537536 | D19: 4.1273121 | E19: 0.00016083649 | F19: 0.15319526 | G19: 0.44557484 | H19: 0.15319526 | I19: 0.44557484
A20: Workers Who Live OOS (JTW) | B20: 0.84588027 | C20: 0.28925903 | D20: 2.9243003 | E20: 0.0054382243 | F20: 0.26291703 | G20: 1.4288435 | H20: 0.26291703 | I20: 1.4288435
A21: N1^4 | B21: 89876.772 | C21: 52682.513 | D21: 1.7060077 | E21: 0.095057047 | F21: -16297.851 | G21: 196051.4 | H21: -16297.851 | I21: 196051.4

Sheet L-NL
A1: SUMMARY OUTPUT
A3: Regression Statistics
A4: Multiple R | B4: 0.81513466
A5: R Square | B5: 0.66444451
A6: Adjusted R Square | B6: 0.63393947
A7: Standard Error | B7: 0.039294496
A8: Observations | B8: 49
A10: ANOVA
B11: df | C11: SS | D11: MS | E11: F | F11: Significance F
A12: Regression | B12: 4 | C12: 0.13452732 | D12: 0.033631831 | E12: 21.781464 | F12: 5.7601638e-10
A13: Residual | B13: 44 | C13: 0.067938527 | D13: 0.0015440574
A14: Total | B14: 48 | C14: 0.20246585
B16: Coefficients | C16: Standard Error | D16: t Stat | E16: P-value | F16: Lower 95% | G16: Upper 95% | H16: Lower 95.0% | I16: Upper 95.0%
A17: Intercept | B17: -0.029467612 | C17: 0.01248993 | D17: -2.3593095 | E17: 0.022812108 | F17: -0.054639411 | G17: -0.0042958121 | H17: -0.054639411 | I17: -0.0042958121
A18: Population | B18: 3.4071093e-09 | C18: 1.0514135e-09 | D18: 3.2405037 | E18: 0.0022757171 | F18: 1.2881248e-09 | G18: 5.5260939e-09 | H18: 1.2881248e-09 | I18: 5.5260939e-09
A19: OldTollMileRatio | B19: 0.27608133 | C19: 0.063653934 | D19: 4.3372234 | E19: 8.2940326e-05 | F19: 0.14779526 | G19: 0.4043674 | H19: 0.14779526 | I19: 0.4043674
A20: Workers Who Live OOS (JTW) | B20: 0.74888358 | C20: 0.25383375 | D20: 2.9502916 | E20: 0.0050711707 | F20: 0.23731528 | G20: 1.2604519 | H20: 0.23731528 | I20: 1.2604519
A21: N1^4 | B21: 73400.249 | C21: 46230.537 | D21: 1.5877006 | E21: 0.11951517 | F21: -19771.272 | G21: 166571.77 | H21: -19771.272 | I21: 166571.77

Sheet Sheet4
A1: 0 | B1: 0
A2: 3.5693265 | B2: 1.368132
A3: 0 | B3: 0
A4: -0.12784769 | B4: 2.7596126
A5: 0 | B5: 0
A6: 2.5288976 | B6: 2.0808406
A7: 0 | B7: 0
A8: 3.5294084 | B8: -1.191604
A9: 0 | B9: 0
A10: -3.5779789 | B10: 1.2779655
A11: 0 | B11: 0
A12: 3.8974224 | B12: -0.014484166
... A18: -2.4145428 | B18: -0.2238202

Sheet Sheet5
A1: 0 | B1: 0
A2: 3.5693265 | B2: 1.368132
A3: 0 | B3: 0
A4: -0.12784769 | B4: 2.7596126
A5: 0 | B5: 0
A6: 2.5288976 | B6: 2.0808406
A7: 0 | B7: 0
A8: 3.5294084 | B8: -1.191604
A9: 0 | B9: 0
A10: -3.5779789 | B10: 1.2779655
A11: 0 | B11: 0
A12: 3.8974224 | B12: -0.014484166
... A18: -2.4145428 | B18: -0.2238202

Sheet Correlate
B1: TollShare | C1: Population | D1: TollMile1963 | E1: ImportedWorkers | F1: ResidentsWhoWorkInState | G1: NeighborTolls | H1: Land | I1: Density | J1: Federal
A2: TollShare | B2: 1
A3: Population | B3: 0.26669007 | C3: 1
A4: TollMile1963 | B4: 0.70652169 | C4: 0.38911354 | D4: 1
A5: ImportedWorkers | B5: 0.48513559 | C5: -0.27094325 | D5: 0.15674437 | E5: 1
A6: ResidentsWhoWorkInState | B6: -0.38005433 | C6: 0.24462457 | D6: -0.11361942 | E6: -0.76487976 | F6: 1
A7: NeighborTolls | B7: 0.61280471 | C7: -0.03359231 | D7: 0.35833907 | E7: 0.54376982 | F7: -0.64353577 | G7: 1
A8: Land | B8: -0.3229898 | C8: 0.35593199 | D8: -0.22050229 | E8: -0.50189741 | F8: 0.51649623 | G8: -0.45400382 | H8: 1
A9: Density | B9: 0.53259128 | C9: 0.17995243 | D9: 0.38610897 | E9: 0.38562299 | F9: -0.44949674 | G9: 0.70145605 | H9: -0.47959695 | I9: 1
A10: Federal | B10: -0.28228467 | C10: -0.065257391 | D10: -0.3151369 | E10: -0.28808129 | F10: 0.29099717 | G10: -0.22356174 | H10: 0.45187929 | I10: -0.31881492 | J10: 1
A14: XLSTAT - Correlations and Principal Components Analysis / Started on 11/25/98 at 10:13:17 AM
A15: Correlation coefficient type : Classical
A16: Data range : Workbook = Levinson-stat.xls / Sheet = UberSelect / Range = $C$1:$K$50
A18: Correlations matrix :
B20: TollShare | C20: Population | D20: TollMile1963 | E20: Workers Who Live OOS (JTW) | F20: ResidentsWhoWorkInState | G20: AVG-Neighbor-1 | H20: Land | I20: Density | J20: Percent Federal Lands
A21: TollShare | B21: 1 | C21: 0.26669007 | D21: 0.70652169 | E21: 0.48513559 | F21: -0.38005433 | G21: 0.61280471 | H21: -0.3229898 | I21: 0.53259128 | J21: -0.28228467
A22: Population | B22: 0.26669007 | C22: 1 | D22: 0.38911354 | E22: -0.27094325 | F22: 0.24462457 | G22: -0.03359231 | H22: 0.35593199 | I22: 0.17995243 | J22: -0.065257391
A23: TollMile1963 | B23: 0.70652169 | C23: 0.38911354 | D23: 1 | E23: 0.15674437 | F23: -0.11361942 | G23: 0.35833907 | H23: -0.22050229 | I23: 0.38610897 | J23: -0.3151369
A24: Workers Who Live OOS (JTW) | B24: 0.48513559 | C24: -0.27094325 | D24: 0.15674437 | E24: 1 | F24: -0.76487976 | G24: 0.54376982 | H24: -0.50189741 | I24: 0.38562299 | J24: -0.28808129
A25: ResidentsWhoWorkInState | B25: -0.38005433 | C25: 0.24462457 | D25: -0.11361942 | E25: -0.76487976 | F25: 1 | G25: -0.64353577 | H25: 0.51649623 | I25: -0.44949674 | J25: 0.29099717
A26: AVG-Neighbor-1 | B26: 0.61280471 | C26: -0.03359231 | D26: 0.35833907 | E26: 0.54376982 | F26: -0.64353577 | G26: 1 | H26: -0.45400382 | I26: 0.70145605 | J26: -0.22356174
A27: Land | B27: -0.3229898 | C27: 0.35593199 | D27: -0.22050229 | E27: -0.50189741 | F27: 0.51649623 | G27: -0.45400382 | H27: 1 | I27: -0.47959695 | J27: 0.45187929
A28: Density | B28: 0.53259128 | C28: 0.17995243 | D28: 0.38610897 | E28: 0.38562299 | F28: -0.44949674 | G28: 0.70145605 | H28: -0.47959695 | I28: 1 | J28: -0.31881492
A29: Percent Federal Lands | B29: -0.28228467 | C29: -0.065257391 | D29: -0.3151369 | E29: -0.28808129 | F29: 0.29099717 | G29: -0.22356174 | H29: 0.45187929 | I29: -0.31881492 | J29: 1
A32: Eigenvalues and eigenvectors (based on the correlations matrix) :
A34: Eigenvalue. | B34: 1 | C34: 2 | D34: 3 | E34: 4 | F34: 5 | G34: 6 | H34: 7 | I34: 8 | J34: 9
A35: Value | B35: 4.0422982 | C35: 1.8463131 | D35: 0.94077356 | E35: 0.65134237 | F35: 0.5950762 | G35: 0.31510507 | H35: 0.26104746 | I35: 0.20586587 | J35: 0.14217819
A36: % of variability. | B36: 0.44914424 | C36: 0.2051459 | D36: 0.1045304 | E36: 0.072371375 | F36: 0.066119578 | G36: 0.035011674 | H36: 0.029005274 | I36: 0.022873986 | J36: 0.015797576
A37: Cumulated % | B37: 0.44914424 | C37: 0.65429014 | D37: 0.75882054 | E37: 0.83119191 | F37: 0.89731149 | G37: 0.93232316 | H37: 0.96132844 | I37: 0.98420242 | J37: 1
A38: Vectors : | B38: 1 | C38: 2 | D38: 3 | E38: 4 | F38: 5 | G38: 6 | H38: 7 | I38: 8 | J38: 9
A39: TollShare | B39: 0.37842616 | C39: 0.31757467 | D39: 0.15896171 | E39: -0.36485997 | F39: -0.14407588 | G39: 0.022158869 | H39: 0.41762673 | I39: -0.38115124 | J39: 0.50656798
A40: Population | B40: -0.013554633 | C40: 0.64056911 | D40: 0.056607557 | E40: 0.17917831 | F40: 0.47090077 | G40: -0.40942833 | H40: -0.17854847 | I40: -0.30014569 | J40: -0.20695922
A41: TollMile1963 | B41: 0.26811808 | C41: 0.48301062 | D41: -0.12253663 | E41: -0.38430479 | F41: -0.36480591 | G41: 0.074366998 | H41: -0.39341382 | I41: 0.45287659 | J41: -0.18336464
A42: Workers Who Live OOS (JTW) | B42: 0.37419397 | C42: -0.27659849 | D42: 0.15497332 | E42: -0.39045074 | F42: 0.3234428 | G42: -0.31966916 | H42: 0.3680679 | I42: 0.23062299 | J42: -0.45993378
A43: ResidentsWhoWorkInState | B43: -0.3793435 | C43: 0.29664498 | D43: -0.18688062 | E43: 0.077391639 | F43: -0.39598094 | G43: 0.018353635 | H43: 0.61173284 | I43: -0.045492969 | J43: -0.44018405
A44: AVG-Neighbor-1 | B44: 0.41321144 | C44: -0.0033621057 | D44: 0.33731268 | E44: 0.2627146 | F44: -0.071419814 | G44: 0.56758731 | H44: -0.0836001 | I44: -0.33212901 | J44: -0.44932326
A45: Land | B45: -0.3468783 | C45: 0.26127673 | D45: 0.37697387 | E45: -0.14766891 | F45: 0.4478072 | G45: 0.50100103 | H45: 0.18059028 | I45: 0.38653091 | J45: 0.1180771
... A47: Percent Federal Lands | B47: -0.25599399 | C47: -0.051953779 | D47: 0.79433263 | E47: -0.032265873 | F47: -0.39001299 | G47: -0.35561466 | H47: -0.14385409 | I47: 0.0049812861 | J47: -0.021719654
A50: Correlations between initial variables and principal factors :
B52: factor 1 | C52: factor 2 | D52: factor 3 | E52: factor 4 | F52: factor 5 | G52: factor 6 | H52: factor 7 | I52: factor 8 | J52: factor 9
A53: TollShare | B53: 0.76084347 | C53: 0.43151762 | D53: 0.1541825 | E53: -0.2944631 | F53: -0.11114184 | G53: 0.012438708 | H53: 0.21337721 | I53: -0.17293764 | J53: 0.19100917
A54: Population | B54: -0.027252222 | C54: 0.87039956 | D54: 0.054905641 | E54: 0.14460726 | F54: 0.36325842 | G54: -0.2298294 | H54: -0.091225422 | I54: -0.13618344 | J54: -0.078037128
A55: TollMile1963 | B55: 0.53906394 | C55: 0.6563105 | D55: -0.11885255 | E55: -0.3101562 | F55: -0.2814156 | G55: 0.041745334 | H55: -0.20100615 | I55: 0.20548118 | J55: -0.069140431
A56: Workers Who Live OOS (JTW) | B56: 0.75233446 | C56: -0.37583955 | D56: 0.15031402 | E56: -0.31511633 | F56: 0.2495076 | G56: -0.17944379 | H56: 0.18805621 | I56: 0.10463929 | J56: -0.17342504
A57: ResidentsWhoWorkInState | B57: -0.76268784 | C57: 0.40307854 | D57: -0.18126202 | E57: 0.06245953 | F57: -0.30546438 | G57: 0.01030267 | H57: 0.31255146 | I57: -0.020641272 | J57: -0.1659781
A58: AVG-Neighbor-1 | B58: 0.83078092 | C58: -0.0045683991 | D58: 0.32717132 | E58: 0.21202588 | F58: -0.055094089 | G58: 0.31861071 | H58: -0.042713635 | I58: -0.15069505 | J58: -0.16942418
A59: Land | B59: -0.69741504 | C59: 0.35502048 | D59: 0.36564008 | E59: -0.11917735 | F59: 0.34544377 | G59: 0.28123302 | H59: 0.092268639 | I59: 0.17537852 | J59: 0.044522769
A60: Density | B60: 0.76347535 | C60: 0.19234111 | D60: 0.10041039 | E60: 0.53337596 | F60: -0.055909491 | G60: -0.08732901 | H60: 0.13415831 | I60: 0.22437207 | J60: 0.080278385
A61: Percent Federal Lands | B61: -0.51468789 | C61: -0.07059433 | D61: 0.77045087 | E61: -0.026040426 | F61: -0.30086063 | G61: -0.19962151 | H61: -0.073499087 | I61: 0.0022601313 | J61: -0.0081897264
A64: Data coordinates on new axes (principal components):
B66: axis 1 | C66: axis 2 | D66: axis 3 | E66: axis 4 | F66: axis 5 | G66: axis 6 | H66: axis 7 | I66: axis 8 | J66: axis 9
A67: Obs 1 | B67: -0.74584235 | C67: -0.46691687 | D67: -0.83428179 | E67: 0.27663024 | F67: 0.13891596 | G67: 0.074224026 | H67: -0.094455912 | I67: -0.22436322 | J67: 0.1082701
A68: Obs 2 | B68: -2.170572 | C68: 0.039337112 | D68: 1.0623906 | E68: 0.11062997 | F68: -0.3815043 | G68: 0.2478421 | H68: -0.038896439 | I68: 0.074626307 | J68: 0.16403029
A69: Obs 3 | B69: -0.68696684 | C69: -0.83455458 | D69: -0.57834608 | E69: -0.12916359 | F69: 0.078381237 | G69: -0.055763535 | H69: 0.17600486 | I69: -0.052683614 | J69: -0.18315472
A70: Obs 4 | B70: -2.4343354 | C70: 3.6897137 | D70: 1.8192711 | E70: 1.303828 | F70: 1.9187409 | G70: -1.335537 | H70: -0.34298754 | I70: -0.84237668 | J70: -0.44348126
A71: Obs 5 | B71: -2.0884025 | C71: 0.099759603 | D71: 0.6783931 | E71: 0.1168704 | F71: -0.55151053 | G71: 0.3095624 | H71: -0.010441998 | I71: 0.035880924 | J71: 0.16693338
A72: Obs 6 | B72: 2.3097646 | C72: -0.070972602 | D72: -0.34889155 | E72: 1.7074215 | F72: -0.821344 | G72: 0.39349904 | H72: -0.21128227 | I72: 0.83974094 | J72: -0.9273976
A73: Obs 7 | B73: 4.4690309 | C73: -1.4655399 | D73: 0.99566202 | E73: -1.4613402 | F73: 0.63457332 | G73: -0.5380697 | H73: 2.0428685 | I73: -0.75457814 | J73: -0.077341762
A74: Obs 8 | B74: -0.1835334 | C74: 2.2337784 | D74: -0.67680167 | E74: 0.36656342 | F74: -0.35726571 | G74: -0.41585159 | H74: -0.20846071 | I74: -0.22221868 | J74: 0.11357802
A75: Obs 9 | B75: -0.76736361 | C75: 0.035339826 | D75: -0.74203656 | E75: 0.3644511 | F75: 0.31337705 | G75: -0.13956194 | H75: 0.12603845 | I75: -0.19278219 | J75: -0.1408656
A76: Obs 10 | B76: -0.71351222 | C76: -0.6220236 | D76: -1.1059315 | E76: 0.94101639 | F76: -1.1959912 | G76: -0.0036649795 | H76: 0.18257078 | I76: -0.47207675 | J76: -0.045902387
A77: Obs 11 | B77: -1.772195 | C77: -0.88267107 | D77: 1.7632317 | E77: -0.24896773 | F77: -0.87942595 | G77: -0.38907718 | H77: -0.40935707 | I77: 0.090287214 | J77: 0.16896312
A78: Obs 12 | B78: 0.26187525 | C78: 1.5993757 | D78: -0.75107327 | E78: -0.21914865 | F78: 0.087207644 | G78: -0.41620231 | H78: 0.0025236361 | I78: -0.10278875 | J78: 0.22324176
... A115: Obs 49 | B115: -1.9702244 | C115: -0.69243875 | D115: 1.2400455 | E115: -0.29627565 | F115: -0.75376193 | G115: 0.010753407 | H115: 0.063787842 | I115: 0.22399872 | J115: 0.056528151

Sheet Sheet7
A1: SUMMARY OUTPUT
A3: Regression Statistics
A4: Multiple R | B4: 0.56930254
A5: R Square | B5: 0.32410538
A6: Adjusted R Square | B6: 0.26266042
A7: Standard Error | B7: 0.023120977
A8: Observations | B8: 49
A10: ANOVA
B11: df | C11: SS | D11: MS | E11: F | F11: Significance F
A12: Regression | B12: 4 | C12: 0.011279044 | D12: 0.002819761 | E12: 5.2747264 | F12: 0.0014704332
A13: Residual | B13: 44 | C13: 0.023521502 | D13: 0.00053457958
A14: Total | B14: 48 | C14: 0.034800546
B16: Coefficients | C16: Standard Error | D16: t Stat | E16: P-value | F16: Lower 95% | G16: Upper 95% | H16: Lower 95.0% | I16: Upper 95.0%
A17: Intercept | B17: 0.044899736 | C17: 0.0078998424 | D17: 5.6836243 | E17: 9.8244038e-07 | F17: 0.02897865 | G17: 0.060820821 | H17: 0.02897865 | I17: 0.060820821
A18: AVG-Neighbor-2 | B18: 0.05748368 | C18: 0.071905742 | D18: 0.79943101 | E18: 0.42833527 | F18: -0.087432816 | G18: 0.20240018 | H18: -0.087432816 | I18: 0.20240018
A19: Population | B19: -1.1216284e-09 | C19: 6.924062e-10 | D19: -1.6198995 | E19: 0.11240006 | F19: -2.5170814e-09 | G19: 2.7382452e-10 | H19: -2.5170814e-09 | I19: 2.7382452e-10
A20: Land | B20: -1.4942463e-07 | C20: 9.5717252e-08 | D20: -1.5611044 | E20: 0.1256637 | F20: -3.4233006e-07 | G20: 4.3480813e-08 | H20: -3.4233006e-07 | I20: 4.3480813e-08
A21: Density | B21: 2.4635647e-05 | C21: 2.0276321e-05 | D21: 1.2149959 | E21: 0.2308475 | F21: -1.6228591e-05 | G21: 6.5499884e-05 | H21: -1.6228591e-05 | I21: 6.5499884e-05

Sheet Sheet9
A1: SUMMARY OUTPUT
A3: Regression Statistics
A4: Multiple R | B4: 0.5490254
A5: R Square | B5: 0.30142889
A6: Adjusted R Square | B6: 0.25485748
A7: Standard Error | B7: 0.023242995
A8: Observations | B8: 49
A10: ANOVA
B11: df | C11: SS | D11: MS | E11: F | F11: Significance F
A12: Regression | B12: 3 | C12: 0.01048989 | D12: 0.0034966299 | E12: 6.4724023 | F12: 0.00097736561
A13: Residual | B13: 45 | C13: 0.024310656 | D13: 0.0005402368
A14: Total | B14: 48 | C14: 0.034800546
B16: Coefficients | C16: Standard Error | D16: t Stat | E16: P-value | F16: Lower 95% | G16: Upper 95% | H16: Lower 95.0% | I16: Upper 95.0%
A17: Intercept | B17: 0.048582928 | C17: 0.0073335558 | D17: 6.6247437 | E17: 3.677408e-08 | F17: 0.033812389 | G17: 0.063353466 | H17: 0.033812389 | I17: 0.063353466
A18: AVG-Neighbor-2 | B18: 0.10061721 | C18: 0.062860929 | D18: 1.6006319 | E18: 0.11645647 | F18: -0.025991197 | G18: 0.22722561 | H18: -0.025991197 | I18: 0.22722561
A19: Population | B19: -8.7890639e-10 | C19: 6.6645986e-10 | D19: -1.3187687 | E19: 0.19391874 | F19: -2.2212254e-09 | G19: 4.6341263e-10 | H19: -2.2212254e-09 | I19: 4.6341263e-10
A20: Land | B20: -1.9823371e-07 | C20: 8.7337633e-08 | D20: -2.2697399 | E20: 0.028063499 | F20: -3.7414072e-07 | G20: -2.2326694e-08 | H20: -3.7414072e-07 | I20: -2.2326694e-08

Sheet Sheet11
A1: SUMMARY OUTPUT
A3: Regression Statistics
A4: Multiple R | B4: 0.51152376
A5: R Square | B5: 0.26165656
A6: Adjusted R Square | B6: 0.22955467
A7: Standard Error | B7: 0.023634332
A8: Observations | B8: 49
A10: ANOVA
B11: df | C11: SS | D11: MS | E11: F | F11: Significance F
A12: Regression | B12: 2 | C12: 0.0091057909 | D12: 0.0045528955 | E12: 8.1508149 | F12: 0.00093313341
A13: Residual | B13: 46 | C13: 0.025694755 | D13: 0.00055858163
A14: Total | B14: 48 | C14: 0.034800546
B16: Coefficients | C16: Standard Error | D16: t Stat | E16: P-value | F16: Lower 95% | G16: Upper 95% | H16: Lower 95.0% | I16: Upper 95.0%
A17: Intercept | B17: 0.055969249 | C17: 0.0057956346 | D17: 9.657139 | E17: 1.2198519e-12 | F17: 0.044303253 | G17: 0.067635245 | H17: 0.044303253 | I17: 0.067635245
A18: Population | B18: -4.9243354e-10 | C18: 6.3164355e-10 | D18: -0.77960669 | E18: 0.43961524 | F18: -1.7638648e-09 | G18: 7.7899777e-10 | H18: -1.7638648e-09 | I18: 7.7899777e-10
A19: Land | B19: -2.6600519e-07 | C19: 7.7674269e-08 | D19: -3.4246244 | E19: 0.0013046721 | F19: -4.2235524e-07 | G19: -1.0965515e-07 | H19: -4.2235524e-07 | I19: -1.0965515e-07

Sheet Sheet6
A1: FULLNAME | B1: AVG-Neighbor-2 | C1: Population | D1: Land | E1: Density | F1: Workers Who Live OOS (JTW)
A2: ALABAMA | B2: 0.016641465 | C2: 4252982 | D2: 50750 | E2: 83.802601 | F2: 0.023851877
A3: ARIZONA | B3: 0.021735556 | C3: 4217940 | D3: 113642 | E3: 37.116031 | F3: 0.011207188
A4: ARKANSAS | B4: 0.020268432 | C4: 2483769 | D4: 52075 | E4: 47.695996 | F4: 0.040294187
A5: CALIFORNIA | B5: 0.046286746 | C5: 31589153 | D5: 155973 | E5: 202.52962 | F5: 0.0045230302
A6: COLORADO | B6: 0.038557176 | C6: 3746585 | D6: 103730 | E6: 36.118625 | F6: 0.0079445411
A7: CONNECTICUT | B7: 0.26023043 | C7: 3274662 | D7: 4845 | E7: 675.88483 | F7: 0.045612423
A8: DELAWARE | B8: 0.11872671 | C8: 717197 | D8: 1955 | E8: 366.85269 | F8: 0.13832888
A9: FLORIDA | B9: 0.062671969 | C9: 14165570 | D9: 53997 | E9: 262.33994 | F9: 0.0079942105
A10: GEORGIA | B10: 0.02061609 | C10: 7200882 | D10: 57919 | E10: 124.32677 | F10: 0.028137824
A11: HAWAII | B11: 0.035368224 | C11: 1186815 | D11: 6423 | E11: 184.77581 | F11: 0.0095240957
A12: IDAHO | B12: 0.025523251 | C12: 1163261 | D12: 82751 | E12: 14.057365 | F12: 0.026148588
A13: ILLINOIS | B13: 0.013967169 | C13: 11829940 | D13: 55593 | E13: 212.7955 | F13: 0.028193774
... A50: WYOMING | B50: 0.011513892 | C50: 480184 | D50: 97105 | E50: 4.9449977 | F50: 0.025620995

Sheet Sheet2
A1: SUMMARY OUTPUT
A3: Regression Statistics
A4: Multiple R | B4: 0.79695486
A5: R Square | B5: 0.63513705
A6: Adjusted R Square | B6: 0.60196769
A7: Standard Error | B7: 0.046042256
A8: Observations | B8: 49
A10: ANOVA
B11: df | C11: SS | D11: MS | E11: F | F11: Significance F
A12: Regression | B12: 4 | C12: 0.16236916 | D12: 0.040592291 | E12: 19.148306 | F12: 3.4846898e-09
A13: Residual | B13: 44 | C13: 0.093275133 | D13: 0.0021198894
A14: Total | B14: 48 | C14: 0.2556443
B16: Coefficients | C16: Standard Error | D16: t Stat | E16: P-value | F16: Lower 95% | G16: Upper 95% | H16: Lower 95.0% | I16: Upper 95.0%
A17: Intercept | B17: -0.035497634 | C17: 0.014660774 | D17: -2.4212661 | E17: 0.019658165 | F17: -0.065044481 | G17: -0.0059507875 | H17: -0.065044481 | I17: -0.0059507875
A18: Population | B18: 3.7762954e-09 | C18: 1.2391032e-09 | D18: 3.0476036 | E18: 0.0038927623 | F18: 1.279047e-09 | G18: 6.2735437e-09 | H18: 1.279047e-09 | I18: 6.2735437e-09
A19: OldTollMileRatio | B19: 0.36028902 | C19: 0.068832128 | D19: 5.2343147 | E19: 4.4311943e-06 | F19: 0.22156698 | G19: 0.49901105 | H19: 0.22156698 | I19: 0.49901105
A20: Workers Who Live OOS (JTW) | B20: 1.0054759 | C20: 0.3983195 | D20: 2.524295 | E20: 0.015275598 | F20: 0.20271576 | G20: 1.8082361 | H20: 0.20271576 | I20: 1.8082361
A21: Ro | B21: -0.16618972 | C21: 0.27300242 | D21: -0.60874817 | E21: 0.54582156 | F21: -0.71638993 | G21: 0.38401048 | H21: -0.71638993 | I21: 0.38401048

Sheet UberSelect
A1: STATE | B1: FULLNAME | C1: TollShare | D1: LN(S/(1-S)) | E1: TollMile1963 | F1: Population | G1: OldTollMileRatio | H1: Workers Who Live OOS (JTW) | I1: Ro | J1: ResidentsWhoWorkInState | K1: AVG-Neighbor-1 | L1: Land | M1: Density | N1: Percent Federal Lands | Q1: Yhat-OLS-Final2 | T1: Disburse | U1: Cap | V1: NonCap
A2: AL | B2: ALABAMA | C2: 0 | D2: =LN(C2/(1-C2)) -> #VALUE! | E2: 0 | F2: 4252982 | G2: 0 | H2: 0.023851877 | I2: =1-J2 -> 0.035998518 | J2: 0.96400148 | K2: 0.0010378069 | L2: 50750 | M2: 83.802601 | N2: 0.03281 | Q2: 0.0020315369 | R2: =B2 -> ALABAMA | S2: Alabama | T2: 1001737 | U2: 436663 | V2: 565074 | W2: Alaska | X2: 438198 | Y2: 254068
A3: AZ | B3: ARIZONA | C3: 0 | D3: =LN(C3/(1-C3)) -> #VALUE! | E3: 0 | F3: 4217940 | G3: 0 | H3: 0.011207188 | I3: =1-J3 -> 0.015804395 | J3: 0.98419561 | K3: 0.0011052052 | L3: 113642 | M3: 37.116031 | N3: 0.41534 | Q3: -0.0087985576 | R3: =B3 -> ARIZONA | S3: Arizona | T3: 1199273 | U3: 454795 | V3: 744478 | W3: Dist. of Col. | X3: 139758 | Y3: 78060
A4: AR | B4: ARKANSAS | C4: 0 | D4: =LN(C4/(1-C4)) -> #VALUE! | E4: 0 | F4: 2483769 | G4: 0 | H4: 0.040294187 | I4: =1-J4 -> 0.03229638 | J4: 0.96770362 | K4: 0.00096823265 | L4: 52075 | M4: 47.695996 | N4: 0.08266 | Q4: 0.0091626078 | R4: =B4 -> ARKANSAS | S4: Arkansas | T4: 665735 | U4: 370697 | V4: 295038
A5: CA | B5: CALIFORNIA | C5: 0.021141521 | D5: =LN(C5/(1-C5)) -> -3.8351481 | E5: 0 | F5: 31589153 | G5: 0 | H5: 0.0045230302 | I5: =1-J5 -> 0.003689812 | J5: 0.99631019 | K5: 0.0010374397 | L5: 155973 | M5: 202.52962 | N5: 0.44598 | Q5: 0.090395311 | R5: =B5 -> CALIFORNIA | S5: California | T5: 5966475 | U5: 2348070 | V5: 3618405
A6: CO | B6: COLORADO | C6: 0.0029577777 | D6: =LN(C6/(1-C6)) -> -5.8203549 | E6: 17.3 | F6: 3746585 | G6: 0.014786325 | H6: 0.0079445411 | I6: =1-J6 -> 0.010250283 | J6: 0.98974972 | K6: 0.0009007506 | L6: 103730 | M6: 36.118625 | N6: 0.35954 | Q6: -0.0089372041 | R6: =B6 -> COLORADO | S6: Colorado | T6: 922112 | U6: 378603 | V6: 543509
A7: CT | B7: CONNECTICUT | C7: 0.00025988579 | D7: =LN(C7/(1-C7)) -> -8.2550084 | E7: 193.9 | F7: 3274662 | G7: 0.35774908 | H7: 0.045612423 | I7: =1-J7 -> 0.047445028 | J7: 0.95255497 | K7: 0.012794545 | L7: 4845 | M7: 675.88483 | N7: 0.00238 | Q7: 0.12620393 | R7: =B7 -> CONNECTICUT | S7: Connecticut | T7: 1153096 | U7: 596585 | V7: 556511
A8: DE | B8: DELAWARE | C8: 0.25259005 | D8: =LN(C8/(1-C8)) -> -1.084846 | E8: 11.2 | F8: 717197 | G8: 0.21960784 | H8: 0.13832888 | I8: =1-J8 -> 0.095045716 | J8: 0.90495428 | K8: 0.011952304 | L8: 1955 | M8: 366.85269 | N8: 0.02219 | Q8: 0.15290266 | R8: =B8 -> DELAWARE | S8: Delaware | T8: 441222 | U8: 240412 | V8: 200810
A9: FL | B9: FLORIDA | C9: 0.077833555 | D9: =LN(C9/(1-C9)) -> -2.4721531 | E9: 206.6 | F9: 14165570 | G9: 0.11101558 | H9: 0.0079942105 | I9: =1-J9 -> 0.009986905 | J9: 0.9900131 | K9: 0.0013827027 | L9: 53997 | M9: 262.33994 | N9: 0.07562 | Q9: 0.059825541 | R9: =B9 -> FLORIDA | S9: Florida | T9: 3421260 | U9: 2103664 | V9: 1317596
A10: GA | B10: GEORGIA | C10: 0.0041858291 | D10: =LN(C10/(1-C10)) -> -5.4718559 | E10: 11.1 | F10: 7200882 | G10: 0.0078556263 | H10: 0.028137824 | I10: =1-J10 -> 0.023891522 | J10: 0.97610848 | K10: 0.00099897011 | L10: 57919 | M10: 124.32677 | N10: 0.03892 | Q10: 0.019300974 | R10: =B10 -> GEORGIA | S10: Georgia | T10: 1436829 | U10: 881477 | V10: 555352
A11: HI | B11: HAWAII | C11: 0 | D11: =LN(C11/(1-C11)) -> #VALUE! | E11: 0 | F11: 1186815 | G11: 0 | H11: 0.0095240957 | I11: =1-J11 -> 0.0046752296 | J11: 0.99532477 | K11: 0.0025331665 | L11: 6423 | M11: 184.77581 | N11: 0.08548 | Q11: -0.021829682 | R11: =B11 -> HAWAII | S11: Hawaii | T11: 359706 | U11: 214054 | V11: 145652
A12: ID | B12: IDAHO | C12: 0 | D12: =LN(C12/(1-C12)) -> #VALUE! | E12: 0 | F12: 1163261 | G12: 0 | H12: 0.026148588 | I12: =1-J12 -> 0.039782418 | J12: 0.96021758 | K12: 0.0011444505 | L12: 82751 | M12: 14.057365 | N12: 0.60588 | Q12: -0.0078611245 | R12: =B12 -> IDAHO | S12: Idaho | T12: 349964 | U12: 165509 | V12: 184455
A13: IL | B13: ILLINOIS | C13: 0.092502027 | D13: =LN(C13/(1-C13)) -> -2.2834608 | E13: 185.3 | F13: 11829940 | G13: 0.082538976 | H13: 0.028193774 | I13: =1-J13 -> 0.02868334 | J13: 0.97131666 | K13: 0.00067228915 | L13: 55593 | M13: 212.7955 | N13: 0.01266 | Q13: 0.059439332 | R13: =B13 -> ILLINOIS | S13: Illinois | T13: 3006384 | U13: 1575878 | V13: 1430506
A14: IN | B14: INDIANA | C14: 0.042572953 | D14: =LN(C14/(1-C14)) -> -3.1130304 | E14: 156.9 | F14: 5803471 | G14: 0.12041443 | H14: 0.032808242 | I14: =1-J14 -> 0.048289858 | J14: 0.95171014 | K14: 0.0026257318 | L14: 35870 | M14: 161.79178 | N14: 0.01725 | Q14: 0.051601285 | R14: =B14 -> INDIANA | S14: Indiana | T14: 1433178 | U14: 650052 | V14: 783126
A15: IA | B15: IOWA | C15: 0.001073349 | D15: =LN(C15/(1-C15)) -> -6.8358977 | E15: 0 | F15: 2841764 | G15: 0 | H15: 0.036918432 | I15: =1-J15 -> 0.042984874 | J15: 0.95701513 | K15: 0.0017501896 | L15: 55875 | M15: 50.859311 | N15: 0.00187 | Q15: 0.0076792201 | R15: =B15 -> IOWA | S15: Iowa | T15: 1077704 | U15: 459382 | V15: 618322
... A50: WY | B50: WYOMING | C50: 0 | D50: =LN(C50/(1-C50)) -> #VALUE! | E50: 0 | F50: 480184 | G50: 0 | H50: 0.025620995 | I50: =1-J50 -> 0.020060442 | J50: 0.97993956 | K50: 0.00067440495 | L50: 97105 | M50: 4.9449977 | N50: 0.48452 | Q50: -0.010924129 | R50: =B50 -> WYOMING | S50: Wyoming | T50: 271998 | U50: 160300 | V50: 111698
G51: 0 | R51: =B51 -> 0
G52: 0 | R52: =B52 -> 0
G53: 0
G54: 0 | U54: 32500624
G55: 0
G56: 0

Sheet 2sls
A1: SUMMARY OUTPUT
A3: Regression Statistics
A4: Multiple R | B4: 0.80925394
A5: R Square | B5: 0.65489194
A6: Adjusted R Square | B6: 0.61476309
A7: Standard Error | B7: 0.045296159
A8: Observations | B8: 49
A10: ANOVA
B11: df | C11: SS | D11: MS | E11: F | F11: Significance F
A12: Regression | B12: 5 | C12: 0.16741939 | D12: 0.033483878 | E12: 16.319731 | F12: 5.2145699e-09
A13: Residual | B13: 43 | C13: 0.088224908 | D13: 0.002051742
A14: Total | B14: 48 | C14: 0.2556443
B16: Coefficients | C16: Standard Error | D16: t Stat | E16: P-value | F16: Lower 95% | G16: Upper 95% | H16: Lower 95.0% | I16: Upper 95.0%
A17: Intercept | B17: -0.0024597021 | C17: 0 | D17: 65535 | E17: =#REF! -> #NUM! | F17: -0.0024597021 | G17: -0.0024597021 | H17: -0.0024597021 | I17: -0.0024597021
A18: Population | B18: 2.7361357e-10 | C18: 0 | D18: 65535 | E18: =#REF! -> #NUM! | F18: 2.7361357e-10 | G18: 2.7361357e-10 | H18: 2.7361357e-10 | I18: 2.7361357e-10
A19: OldTollMileRatio | B19: 0.021384647 | C19: 0 | D19: 65535 | E19: =#REF! -> #NUM! | F19: 0.021384647 | G19: 0.021384647 | H19: 0.021384647 | I19: 0.021384647
A20: Workers Who Live OOS (JTW) | B20: 0.060420019 | C20: 0 | D20: 65535 | E20: =#REF! -> #NUM! | F20: 0.060420019 | G20: 0.060420019 | H20: 0.060420019 | I20: 0.060420019
A21: N1^4 | B21: 6419.7695 | C21: 0 | D21: 65535 | E21: =#REF! -> #NUM! | F21: 6419.7695 | G21: 6419.7695 | H21: 6419.7695 | I21: 6419.7695
A22: Yhat | B22: 0.92857143 | C22: 0 | D22: 65535 | E22: =#REF! -> #NUM! | F22: 0.92857143 | G22: 0.92857143 | H22: 0.92857143 | I22: 0.92857143

Sheet NL-NL-f(P,M,O,N,TotExp)
A1: SUMMARY OUTPUT
A3: Regression Statistics
A4: Multiple R | B4: 0.81486345
A5: R Square | B5: 0.66400245
A6: Adjusted R Square | B6: 0.62493296
A7: Standard Error | B7: 0.044694274
A8: Observations | B8: 49
A10: ANOVA
B11: df | C11: SS | D11: MS | E11: F | F11: Significance F
A12: Regression | B12: 5 | C12: 0.16974844 | D12: 0.033949688 | E12: 16.995424 | F12: 2.9909657e-09
A13: Residual | B13: 43 | C13: 0.085895859 | D13: 0.0019975781
A14: Total | B14: 48 | C14: 0.2556443
B16: Coefficients | C16: Standard Error | D16: t Stat | E16: P-value | F16: Lower 95% | G16: Upper 95% | H16: Lower 95.0% | I16: Upper 95.0%
A17: Intercept | B17: -0.062720501 | C17: 0.029799016 | D17: -2.1047843 | E17: 0.041191395 | F17: -0.1228159 | G17: -0.0026250986 | H17: -0.1228159 | I17: -0.0026250986
A18: Population | B18: 4.4164686e-09 | C18: 1.3132292e-09 | D18: 3.3630601 | E18: 0.0016285474 | F18: 1.7680914e-09 | G18: 7.0648458e-09 | H18: 1.7680914e-09 | I18: 7.0648458e-09
A19: OldTollMileRatio | B19: 0.29136084 | C19: 0.072781519 | D19: 4.0032255 | E19: 0.00024266246 | F19: 0.14458302 | G19: 0.43813866 | H19: 0.14458302 | I19: 0.43813866
A20: Workers Who Live OOS (JTW) | B20: 0.7222294 | C20: 0.31059612 | D20: 2.3253008 | E20: 0.024842427 | F20: 0.095853059 | G20: 1.3486057 | H20: 0.095853059 | I20: 1.3486057
A21: N1^4 | B21: 100094.93 | C21: 53428.18 | D21: 1.8734483 | E21: 0.067813429 | F21: -7653.1892 | G21: 207843.05 | H21: -7653.1892 | I21: 207843.05
A22: Expend/Pop | B22: 0.099820079 | C22: 0.092444371 | D22: 1.0797854 | E22: 0.28625725 | F22: -0.086611635 | G22: 0.28625179 | H22: -0.086611635 | I22: 0.28625179

Sheet NL-NL-f(P,M,O,N,NonCap)
A1: SUMMARY OUTPUT
A3: Regression Statistics
A4: Multiple R | B4: 0.81355473
A5: R Square | B5: 0.6618713
A6: Adjusted R Square | B6: 0.62255401
A7: Standard Error | B7: 0.044835792
A8: Observations | B8: 49
A10: ANOVA
B11: df | C11: SS | D11: MS | E11: F | F11: Significance F
A12: Regression | B12: 5 | C12: 0.16920362 | D12: 0.033840725 | E12: 16.834102 | F12: 3.4110898e-09
A13: Residual | B13: 43 | C13: 0.086440674 | D13: 0.0020102482
A14: Total | B14: 48 | C14: 0.2556443
B16: Coefficients | C16: Standard Error | D16: t Stat | E16: P-value | F16: Lower 95% | G16: Upper 95% | H16: Lower 95.0% | I16: Upper 95.0%
A17: Intercept | B17: -0.057934969 | C17: 0.028727305 | D17: -2.0167214 | E17: 0.049996828 | F17: -0.11586906 | G17: -8.7784005e-07 | H17: -0.11586906 | I17: -8.7784005e-07
A18: Population | B18: 4.1903996e-09 | C18: 1.2590087e-09 | D18: 3.3283327 | E18: 0.001798244 | F18: 1.6513685e-09 | G18: 6.7294308e-09 | H18: 1.6513685e-09 | I18: 6.7294308e-09
A19: OldTollMileRatio | B19: 0.28782253 | C19: 0.073660034 | D19: 3.9074449 | E19: 0.00032533717 | F19: 0.13927301 | G19: 0.43637204 | H19: 0.13927301 | I19: 0.43637204
A20: Workers Who Live OOS (JTW) | B20: 0.78613232 | C20: 0.2964914 | D20: 2.6514507 | E20: 0.011176553 | F20: 0.18820084 | G20: 1.3840638 | H20: 0.18820084 | I20: 1.3840638
A21: N1^4 | B21: 93125.486 | C21: 52862.542 | D21: 1.7616536 | E21: 0.085236712 | F21: -13481.917 | G21: 199732.89 | H21: -13481.917 | I21: 199732.89
A22: NonCap/Pop | B22: 0.165183 | C22: 0.17533327 | D22: 0.94210869 | E22: 0.35140012 | F22: -0.18841 | G22: 0.518776 | H22: -0.18841 | I22: 0.518776

Sheet Sheet22
A1: FULLNAME | B1: TollShare | C1: LN(S/1-S) | D1: NonTollShare | E1: LN(S/1-S) | F1: =A1 -> FULLNAME | G1: Binary | H1: Population | I1: OldTollMileRatio | J1: Workers Who Live OOS (JTW) | K1: Yhat | L1: AVG-Neighbor-2 | M1: N1^4 | O1: S*Ow | P1: (1-S)*(1-Ow) | Q1: S*(1-Ow) | R1: (1-S)*Ow
A2: ALABAMA | B2: 0 | C2: =LN(B2/(1-B2)) -> #VALUE! | D2: =1-B2 -> 1 | E2: =LN(D2/(1-D2)) -> #DIV/0! | F2: =A2 -> ALABAMA | G2: =IF(B2>0,1,0) -> 0 | H2: 4252982 | I2: 0 | J2: 0.023851877 | K2: =Sheet21!$B$17+Sheet21!$B$18*H2+Sheet21!$B$19*I2+Sheet21!$B$20*J2 -> -0.0063599856 | L2: 0.016641465 | M2: 1.1600218e-12 | O2: =B2*J2 -> 0 | P2: =(1-B2)*(1-J2) -> 0.97614812 | Q2: =B2*(1-J2) -> 0 | R2: =(1-B2)*J2 -> 0.023851877
A3: ARIZONA | B3: 0 | C3: =LN(B3/(1-B3)) -> #VALUE! | D3: =1-B3 -> 1 | E3: =LN(D3/(1-D3)) -> #DIV/0! | F3: =A3 -> ARIZONA | G3: =IF(B3>0,1,0) -> 0 | H3: 4217940 | I3: 0 | J3: 0.011207188 | K3: =Sheet21!$B$17+Sheet21!$B$18*H3+Sheet21!$B$19*I3+Sheet21!$B$20*J3 -> -0.019074388 | L3: 0.021735556 | M3: 1.4920096e-12 | O3: =B3*J3 -> 0 | P3: =(1-B3)*(1-J3) -> 0.98879281 | Q3: =B3*(1-J3) -> 0 | R3: =(1-B3)*J3 -> 0.011207188
A4: ARKANSAS | B4: 0 | C4: =LN(B4/(1-B4)) -> #VALUE! | D4: =1-B4 -> 1 | E4: =LN(D4/(1-D4)) -> #DIV/0! | F4: =A4 -> ARKANSAS | G4: =IF(B4>0,1,0) -> 0 | H4: 2483769 | I4: 0 | J4: 0.040294187 | K4: =Sheet21!$B$17+Sheet21!$B$18*H4+Sheet21!$B$19*I4+Sheet21!$B$20*J4 -> 0.0021231117 | L4: 0.020268432 | M4: 8.7885835e-13 | O4: =B4*J4 -> 0 | P4: =(1-B4)*(1-J4) -> 0.95970581 | Q4: =B4*(1-J4) -> 0 | R4: =(1-B4)*J4 -> 0.040294187
A5: CALIFORNIA | B5: 0.021141521 | C5: =LN(B5/(1-B5)) -> -3.8351481 | D5: =1-B5 -> 0.97885848 | E5: =LN(D5/(1-D5)) -> 3.8351481 | F5: =A5 -> CALIFORNIA | G5: =IF(B5>0,1,0) -> 1 | H5: 31589153 | I5: 0 | J5: 0.0045230302 | K5: =Sheet21!$B$17+Sheet21!$B$18*H5+Sheet21!$B$19*I5+Sheet21!$B$20*J5 -> 0.095697965 | L5: 0.046286746 | M5: 1.1583812e-12 | O5: =B5*J5 -> 9.562374e-05 | P5: =(1-B5)*(1-J5) -> 0.97443107 | Q5: =B5*(1-J5) -> 0.021045898 | R5: =(1-B5)*J5 -> 0.0044274065
A6: COLORADO | B6: 0.0029577777 | C6: =LN(B6/(1-B6)) -> -5.8203549 | D6: =1-B6 -> 0.99704222 | E6: =LN(D6/(1-D6)) -> 5.8203549 | F6: =A6 -> COLORADO | G6: =IF(B6>0,1,0) -> 1 | H6: 3746585 | I6: 0.014786325 | J6: 0.0079445411 | K6: =Sheet21!$B$17+Sheet21!$B$18*H6+Sheet21!$B$19*I6+Sheet21!$B$20*J6 -> -0.019158967 | L6: 0.038557176 | M6: 6.5829148e-13 | O6: =B6*J6 -> 2.3498187e-05 | P6: =(1-B6)*(1-J6) -> 0.98912118 | Q6: =B6*(1-J6) -> 0.0029342795 | R6: =(1-B6)*J6 -> 0.007921043
A7: CONNECTICUT | B7: 0.00025988579 | C7: =LN(B7/(1-B7)) -> -8.2550084 | D7: =1-B7 -> 0.99974011 | E7: =LN(D7/(1-D7)) -> 8.2550084 | F7: =A7 -> CONNECTICUT | G7: =IF(B7>0,1,0) -> 1 | H7: 3274662 | I7: 0.35774908 | J7: 0.045612423 | K7: =Sheet21!$B$17+Sheet21!$B$18*H7+Sheet21!$B$19*I7+Sheet21!$B$20*J7 -> 0.13785645 | L7: 0.26023043 | M7: 2.6797815e-08 | O7: =B7*J7 -> 1.185402e-05 | P7: =(1-B7)*(1-J7) -> 0.95413955 | Q7: =B7*(1-J7) -> 0.00024803176 | R7: =(1-B7)*J7 -> 0.045600569
A8: DELAWARE | B8: 0.25259005 | C8: =LN(B8/(1-B8)) -> -1.084846 | D8: =1-B8 -> 0.74740995 | E8: =LN(D8/(1-D8)) -> 1.084846 | F8: =A8 -> DELAWARE | G8: =IF(B8>0,1,0) -> 1 | H8: 717197 | I8: 0.21960784 | J8: 0.13832888 | K8: =Sheet21!$B$17+Sheet21!$B$18*H8+Sheet21!$B$19*I8+Sheet21!$B$20*J8 -> 0.16958237 | L8: 0.11872671 | M8: 2.0408282e-08 | O8: =B8*J8 -> 0.034940497 | P8: =(1-B8)*(1-J8) -> 0.64402157 | Q8: =B8*(1-J8) -> 0.21764955 | R8: =(1-B8)*J8 -> 0.10338838
A9: FLORIDA | B9: 0.077833555 | C9: =LN(B9/(1-B9)) -> -2.4721531 | D9: =1-B9 -> 0.92216645 | E9: =LN(D9/(1-D9)) -> 2.4721531 | F9: =A9 -> FLORIDA | G9: =IF(B9>0,1,0) -> 1 | H9: 14165570 | I9: 0.11101558 | J9: 0.0079942105 | K9: =Sheet21!$B$17+Sheet21!$B$18*H9+Sheet21!$B$19*I9+Sheet21!$B$20*J9 -> 0.061251926 | L9: 0.062671969 | M9: 3.6552342e-12 | O9: =B9*J9 -> 0.00062221782 | P9: =(1-B9)*(1-J9) -> 0.91479445 | Q9: =B9*(1-J9) -> 0.077211337 | R9: =(1-B9)*J9 -> 0.0073719926
A10: GEORGIA | B10: 0.0041858291 | C10: =LN(B10/(1-B10)) -> -5.4718559 | D10: =1-B10 -> 0.99581417 | E10: =LN(D10/(1-D10)) -> 5.4718559 | F10: =A10 -> GEORGIA | G10: =IF(B10>0,1,0) -> 1 | H10: 7200882 | I10: 0.0078556263 | J10: 0.028137824 | K10: =Sheet21!$B$17+Sheet21!$B$18*H10+Sheet21!$B$19*I10+Sheet21!$B$20*J10 -> 0.013760456 | L10: 0.02061609 | M10: 9.9588679e-13 | O10: =B10*J10 -> 0.00011778012 | P10: =(1-B10)*(1-J10) -> 0.96779413 | Q10: =B10*(1-J10) -> 0.004068049 | R10: =(1-B10)*J10 -> 0.028020044
A11: HAWAII | B11: 0 | C11: =LN(B11/(1-B11)) -> #VALUE! | D11: =1-B11 -> 1 | E11: =LN(D11/(1-D11)) -> #DIV/0! | F11: =A11 -> HAWAII | G11: =IF(B11>0,1,0) -> 0 | H11: 1186815 | I11: 0 | J11: 0.0095240957 | K11: =Sheet21!$B$17+Sheet21!$B$18*H11+Sheet21!$B$19*I11+Sheet21!$B$20*J11 -> -0.034191309 | L11: 0.035368224 | M11: 4.1177025e-11 | O11: =B11*J11 -> 0 | P11: =(1-B11)*(1-J11) -> 0.9904759 | Q11: =B11*(1-J11) -> 0 | R11: =(1-B11)*J11 -> 0.0095240957
A12: IDAHO | B12: 0 | C12: =LN(B12/(1-B12)) -> #VALUE! | D12: =1-B12 -> 1 | E12: =LN(D12/(1-D12)) -> #DIV/0! | F12: =A12 -> IDAHO | G12: =IF(B12>0,1,0) -> 0 | H12: 1163261 | I12: 0 | J12: 0.026148588 | K12: =Sheet21!$B$17+Sheet21!$B$18*H12+Sheet21!$B$19*I12+Sheet21!$B$20*J12 -> -0.017783999 | L12: 0.025523251 | M12: 1.7154896e-12 | O12: =B12*J12 -> 0 | P12: =(1-B12)*(1-J12) -> 0.97385141 | Q12: =B12*(1-J12) -> 0 | R12: =(1-B12)*J12 -> 0.026148588
A13: ILLINOIS | B13: 0.092502027 | C13: =LN(B13/(1-B13)) -> -2.2834608 | D13: =1-B13 -> 0.90749797 | E13: =LN(D13/(1-D13)) -> 2.2834608 | F13: =A13 -> ILLINOIS | G13: =IF(B13>0,1,0) -> 1 | H13: 11829940 | I13: 0.082538976 | J13: 0.028193774 | K13: =Sheet21!$B$17+Sheet21!$B$18*H13+Sheet21!$B$19*I13+Sheet21!$B$20*J13 -> 0.060849752 | L13: 0.013967169 | M13: 2.0427933e-13 | O13: =B13*J13 -> 0.0026079813 | P13: =(1-B13)*(1-J13) -> 0.88191218 | Q13: =B13*(1-J13) -> 0.089894046 | R13: =(1-B13)*J13 -> 0.025585793
... A50: WYOMING | B50: 0 | C50: =LN(B50/(1-B50)) -> #VALUE! | D50: =1-B50 -> 1 | E50: =LN(D50/(1-D50)) -> #DIV/0! | F50: =A50 -> WYOMING | G50: =IF(B50>0,1,0) -> 0 | H50: 480184 | I50: 0 | J50: 0.025620995 | K50: =Sheet21!$B$17+Sheet21!$B$18*H50+Sheet21!$B$19*I50+Sheet21!$B$20*J50 -> -0.021337958 | L50: 0.011513892 | M50: 2.0686308e-13 | O50: =B50*J50 -> 0 | P50: =(1-B50)*(1-J50) -> 0.974379 | Q50: =B50*(1-J50) -> 0 | R50: =(1-B50)*J50 -> 0.025620995
A52: XLSTAT - Models for Binary Response Data / Started on 12/4/98 at 11:18:46 AM
A53: Input data :
A54: Binary response : Workbook = Levinson-stat.xls / Sheet = Sheet22 / Range = $g$1:$g$50
A55: Numerical variables : Workbook = Levinson-stat.xls / Sheet = Sheet22 / Range = $K$1:$L$50
A56: Categorical variables : None
A57: Probit Model
A60: Numerical data summary :
A62: Variable | B62: Mean | C62: Std. dev.
A63: Yhat | B63: 0.03832306 | C63: 0.061931827
A64: N1 | B64: 0.0034698356 | C64: 0.0054679668
A68: Maximum Likelihood estimators for parameters :
A70: Parameter | B70: Value | C70: Std dev. | D70: Chi-Sq | E70: Prob>Chi-Sq
A71: Intercept | B71: 0.28796244 | C71: 0.2446273 | D71: 1.3856765 | E71: 0.23913672
A72: Yhat | B72: 40.995602 | C72: 3.6569216 | D72: 125.67336 | E72: 0.0001
A73: N1 | B73: -58.4564 | C73: 43.871906 | D73: 1.7753792 | E73: 0.18271783 | G73: =B73/C73 -> -1.3324335
A76: Goodness of fit evaluation :
A77: total obs. | B77: Log Like. | C77: Log Like. (indep) | D77: Pearson Chi-Sq | E77: DF (Chi-Sq) | F77: Prob>Pearson Chi-Sq | G77: L.R. Chi-Sq | H77: DF (L.R. Chi-Sq) | I77: Prob>L.R. Chi-Sq | J77: R2 | K77: R2 (McFadden)
A78: 49 | B78: -17.374796 | C78: -30.182184 | D78: 29.405238 | E78: 46 | F78: 0.97290175 | G78: 25.614776 | H78: 2 | I78: 0.0001 | J78: 0.42399902 | K78: 0.42433603
A80: Predictions and residuals :
A82: Observations | C82: Yhat | D82: N1 | E82: Binary | F82: Fitted Probit | G82: Indep. model | H82: Binary / | I82: Fitted prop. | J82: Res. on Probit | K82: Res. on Indep model
A83: Obs 1 | B83: 1 | C83: -0.0063599856 | D83: 0.0010378069 | E83: 0 | F83: 0.48666361 | G83: 0.69387755 | H83: 0 | I83: 0.48666361 | J83: -0.97367364 | K83: -1.5055453
A84: Obs 2 | B84: 1 | C84: -0.019074388 | D84: 0.0011052052 | E84: 0 | F84: 0.28821397 | G84: 0.69387755 | H84: 0 | I84: 0.28821397 | J84: -0.63633056 | K84: -1.5055453
A85: Obs 3 | B85: 1 | C85: 0.0021231117 | D85: 0.00096823265 | E85: 0 | F85: 0.62490965 | G85: 0.69387755 | H85: 0 | I85: 0.62490965 | J85: -1.2907456 | K85: -1.5055453
A86: Obs 4 | B86: 1 | C86: 0.095697965 | D86: 0.0010374397 | E86: 1 | F86: 0.9999834 | G86: 0.69387755 | H86: 1 | I86: 0.9999834 | J86: 0.0040738801 | K86: 0.66421116
A87: Obs 5 | B87: 1 | C87: -0.019158967 | D87: 0.0009007506 | E87: 1 | F87: 0.2911166 | G87: 0.69387755 | H87: 1 | I87: 0.2911166 | J87: 1.5604646 | K87: 0.66421116
A88: Obs 6 | B88: 1 | C88: 0.13785645 | D88: 0.012794545 | E88: 1 | F88: 0.9999999 | G88: 0.69387755 | H88: 1 | I88: 0.9999999 | J88: 0.00032322456 | K88: 0.66421116
A89: Obs 7 | B89: 1 | C89: 0.16958237 | D89: 0.011952304 | E89: 1 | F89: 1 | G89: 0.69387755 | H89: 1 | I89: 1 | J89: 5.5340513e-06 | K89: 0.66421116
A90: Obs 8 | B90: 1 | C90: 0.061251926 | D90: 0.0013827027 | E90: 1 | F90: 0.99671798 | G90: 0.69387755 | H90: 1 | I90: 0.99671798 | J90: 0.057383135 | K90: 0.66421116
A91: Obs 9 | B91: 1 | C91: 0.013760456 | D91: 0.00099897011 | E91: 1 | F91: 0.78631048 | G91: 0.69387755 | H91: 1 | I91: 0.78631048 | J91: 0.52130824 | K91: 0.66421116
A92: Obs 10 | B92: 1 | C92: -0.034191309 | D92: 0.0025331665 | E92: 0 | F92: 0.10350854 | G92: 0.69387755 | H92: 0 | I92: 0.10350854 | J92: -0.33979345 | K92: -1.5055453
A93: Obs 11 | B93: 1 | C93: -0.017783999 | D93: 0.0011444505 | E93: 0 | F93: 0.30572534 | G93: 0.69387755 | H93: 0 | I93: 0.30572534 | J93: -0.66359035 | K93: -1.5055453
A94: Obs 12 | B94: 1 | C94: 0.060849752 | D94: 0.00067228915 | E94: 1 | F94: 0.99695809 | G94: 0.69387755 | H94: 1 | I94: 0.99695809 | J94: 0.055237603 | K94: 0.66421116
... A131: Obs 49 | B131: 1 | C131: -0.021337958 | D131: 0.00067440495 | E131: 0 | F131: 0.26558419 | G131: 0.69387755 | H131: 0 | I131: 0.26558419 | J131: -0.60135386 | K131: -1.5055453
A140: XLSTAT - Models for Binary Response Data / Started on 12/4/98 at 11:25:12 AM
A141: Input data :
A142: Binary response : Workbook = Levinson-stat.xls / Sheet = Sheet22 / Range = $f$1:$g$50
A143: Numerical variables : Workbook = Levinson-stat.xls / Sheet = Sheet22 / Range = $K$1:$L$50
A144: Categorical variables : None
A145: Probit Model
A148: Numerical data summary :
A150: Variable | B150: Mean | C150: Std. dev.
A151: Yhat | B151: 0.03832306 | C151: 0.061931827
A152: N1^4 | B152: 2.3050017e-08 | C152: 1.3983592e-07
A156: Maximum Likelihood estimators for parameters :
A158: Parameter | B158: Value | C158: Std dev. | D158: Chi-Sq | E158: Prob>Chi-Sq
A159: Intercept | B159: 0.19172173 | C159: 0.24057593 | D159: 0.63509447 | E159: 0.42549276
A160: Yhat | B160: 39.35385 | C160: 6.8677359 | D160: 32.835777 | E160: 0.0001
A161: N1^4 | B161: -5310294.6 | C161: 10771593 | D161: 0.24303978 | E161: 0.62201919
A164: Goodness of fit evaluation :
A165: total obs. | B165: Log Like. | C165: Log Like. (indep) | D165: Pearson Chi-Sq | E165: DF (Chi-Sq) | F165: Prob>Pearson Chi-Sq | G165: L.R. Chi-Sq | H165: DF (L.R. Chi-Sq) | I165: Prob>L.R. Chi-Sq | J165: R2 | K165: R2 (McFadden)
A166: 49 | B166: -17.466819 | C166: -30.182184 | D166: 29.310372 | E166: 46 | F166: 0.97372896 | G166: 25.43073 | H166: 2 | I166: 0.0001 | J166: 0.41806978 | K166: 0.42128711
A168: Predictions and residuals :
A170: Observations | C170: Yhat | D170: N1^4 | E170: Binary | F170: Fitted Probit | G170: Indep. model | H170: Binary / | I170: Fitted prop. | J170: Res. on Probit | K170: Res. on Indep model
A171: ALABAMA | B171: 1 | C171: -0.0063599856 | D171: 1.1600218e-12 | E171: 0 | F171: 0.4766455 | G171: 0.69387755 | H171: 0 | I171: 0.4766455 | J171: -0.95433261 | K171: -1.5055453
A172: ARIZONA | B172: 1 | C172: -0.019074388 | D172: 1.4920096e-12 | E172: 0 | F172: 0.2881024 | G172: 0.69387755 | H172: 0 | I172: 0.2881024 | J172: -0.63615753 | K172: -1.5055453
A173: ARKANSAS | B173: 1 | C173: 0.0021231117 | D173: 8.7885835e-13 | E173: 0 | F173: 0.60844541 | G173: 0.69387755 | H173: 0 | I173: 0.60844541 | J173: -1.2465642 | K173: -1.5055453
A174: CALIFORNIA | B174: 1 | C174: 0.095697965 | D174: 1.1583812e-12 | E174: 1 | F174: 0.99996216 | G174: 0.69387755 | H174: 1 | I174: 0.99996216 | J174: 0.0061514045 | K174: 0.66421116
A175: COLORADO | B175: 1 | C175: -0.019158967 | D175: 6.5829148e-13 | E175: 1 | F175: 0.28696911 | G175: 0.69387755 | H175: 1 | I175: 0.28696911 | J175: 1.5762917 | K175: 0.66421116
A176: CONNECTICUT | B176: 1 | C176: 0.13785645 | D176: 2.6797815e-08 | E176: 1 | F176: 0.99999998 | G176: 0.69387755 | H176: 1 | I176: 0.99999998 | J176: 0.00014825003 | K176: 0.66421116
A177: DELAWARE | B177: 1 | C177: 0.16958237 | D177: 2.0408282e-08 | E177: 1 | F177: 1 | G177: 0.69387755 | H177: 1 | I177: 1 | J177: 2.6609944e-06 | K177: 0.66421116
A178: FLORIDA | B178: 1 | C178: 0.061251926 | D178: 3.6552342e-12 | E178: 1 | F178: 0.99536859 | G178: 0.69387755 | H178: 1 | I178: 0.99536859 | J178: 0.068212577 | K178: 0.66421116
A179: GEORGIA | B179: 1 | C179: 0.013760456 | D179: 9.9588679e-13 | E179: 1 | F179: 0.76829506 | G179: 0.69387755 | H179: 1 | I179: 0.76829506 | J179: 0.54916597 | K179: 0.66421116
A180: HAWAII | B180: 1 | C180: -0.034191309 | D180: 4.1177025e-11 | E180: 0 | F180: 0.12423854 | G180: 0.69387755 | H180: 0 | I180: 0.12423854 | J180: -0.37664765 | K180: -1.5055453
A181: IDAHO | B181: 1 | C181: -0.017783999 | D181: 1.7154896e-12 | E181: 0 | F181: 0.30567188 | G181: 0.69387755 | H181: 0 | I181: 0.30567188 | J181: -0.66350679 | K181: -1.5055453
A182: ILLINOIS | B182: 1 | C182: 0.060849752 | D182: 2.0427933e-13 | E182: 1 | F182: 0.99515065 | G182: 0.69387755 | H182: 1 | I182: 0.99515065 | J182: 0.069806744 | K182: 0.66421116
... A219: WYOMING | B219: 1 | C219: -0.021337958 | D219: 2.0686308e-13 | E219: 0 | F219: 0.25848912 | G219: 0.69387755 | H219: 0 | I219: 0.25848912 | J219: -0.59042178 | K219: -1.5055453
A240: XLSTAT - Models for Binary Response Data / Started on 12/4/98 at 11:27:11 AM
A241: Input data :
A242: Binary response : Workbook = Levinson-stat.xls / Sheet = Sheet22 / Range = $f$1:$g$50
A243: Numerical variables : Workbook = Levinson-stat.xls / Sheet = Sheet22 / Range = $K$1:$L$50
A244: Categorical variables : None
A245: Logit Model
A248: Numerical data summary :
A250: Variable | B250: Mean | C250: Std. dev.
A251: Yhat | B251: 0.03832306 | C251: 0.061931827
A252: N1 | B252: 0.0034698356 | C252: 0.0054679668
A256: Maximum Likelihood estimators for parameters :
A258: Parameter | B258: Value | C258: Std dev. | D258: Chi-Sq | E258: Prob>Chi-Sq
A259: Intercept | B259: 0.49408675 | C259: 0.5659383 | D259: 0.76219877 | E259: 0.3826413
A260: Yhat | B260: 69.951524 | C260: 26.806986 | D260: 6.8092359 | E260: 0.0090687568
A261: N1 | B261: -105.13949 | C261: 203.94222 | D261: 0.26577704 | E261: 0.60617875
A264: Goodness of fit evaluation :
A265: total obs. | B265: Log Like. | C265: Log Like. (indep) | D265: Pearson Chi-Sq | E265: DF (Chi-Sq) | F265: Prob>Pearson Chi-Sq | G265: L.R. Chi-Sq | H265: DF (L.R. Chi-Sq) | I265: Prob>L.R. Chi-Sq | J265: R2 | K265: R2 (McFadden)
A266: 49 | B266: -17.467077 | C266: -30.182184 | D266: 29.959868 | E266: 46 | F266: 0.96766243 | G266: 25.430213 | H266: 2 | I266: 0.0001 | J266: 0.42352516 | K266: 0.42127855
A268: Predictions and residuals :
A270: Observations | C270: Yhat | D270: N1 | E270: Binary | F270: Fitted Logit | G270: Indep. model | H270: Binary / | I270: Fitted prop. | J270: Res. on Logit | K270: Res. on Indep model
...

Sheet BinaryChoice
A1: FULLNAME | B1: TollShare | C1: LN(S/1-S) | D1: NonTollShare | E1: LN(S/1-S) | F1: =A1 -> FULLNAME | G1: Binary | H1: Population | I1: OldTollMileRatio | J1: Workers Who Live OOS (JTW) | K1: N1 | L1: N1^4 | N1: S*Ow | O1: (1-S)*(1-Ow) | P1: S*(1-Ow) | Q1: (1-S)*Ow
A2: ALABAMA | B2: 0 | C2: =LN(B2/(1-B2)) -> #VALUE! | D2: =1-B2 -> 1 | E2: =LN(D2/(1-D2)) -> #DIV/0! | F2: =A2 -> ALABAMA | G2: =IF(B2>0,1,0) -> 0 | H2: 4252982 | I2: 0 | J2: 0.023851877 | K2: =L2^0.25 -> 0.0010378069 | L2: 1.1600218e-12 | N2: =B2*J2 -> 0 | O2: =(1-B2)*(1-J2) -> 0.97614812 | P2: =B2*(1-J2) -> 0 | Q2: =(1-B2)*J2 -> 0.023851877
A3: ARIZONA | B3: 0 | C3: =LN(B3/(1-B3)) -> #VALUE! | D3: =1-B3 -> 1 | E3: =LN(D3/(1-D3)) -> #DIV/0! | F3: =A3 -> ARIZONA | G3: =IF(B3>0,1,0) -> 0 | H3: 4217940 | I3: 0 | J3: 0.011207188 | K3: =L3^0.25 -> 0.0011052052 | L3: 1.4920096e-12 | N3: =B3*J3 -> 0 | O3: =(1-B3)*(1-J3) -> 0.98879281 | P3: =B3*(1-J3) -> 0 | Q3: =(1-B3)*J3 -> 0.011207188
A4: ARKANSAS | B4: 0 | C4: =LN(B4/(1-B4)) -> #VALUE! | D4: =1-B4 -> 1 | E4: =LN(D4/(1-D4)) -> #DIV/0! | F4: =A4 -> ARKANSAS | G4: =IF(B4>0,1,0) -> 0 | H4: 2483769 | I4: 0 | J4: 0.040294187 | K4: =L4^0.25 -> 0.00096823265 | L4: 8.7885835e-13 | N4: =B4*J4 -> 0 | O4: =(1-B4)*(1-J4) -> 0.95970581 | P4: =B4*(1-J4) -> 0 | Q4: =(1-B4)*J4 -> 0.040294187
A5: CALIFORNIA | B5: 0.021141521 | C5: =LN(B5/(1-B5)) -> -3.8351481 | D5: =1-B5 -> 0.97885848 | E5: =LN(D5/(1-D5)) -> 3.8351481 | F5: =A5 -> CALIFORNIA | G5: =IF(B5>0,1,0) -> 1 | H5: 31589153 | I5: 0 | J5: 0.0045230302 | K5: =L5^0.25 -> 0.0010374397 | L5: 1.1583812e-12 | N5: =B5*J5 -> 9.562374e-05 | O5: =(1-B5)*(1-J5) -> 0.97443107 | P5: =B5*(1-J5) -> 0.021045898 | Q5: =(1-B5)*J5 -> 0.0044274065
A6: COLORADO | B6: 0.0029577777 | C6: =LN(B6/(1-B6)) -> -5.8203549 | D6: =1-B6 -> 0.99704222 | E6: =LN(D6/(1-D6)) -> 5.8203549 | F6: =A6 -> COLORADO | G6: =IF(B6>0,1,0) -> 1 | H6: 3746585 | I6: 0.014786325 | J6: 0.0079445411 | K6: =L6^0.25 -> 0.0009007506 | L6: 6.5829148e-13 | N6: =B6*J6 -> 2.3498187e-05 | O6: =(1-B6)*(1-J6) -> 0.98912118 | P6: =B6*(1-J6) -> 0.0029342795 | Q6: =(1-B6)*J6 -> 0.007921043
A7: CONNECTICUT | B7: 0.00025988579 | C7: =LN(B7/(1-B7)) -> -8.2550084 | D7: =1-B7 -> 0.99974011 | E7: =LN(D7/(1-D7)) -> 8.2550084 | F7: =A7 -> CONNECTICUT | G7: =IF(B7>0,1,0) -> 1 | H7: 3274662 | I7: 0.35774908 | J7: 0.045612423 | K7: =L7^0.25 -> 0.012794545 | L7: 2.6797815e-08 | N7: =B7*J7 -> 1.185402e-05 | O7: =(1-B7)*(1-J7) -> 0.95413955 | P7: =B7*(1-J7) -> 0.00024803176 | Q7: =(1-B7)*J7 -> 0.045600569
A8: DELAWARE | B8: 0.25259005 | C8: =LN(B8/(1-B8)) -> -1.084846 | D8: =1-B8 -> 0.74740995 | E8: =LN(D8/(1-D8)) -> 1.084846 | F8: =A8 -> DELAWARE | G8: =IF(B8>0,1,0) -> 1 | H8: 717197 | I8: 0.21960784 | J8: 0.13832888 | K8: =L8^0.25 -> 0.011952304 | L8: 2.0408282e-08 | N8: =B8*J8 -> 0.034940497 | O8: =(1-B8)*(1-J8) -> 0.64402157 | P8: =B8*(1-J8) -> 0.21764955 | Q8: =(1-B8)*J8 -> 0.10338838
A9: FLORIDA | B9: 0.077833555 | C9: =LN(B9/(1-B9)) -> -2.4721531 | D9: =1-B9 -> 0.92216645 | E9: =LN(D9/(1-D9)) -> 2.4721531 | F9: =A9 -> FLORIDA | G9: =IF(B9>0,1,0) -> 1 | H9: 14165570 | I9: 0.11101558 | J9: 0.0079942105 | K9: =L9^0.25 -> 0.0013827027 | L9: 3.6552342e-12 | N9: =B9*J9 -> 0.00062221782 | O9: =(1-B9)*(1-J9) -> 0.91479445 | P9: =B9*(1-J9) -> 0.077211337 | Q9: =(1-B9)*J9 -> 0.0073719926
A10: GEORGIA | B10: 0.0041858291 | C10: =LN(B10/(1-B10)) -> -5.4718559 | D10: =1-B10 -> 0.99581417 | E10: =LN(D10/(1-D10)) -> 5.4718559 | F10: =A10 -> GEORGIA | G10: =IF(B10>0,1,0) -> 1 | H10: 7200882 | I10: 0.0078556263 | J10: 0.028137824 | K10: =L10^0.25 -> 0.00099897011 | L10: 9.9588679e-13 | N10: =B10*J10 -> 0.00011778012 | O10: =(1-B10)*(1-J10) -> 0.96779413 | P10: =B10*(1-J10) -> 0.004068049 | Q10: =(1-B10)*J10 -> 0.028020044
A11: HAWAII | B11: 0 | C11: =LN(B11/(1-B11)) -> #VALUE! | D11: =1-B11 -> 1 | E11: =LN(D11/(1-D11)) -> #DIV/0! | F11: =A11 -> HAWAII | G11: =IF(B11>0,1,0) -> 0 | H11: 1186815 | I11: 0 | J11: 0.0095240957 | K11: =L11^0.25 -> 0.0025331665 | L11: 4.1177025e-11 | N11: =B11*J11 -> 0 | O11: =(1-B11)*(1-J11) -> 0.9904759 | P11: =B11*(1-J11) -> 0 | Q11: =(1-B11)*J11 -> 0.0095240957
A12: IDAHO | B12: 0 | C12: =LN(B12/(1-B12)) -> #VALUE! | D12: =1-B12 -> 1 | E12: =LN(D12/(1-D12)) -> #DIV/0! | F12: =A12 -> IDAHO | G12: =IF(B12>0,1,0) -> 0 | H12: 1163261 | I12: 0 | J12: 0.026148588 | K12: =L12^0.25 -> 0.0011444505 | L12: 1.7154896e-12 | N12: =B12*J12 -> 0 | O12: =(1-B12)*(1-J12) -> 0.97385141 | P12: =B12*(1-J12) -> 0 | Q12: =(1-B12)*J12 -> 0.026148588
A13: ILLINOIS | B13: 0.092502027 | C13: =LN(B13/(1-B13)) -> -2.2834608 | D13: =1-B13 -> 0.90749797 | E13: =LN(D13/(1-D13)) -> 2.2834608 | F13: =A13 -> ILLINOIS | G13: =IF(B13>0,1,0) -> 1 | H13: 11829940 | I13: 0.082538976 | J13: 0.028193774 | K13: =L13^0.25 -> 0.00067228915 | L13: 2.0427933e-13 | N13: =B13*J13 -> 0.0026079813 | O13: =(1-B13)*(1-J13) -> 0.88191218 | P13: =B13*(1-J13) -> 0.089894046 | Q13: =(1-B13)*J13 -> 0.025585793
... A50: WYOMING | B50: 0 | C50: =LN(B50/(1-B50)) -> #VALUE! | D50: =1-B50 -> 1 | E50: =LN(D50/(1-D50)) -> #DIV/0! | F50: =A50 -> WYOMING | G50: =IF(B50>0,1,0) -> 0 | H50: 480184 | I50: 0 | J50: 0.025620995 | K50: =L50^0.25 -> 0.00067440495 | L50: 2.0686308e-13 | N50: =B50*J50 -> 0 | O50: =(1-B50)*(1-J50) -> 0.974379 | P50: =B50*(1-J50) -> 0 | Q50: =(1-B50)*J50 -> 0.025620995
A52: XLSTAT - Models for Binary Response Data / Started on 12/3/98 at 11:17:36 AM
A53: Input data :
A54: Binary response : Workbook = Levinson-stat.xls / Sheet = Sheet13 / Range = $F$1:$F$50
A55: Numerical variables : Workbook = Levinson-stat.xls / Sheet = Sheet13 / Range = $G$1:$J$50
A56: Categorical variables : None
A57: Logit Model
A60: Numerical data summary :
A62: Variable | B62: Mean | C62: Std. dev.
A63: Population | B63: 5338722.4 | C63: 5779174.7
A64: OldTollMileRatio | B64: 0.074880138 | C64: 0.11461002
A65: Workers Who Live OOS (JTW) | B65: 0.037239314 | C65: 0.026926035
A66: N1^4 | B66: 2.3050017e-08 | C66: 1.3983592e-07
A70: Maximum Likelihood estimators for parameters :
A72: Parameter | B72: Value | C72: Std dev. | D72: Chi-Sq | E72: Prob>Chi-Sq
A73: Intercept | B73: -4.4629053 | C73: 2.1758305 | D73: 4.2071234 | E73: 0.040254552
A74: Population | B74: 9.077157e-07 | C74: 3.7258949e-07 | D74: 5.935243 | E74: 0.014841023
A75: OldTollMileRatio | B75: 3567.8683 | C75: 4.8345866e+08 | D75: 5.4462671e-11 | E75: 0.99999411
A76: Workers Who Live OOS (JTW) | B76: 42.688247 | C76: 44.645718 | D76: 0.91423327 | E76: 0.3389937
A77: N1^4 | B77: 1.7895387e+08 | C77: 2.5932072e+08 | D77: 0.47622013 | E77: 0.49013945
A80: Goodness of fit evaluation :
A81: total obs. | B81: Log Like. | C81: Log Like. (indep) | D81: Pearson Chi-Sq | E81: DF (Chi-Sq) | G81: Prob>Pearson Chi-Sq | H81: L.R. Chi-Sq | I81: DF (L.R. Chi-Sq) | J81: Prob>L.R. Chi-Sq | L81: R2 | M81: R2 (McFadden)
A82: 49 | B82: -12.2295 | C82: -30.182184 | D82: 24.751642 | E82: 44 | G82: 0.99154163 | H82: 35.905368 | I82: 4 | J82: 0.0001 | L82: 0.61324604 | M82: 0.59481064
A84: Predictions and residuals :
A86: Observations | C86: Population | D86: OldTollMileRatio | E86: Workers Who Live OOS (JTW) | G86: N1^4 | H86: Binary | I86: Fitted Logit | J86: Indep. model | L86: Binary / | M86: Fitted prop. | N86: Res. on Logit | O86: Res. on Indep model
A87: Obs 1 | B87: 1 | C87: 4252982 | D87: 0 | E87: 0.023851877 | G87: 1.1600218e-12 | H87: 0 | I87: 0.60252463 | J87: 0.69387755 | L87: 0 | M87: 0.60252463 | N87: -1.2312105 | O87: -1.5055453
A88: Obs 2 | B88: 1 | C88: 4217940 | D88: 0 | E88: 0.011207188 | G88: 1.4920096e-12 | H88: 0 | I88: 0.461195 | J88: 0.69387755 | L88: 0 | M88: 0.461195 | N88: -0.92518053 | O88: -1.5055453
A89: Obs 3 | B89: 1 | C89: 2483769 | D89: 0 | E89: 0.040294187 | G89: 8.7885835e-13 | H89: 0 | I89: 0.38034038 | J89: 0.69387755 | L89: 0 | M89: 0.38034038 | N89: -0.783447 | O89: -1.5055453
A90: Obs 4 | B90: 1 | C90: 31589153 | D90: 0 | E90: 0.0045230302 | G90: 1.1583812e-12 | H90: 1 | I90: 1 | J90: 0.69387755 | L90: 1 | M90: 1 | N90: 5.0195242e-06 | O90: 0.66421116
A91: Obs 5 | B91: 1 | C91: 3746585 | D91: 0.014786325 | E91: 0.0079445411 | G91: 6.5829148e-13 | H91: 1 | I91: 1 | J91: 0.69387755 | L91: 1 | M91: 1 | N91: 1.0536712e-08 | O91: 0.66421116
A92: Obs 6 | B92: 1 | C92: 3274662 | D92: 0.35774908 | E92: 0.045612423 | G92: 2.6797815e-08 | H92: 1 | I92: 1 | J92: 0.69387755 | L92: 1 | M92: 1 | N92: 1.0536712e-08 | O92: 0.66421116
A93: Obs 7 | B93: 1 | C93: 717197 | D93: 0.21960784 | E93: 0.13832888 | G93: 2.0408282e-08 | H93: 1 | I93: 1 | J93: 0.69387755 | L93: 1 | M93: 1 | N93: 1.0536712e-08 | O93: 0.66421116
A94: Obs 8 | B94: 1 | C94: 14165570 | D94: 0.11101558 | E94: 0.0079942105 | G94: 3.6552342e-12 | H94: 1 | I94: 1 | J94: 0.69387755 | L94: 1 | M94: 1 | N94: 1.0536712e-08 | O94: 0.66421116
A95: Obs 9 | B95: 1 | C95: 7200882 | D95: 0.0078556263 | E95: 0.028137824 | G95: 9.9588679e-13 | H95: 1 | I95: 1 | J95: 0.69387755 | L95: 1 | M95: 1 | N95: 2.62996e-07 | O95: 0.66421116
A96: Obs 10 | B96: 1 | C96: 1186815 | D96: 0 | E96: 0.0095240957 | G96: 4.1177025e-11 | H96: 0 | I96: 0.048721846 | J96: 0.69387755 | L96: 0 | M96: 0.048721846 | N96: -0.22631227 | O96: -1.5055453
A97: Obs 11 | B97: 1 | C97: 1163261 | D97: 0 | E97: 0.026148588 | G97: 1.7154896e-12 | H97: 0 | I97: 0.091916927 | J97: 0.69387755 | L97: 0 | M97: 0.091916927 | N97: -0.31815222 | O97: -1.5055453
A98: Obs 12 | B98: 1 | C98: 11829940 | D98: 0.082538976 | E98: 0.028193774 | G98: 2.0427933e-13 | H98: 1 | I98: 1 | J98: 0.69387755 | L98: 1 | M98: 1 | N98: 1.0536712e-08 | O98: 0.66421116
... A135: Obs 49 | B135: 1 | C135: 480184 | D135: 0 | E135: 0.025620995 | G135: 2.0686308e-13 | H135: 0 | I135: 0.050532607 | J135: 0.69387755 | L135: 0 | M135: 0.050532607 | N135: -0.23069906 | O135: -1.5055453
A138: XLSTAT - Models for Binary Response Data / Started on 12/3/98 at 11:19:33 AM
A139: Input data :
A140: Binary response : Workbook = Levinson-stat.xls / Sheet = Sheet13 / Range = $F$1:$F$50
A141: Numerical variables : Workbook = Levinson-stat.xls / Sheet = Sheet13 / Range = $G$1:$J$50
A142: Categorical variables : None
A143: Probit Model
A146: Numerical data summary :
A148: Variable | B148: Mean | C148: Std. dev.
A149: Population | B149: 5338722.4 | C149: 5779174.7
A150: OldTollMileRatio | B150: 0.074880138 | C150: 0.11461002
A151: Workers Who Live OOS (JTW) | B151: 0.037239314 | C151: 0.026926035
A152: N1^4 | B152: 2.3050017e-08 | C152: 1.3983592e-07
A156: Maximum Likelihood estimators for parameters :
A158: Parameter | B158: Value | C158: Std dev. | D158: Chi-Sq | E158: Prob>Chi-Sq
A159: Intercept | B159: -2.5006155 | C159: 1.045545 | D159: 5.7201626 | E159: 0.016771178
A160: Population | B160: 5.325938e-07 | C160: 1.9765726e-07 | D160: 7.2605021 | E160: 0.0070487582
A161: OldTollMileRatio | B161: 364.48955 | C161: 45.806043 | D161: 63.317625 | E161: 0.0001
A162: Workers Who Live OOS (JTW) | B162: 21.54818 | C162: 22.991262 | D162: 0.87840661 | E162: 0.34863847
A163: N1^4 | B163: 1.2081426e+08 | C163: 1.5335542e+08 | D163: 0.62063769 | E163: 0.43081041
A166: Goodness of fit evaluation :
A167: total obs. | B167: Log Like. | C167: Log Like. (indep) | D167: Pearson Chi-Sq | E167: DF (Chi-Sq) | G167: Prob>Pearson Chi-Sq | H167: L.R. Chi-Sq | I167: DF (L.R. Chi-Sq) | J167: Prob>L.R. Chi-Sq | L167: R2 | M167: R2 (McFadden)
A168: 49 | B168: -12.191427 | C168: -30.182184 | D168: 23.74776 | E168: 44 | G168: 0.99460039 | H168: 35.981514 | I168: 4 | J168: 0.0001 | L168: 0.6097811 | M168: 0.59607208
A170: Predictions and residuals :
A172: Observations | C172: Population | D172: OldTollMileRatio | E172: Workers Who Live OOS (JTW) | G172: N1^4 | H172: Binary | I172: Fitted Probit | J172: Indep. model | L172: Binary / | M172: Fitted prop. | N172: Res. on Probit | O172: Res. on Indep model
A173: Obs 1 | B173: 1 | C173: 4252982 | D173: 0 | E173: 0.023851877 | G173: 1.1600218e-12 | H173: 0 | I173: 0.60972444 | J173: 0.69387755 | L173: 0 | M173: 0.60972444 | N173: -1.2499168 | O173: -1.5055453
A174: Obs 2 | B174: 1 | C174: 4217940 | D174: 0 | E174: 0.011207188 | G174: 1.4920096e-12 | H174: 0 | I174: 0.49501651 | J174: 0.69387755 | L174: 0 | M174: 0.49501651 | N174: -0.99008219 | O174: -1.5055453
A175: Obs 3 | B175: 1 | C175: 2483769 | D175: 0 | E175: 0.040294187 | G175: 8.7885835e-13 | H175: 0 | I175: 0.37850759 | J175: 0.69387755 | L175: 0 | M175: 0.37850759 | N175: -0.78040381 | O175: -1.5055453
A176: Obs 4 | B176: 1 | C176: 31589153 | D176: 0 | E176: 0.0045230302 | G176: 1.1583812e-12 | H176: 1 | I176: 1 | J176: 0.69387755 | L176: 1 | M176: 1 | N176: 1.0536712e-08 | O176: 0.66421116
A177: Obs 5 | B177: 1 | C177: 3746585 | D177: 0.014786325 | E177: 0.0079445411 | G177: 6.5829148e-13 | H177: 1 | I177: 0.99999979 | J177: 0.69387755 | L177: 1 | M177: 0.99999979 | N177: 0.00046364316 | O177: 0.66421116
A178: Obs 6 | B178: 1 | C178: 3274662 | D178: 0.35774908 | E178: 0.045612423 | G178: 2.6797815e-08 | H178: 1 | I178: 1 | J178: 0.69387755 | L178: 1 | M178: 1 | N178: 1.0536712e-08 | O178: 0.66421116
A179: Obs 7 | B179: 1 | C179: 717197 | D179: 0.21960784 | E179: 0.13832888 | G179: 2.0408282e-08 | H179: 1 | I179: 1 | J179: 0.69387755 | L179: 1 | M179: 1 | N179: 1.0536712e-08 | O179: 0.66421116
A180: Obs 8 | B180: 1 | C180: 14165570 | D180: 0.11101558 | E180: 0.0079942105 | G180: 3.6552342e-12 | H180: 1 | I180: 1 | J180: 0.69387755 | L180: 1 | M180: 1 | N180: 1.0536712e-08 | O180: 0.66421116
A181: Obs 9 | B181: 1 | C181: 7200882 | D181: 0.0078556263 | E181: 0.028137824 | G181: 9.9588679e-13 | H181: 1 | I181: 0.99999922 | J181: 0.69387755 | L181: 1 | M181: 0.99999922 | N181: 0.00088182978 | O181: 0.66421116
A182: Obs 10 | B182: 1 | C182: 1186815 | D182: 0 | E182: 0.0095240957 | G182: 4.1177025e-11 | H182: 0 | I182: 0.048626078 | J182: 0.69387755 | L182: 0 | M182: 0.048626078 | N182: -0.22607836 | O182: -1.5055453
A183: Obs 11 | B183: 1 | C183: 1163261 | D183: 0 | E183: 0.026148588 | G183: 1.7154896e-12 | H183: 0 | I183: 0.093850992 | J183: 0.69387755 | L183: 0 | M183: 0.093850992 | N183: -0.32182489 | O183: -1.5055453
A184: Obs 12 | B184: 1 | C184: 11829940 | D184: 0.082538976 | E184: 0.028193774 | G184: 2.0427933e-13 | H184: 1 | I184: 1 | J184: 0.69387755 | L184: 1 | M184: 1 | N184: 1.0536712e-08 | O184: 0.66421116
... A221: Obs 49 | B221: 1 | C221: 480184 | D221: 0 | E221: 0.025620995 | G221: 2.0686308e-13 | H221: 0 | I221: 0.045250394 | J221: 0.69387755 | L221: 0 | M221: 0.045250394 | N221: -0.21770402 | O221: -1.5055453
A224: XLSTAT - Models for Binary Response Data / Started on 12/3/98 at 11:25:00 AM
A225: Input data :
A226: Binary response : Workbook = Levinson-stat.xls / Sheet = Sheet13 / Range = $F$1:$F$50
A227: Numerical variables : Workbook = Levinson-stat.xls / Sheet = Sheet13 / Range = $G$1:$J$50
A228: Categorical variables : None
A229: Log-logit up Model
A232: Numerical data summary :
A234: Variable | B234: Mean | C234: Std. dev.
A235: Population | B235: 5338722.4 | C235: 5779174.7
A236: OldTollMileRatio | B236: 0.074880138 | C236: 0.11461002
A237: Workers Who Live OOS (JTW) | B237: 0.037239314 | C237: 0.026926035
A238: N1^4 | B238: 2.3050017e-08 | C238: 1.3983592e-07
...

Sheet VMT
A1: Total Rural and Urban | B1: Urban Total | C1: Urban Local | D1: Urban Collector | E1: Urban Minor Arterial | F1: Urban Other Principal Arterial | G1: Urban Other Freeways and Expressways | H1: Urban Interstate | I1: Rural Total | J1: Rural Local | K1: Rural Minor Collector | L1: Rural Major Collector | M1: Rural Minor Arterial | N1: Rural Other Principal Arterial | O1: Rural Interstate | P1: ABBREV | Q1: FULLNAME
A2: 50628 | B2: 24930 | C2: 5724 | D2: 2417 | E2: 4996 | F2: 6461 | G2: 387 | H2: 4945 | I2: 25698 | J2: 4713 | K2: 1209 | L2: 5041 | M2: 4247 | N2: 5351 | O2: 5137 | P2: AL | Q2: ALABAMA
A3: 4123 | B3: 2030 | C3: 234 | D3: 204 | E3: 676 | F3: 399 | G3: 0 | H3: 517 | I3: 2093 | J3: 457 | K3: 101 | L3: 332 | M3: 123 | N3: 295 | O3: 785 | P3: AK | Q3: ALASKA
A4: 39653 | B4: 25603 | C4: 2899 | D4: 2823 | E4: 5359 | F4: 9005 | G4: 1826 | H4: 3691 | I4: 14050 | J4: 1619 | K4: 315 | L4: 2707 | M4: 1668 | N4: 2299 | O4: 5442 | P4: AZ | Q4: ARIZONA
A5: 26653 | B5: 9002 | C5: 700 | D5: 776 | E5: 1964 | F5: 2638 | G5: 831 | H5: 2093 | I5: 17651 | J5: 1130 | K5: 663 | L5: 5022 | M5: 3220 | N5: 4371 | O5: 3245 | P5: AR | Q5: ARKANSAS
A6: 276371 | B6: 223033 | C6: 16390 | D6: 13915 | E6: 41202 | F6: 53574 | G6: 42768 | H6: 55184 | I6: 53338 | J6: 2395 | K6: 2716 | L6: 9693 | M6: 8893 | N6: 15396 | O6: 14245 | P6: CA | Q6: CALIFORNIA
A7: 35058 | B7: 21035 | C7: 2103 | D7: 1559 | E7: 3905 | F7: 6354 | G7: 2749 | H7: 4365 | I7: 14023 | J7: 1402 | K7: 701 | L7: 1926 | M7: 2251 | N7: 3478 | O7: 4265 | P7: CO | Q7: COLORADO
A8: 28045 | B8: 21344 | C8: 2274 | D8: 1565 | E8: 4153 | F8: 3371 | G8: 2839 | H8: 7142 | I8: 6701 | J8: 1160 | K8: 264 | L8: 1229 | M8: 1187 | N8: 1379 | O8: 1482 | P8: CT | Q8: CONNECTICUT
A9: 7515 | B9: 4561 | C9: 826 | D9: 464 | E9: 715 | F9: 1223 | G9: 98 | H9: 1235 | I9: 2954 | J9: 466 | K9: 81 | L9: 615 | M9: 324 | N9: 1468 | O9: 0 | P9: DE | Q9: DELAWARE
A10: 3465 | B10: 3465 | C10: 438 | D10: 328 | E10: 912 | F10: 912 | G10: 401 | H10: 474 | I10: 0 | J10: 0 | K10: 0 | L10: 0 | M10: 0 | N10: 0 | O10: 0 | P10: DC | Q10: District-of-Columbia
A11: 127801 | B11: 95398 | C11: 19308 | D11: 11602 | E11: 15707 | F11: 27316 | G11: 6227 | H11: 15238 | I11: 32403 | J11: 3571 | K11: 1406 | L11: 2378 | M11: 4385 | N11: 10978 | O11: 9685 | P11: FL | Q11: FLORIDA
A12: 85384 | B12: 49822 | C12: 8079 | D12: 4573 | E12: 9975 | F12: 10790 | G12: 2314 | H12: 14091 | I12: 35562 | J12: 4827 | K12: 2102 | L12: 6362 | M12: 7081 | N12: 6324 | O12: 8866 | P12: GA | Q12: GEORGIA
A13: 7945 | B13: 5847 | C13: 797 | D13: 872 | E13: 683 | F13: 1324 | G13: 614 | H13: 1557 | I13: 2098 | J13: 307 | K13: 33 | L13: 323 | M13: 780 | N13: 655 | O13: 0 | P13: HI | Q13: HAWAII
... A54: 2438323 | B54: 1501008 | C54: 207361 | D54: 128324 | E54: 295353 | F54: 373015 | G54: 152353 | H54: 344602 | I54: 937315 | J54: 105818 | K54: 50389 | L54: 186904 | M54: 153824 | N54: 215942 | O54: 224438 | P54: US | Q54: *United States

Sheet TotalWorkers
A1: SUMMARY OUTPUT
A3: Regression Statistics
A4: Multiple R | B4: 0.8028288
A5: R Square | B5: 0.64453408
A6: Adjusted R Square | B6: 0.612219
A7: Standard Error | B7: 0.045445481
A8: Observations | B8: 49
A10: ANOVA
B11: df | C11: SS | D11: MS | E11: F | F11: Significance F
A12: Regression | B12: 4 | C12: 0.16477146 | D12: 0.041192865 | E12: 19.945301 | F12: 1.9898482e-09
A13: Residual | B13: 44 | C13: 0.090872835 | D13: 0.0020652917
A14: Total | B14: 48 | C14: 0.2556443
B16: Coefficients | C16: Standard Error | D16: t Stat | E16: P-value | F16: Lower 95% | G16: Upper 95% | H16: Lower 95.0% | I16: Upper 95.0%
A17: Intercept | B17: -0.031917548 | C17: 0.014317343 | D17: -2.2292927 | E17: 0.030947876 | F17: -0.060772255 | G17: -0.0030628399 | H17: -0.060772255 | I17: -0.0030628399
A18: Total Workers | B18: 8.1006344e-09 | C18: 2.7556646e-09 | D18: 2.93963 | E18: 0.0052188424 | F18: 2.5469575e-09 | G18: 1.3654311e-08 | H18: 2.5469575e-09 | I18: 1.3654311e-08
A19: OldTollMileRatio | B19: 0.30745868 | C19: 0.0732881 | D19: 4.195206 | E19: 0.00012998215 | F19: 0.15975622 | G19: 0.45516114 | H19: 0.15975622 | I19: 0.45516114
A20: Workers Who Live OOS (JTW) | B20: 0.80522142 | C20: 0.29136552 | D20: 2.7636126 | E20: 0.0083160403 | F20: 0.21801283 | G20: 1.39243 | H20: 0.21801283 | I20: 1.39243
A21: N1^4 | B21: 86074.156 | C21: 53502.018 | D21: 1.608802 | E21: 0.11481228 | F21: -21752.073 | G21: 193900.38 | H21: -21752.073 | I21: 193900.38

Sheet TotWork+Pop
A1: Tot
A3: Regression Statistics
A4: Multiple R | B4: 0.80926441
A5: R Square | B5: 0.65490888
A6: Adjusted R Square | B6: 0.61478201
A7: Standard Error | B7: 0.045295047
A8: Observations | B8: 49
A10: ANOVA
B11: df | C11: SS | D11: MS | E11: F | F11: Significance F
A12: Regression | B12: 5 | C12: 0.16742372 | D12: 0.033484744 | E12: 16.320954 | F12: 5.2092574e-09
A13: Residual | B13: 43 | C13: 0.088220576 | D13: 0.0020516413
A14: Total | B14: 48 | C14: 0.2556443
B16: Coefficients | C16: Standard Error | D16: t Stat | E16: P-value | F16: Lower 95% | G16: Upper 95% | H16: Lower 95.0% | I16: Upper 95.0%
A17: Intercept | B17: -0.034388233 | C17: 0.014434452 | D17: -2.3823719 | E17: 0.021694227 | F17: -0.06349806 | G17: -0.0052784062 | H17: -0.06349806 | I17: -0.0052784062
A18: Population | B18: 3.981542e-09 | C18: 3.501822e-09 | D18: 1.1369915 | E18: 0.26183833 | F18: -3.0805503e-09 | G18: 1.1043634e-08 | H18: -3.0805503e-09 | I18: 1.1043634e-08
A19: Total Workers | B19: -3.6461785e-10 | C19: 7.9357489e-09 | D19: -0.045946244 | E19: 0.96356582 | F19: -1.636857e-08 | G19: 1.5639334e-08 | H19: -1.636857e-08 | I19: 1.5639334e-08
A20: OldTollMileRatio | B20: 0.29930127 | C20: 0.073397001 | D20: 4.0778406 | E20: 0.00019276918 | F20: 0.15128221 | G20: 0.44732033 | H20: 0.15128221 | I20: 0.44732033
A21: Workers Who Live OOS (JTW) | B21: 0.84589591 | C21: 0.29259619 | D21: 2.8910012 | E21: 0.0059989483 | F21: 0.25581987 | G21: 1.435972 | H21: 0.25581987 | I21: 1.435972
A22: N1^4 | B22: 90060.476 | C22: 53440.05 | D22: 1.6852618 | E22: 0.099183189 | F22: -17711.581 | G22: 197832.53 | H22: -17711.581 | I22: 197832.53

Sheet Sheet13
A1: SUMMARY OUTPUT
A3: Regression Statistics
A4: Multiple R | B4: 0.76490521
A5: R Square | B5: 0.58507999
A6: Adjusted R Square | B6: 0.54735998
A7: Standard Error | B7: 0.049099143
A8: Observations | B8: 49
A10: ANOVA
B11: df | C11: SS | D11: MS | E11: F | F11: Significance F
A12: Regression | B12: 4 | C12: 0.14957236 | D12: 0.03739309 | E12: 15.511134 | F12: 5.4619537e-08
A13: Residual | B13: 44 | C13: 0.10607194 | D13: 0.0024107258
A14: Total | B14: 48 | C14: 0.2556443
B16: Coefficients | C16: Standard Error | D16: t Stat | E16: P-value | F16: Lower 95% | G16: Upper 95% | H16: Lower 95.0% | I16: Upper 95.0%
A17: Intercept | B17: -0.0081928953 | C17: 0.012333859 | D17: -0.66426053 | E17: 0.50998983 | F17: -0.033050153 | G17: 0.016664362 | H17: -0.033050153 | I17: 0.016664362
A18: Density | B18: 4.0952613e-05 | C18: 3.9075058e-05 | D18: 1.04805 | E18: 0.30033863 | F18: -3.7797988e-05 | G18: 0.00011970321 | H18: -3.7797988e-05 | I18: 0.00011970321
A19: OldTollMileRatio | B19: 0.32992811 | C19: 0.079838788 | D19: 4.1324288 | E19: 0.0001582821 | F19: 0.16902361 | G19: 0.49083261 | H19: 0.16902361 | I19: 0.49083261
A20: Workers Who Live OOS (JTW) | B20: 0.45265209 | C20: 0.30439697 | D20: 1.4870453 | E20: 0.1441344 | F20: -0.16081968 | G20: 1.0661239 | H20: -0.16081968 | I20: 1.0661239
A21: N1^4 | B21: 63308.776 | C21: 63966.946 | D21: 0.98971078 | E21: 0.32772714 | F21: -65608.128 | G21: 192225.68 | H21: -65608.128 | I21: 192225.68

Sheet N-N-F(M,O,P)
A1: SUMMARY OUTPUT
A3: Regression Statistics
A4: Multiple R | B4: 0.7950246
A5: R Square | B5: 0.63206412
A6: Adjusted R Square | B6: 0.60753506
A7: Standard Error | B7: 0.045719121
A8: Observations | B8: 49
A10: ANOVA
B11: df | C11: SS | D11: MS | E11: F | F11: Significance F
A12: Regression | B12: 3 | C12: 0.16158359 | D12: 0.053861196 | E12: 25.767973 | F12: 7.433916e-10
A13: Residual | B13: 45 | C13: 0.094060709 | D13: 0.002090238
A14: Total | B14: 48 | C14: 0.2556443
B16: Coefficients | C16: Standard Error | D16: t Stat | E16: P-value | F16: Lower 95% | G16: Upper 95% | H16: Lower 95.0% | I16: Upper 95.0%
A17: Intercept | B17: -0.036390329 | C17: 0.014484872 | D17: -2.5122989 | E17: 0.01564852 | F17: -0.065564357 | G17: -0.0072163001 | H17: -0.065564357 | I17: -0.0072163001
A18: Population | B18: 3.8577556e-09 | C18: 1.2232109e-09 | D18: 3.1537944 | E18: 0.0028694186 | F18: 1.3940826e-09 | G18: 6.3214286e-09 | H18: 1.3940826e-09 | I18: 6.3214286e-09
A19: OldTollMileRatio | B19: 0.35205821 | C19: 0.067017425 | D19: 5.2532339 | E19: 3.9413953e-06 | F19: 0.21707819 | G19: 0.48703822 | H19: 0.21707819 | I19: 0.48703822
A20: Workers Who Live OOS (JTW) | B20: 0.84418736 | C20: 0.29533367 | D20: 2.858419 | E20: 0.0064284078 | F20: 0.24935484 | G20: 1.4390199 | H20: 0.24935484 | I20: 1.4390199

Sheet Select
E1: 1995 | F1: 1995 | G1: 1995 | H1: 1995 | M1: 1e-06 | N1: 1 | O1: 0.5 | AA1: 0 | AB1: 0.5 | AD1: 1 | AV1: ATS | BL1: from ATS-Data-Neighbors-OOS
E2: Highway-user taxation - Total | F2: Highway-user taxation - State and local tolls | G2: Highway-user taxation - State and local fuel and vehicle taxes | H2: Highway-user taxation - Federal fuel and vehicle taxes | O2: JTW-Tables | AK2: ATS-Tables | AO2: Published | AV2: Vistors to State by Origin | AX2: Destinations by Residents of | BA2: Visitors | BB2: Residents | BE2: PUBLISHED JTW DATA | BL2: Neighbor Tolls | BP2: FROM JTW-TRIP TABLE | BU2: FROM JTW-TRIP TABLE | CA2: RAE 1969 | CD2: Freeways, Expwy, Interstates | CJ2: Urban Other Freeways and Expressways | CK2: Urban Interstate | CL2: Rural Interstate
A3: STATE | B3: FULLNAME | C3: TollShare | D3: Toll[1,0] | E3: (Thousands of $) | F3: (Thousands of $) | G3: (Thousands of $) | H3: (Thousands of $) | J3: Land | K3: Density | L3: Total Workers | M3: Population | N3: OldTollMileRatio | O3: Workers Who Live OOS (JTW) | P3: N1^4 | Q3: NonCap/Pop | R3: Expenditures | S3: NonCap | T3: Yhat | U3: LN(POP) | V3: LN(OLDMILES+1) | W3: LN(Ow) | X3: LN(N1^4) | Z3: AVGNeighbor2*ResidentsWhoWorkOutofState^4 | AA3: Percent Federal Land | AB3: =BV3 -> AVG-Neighbor-2 | AD3: Residents Who Work OOS - JTW | AG3: =A3 -> STATE | AH3: Expected Toll Share | AI3: Actual Toll Share | AJ3: Weight | AK3: Out of State Visitors - ATS | AL3: Neighbor - ATS | AM3: Residents Out-of-State Trips - ATS | AO3: JTW-OOSRATIO | AQ3: Log(TollShare+1) | AR3: Log(Land) | AS3: Log(Pop) | AT3: Log(Miles) | AV3: In-State | AW3: Out-of-State | AX3: In-State | AY3: Out-Of-Staet | BA3: Visitors In-State Ratio | BB3: Residents In-State Ratio | BC3: STATE | BD3: STATE | BG3: P0450001 Worked in county of residence | BH3: P0450002 Worked outside county of residence | BI3: P0450003 Worked outside State of residence | BJ3: JTW-OOSRATIO | BL3: TOTAL/TOTAL-OOS | BM3: STATE | BO3: State | BP3: WorkersWhoLiveInState | BQ3: ResidentsWhoWorkInState | BT3: x | BU3: AVG-Neighbor-1 | BV3: AVG-Neighbor-2 | BW3: Percent Federal Lands | BX3: State | BZ3: State | CA3: TollMile1963 | CD3: (miles ) | CE3: OldTollMileRatio | CG3: STATE | CH3: FULLNAME | CI3: STATE | CJ3: (Miles ) | CK3: (Miles ) | CL3: (Miles )
A4: AL | B4: ALABAMA | C4: =F4/E4 -> 0 | D4: 1 | E4: 1142121 | F4: 0 | G4: 691523 | H4: 450598 | J4: 50750 | K4: 83.802601 | L4: =BG4+BH4+BI4 -> 1735588 | M4: 4252982 | N4: 0 | O4: 0.023851877 | P4: =BU4^4 -> 1.1600218e-12 | Q4: =S4/M4 -> 0.13286536 | R4: 1001737 | S4: 565074 | T4: =AH4 -> 0.0020315369 | U4: =LN(M4) -> 15.263131 | V4: =LN(N4+1) -> 0 | W4: =LN(O4) -> -3.7358924 | X4: =LN(P4) -> -27.482582 | Z4: =(AB4*AD4)^4 -> 1.2879668e-13 | AA4: 0.03281 | AB4: =BV4 -> 0.016641465 | AD4: 0.035998518 | AG4: =A4 -> AL | AH4: ='Final-2'!B$41+'Final-2'!B$42*M4+'Final-2'!B$43*N4+'Final-2'!B$44*O4+'Final-2'!B$45*P4 -> 0.0020315369 | AI4: =C4 -> 0 | AJ4: =1/ABS(AH4-AI4) -> 492.23816 | AK4: 0.57102882 | AL4: 0.026365956 | AM4: 0.57465022 | AO4: 0.035732559 | AQ4: 0 | AR4: 10.834667 | AS4: 15.263131 | AT4: 11.443715 | AV4: 7205 | AW4: 9591 | AX4: 7205 | AY4: 9734 | BA4: 0.42897118 | BB4: 0.42534978 | BC4: AL | BD4: AL | BE4: Alabama | BF4: 4040587 | BG4: 1363133 | BH4: 310438 | BI4: 62017 | BJ4: 0.035732559 | BL4: 0.026365956 | BM4: AL | BO4: alabama | BP4: 0.97614812 | BQ4: 0.96400148 | BT4: alabama | BU4: 0.0010378069 | BV4: 0.016641465 | BW4: 3.281 | BX4: Alabama | BZ4: Alabama | CA4: 0 | CD4: 925 | CE4: 0 | CG4: AL | CH4: ALABAMA | CI4: AL | CJ4: 21 | CK4: 303 | CL4: 601
A5: AZ | B5: ARIZONA | C5: =F5/E5 -> 0 | D5: 1 | E5: 971888 | F5: 0 | G5: 618012 | H5: 353876 | J5: 113642 | K5: 37.116031 | L5: =BG5+BH5+BI5 -> 1600604 | M5: 4217940 | N5: 0 | O5: 0.011207188 | P5: =BU5^4 -> 1.4920096e-12 | Q5: =S5/M5 -> 0.17650275 | R5: 1199273 | S5: 744478 | T5: =AH5 -> -0.0087985576 | U5: =LN(M5) -> 15.254857 | V5: =LN(N5+1) -> 0 | W5: =LN(O5) -> -4.4911999 | X5: =LN(P5) -> -27.230897 | Z5: =(AB5*AD5)^4 -> 1.3924977e-14 | AA5: 0.41534 | AB5: =BV5 -> 0.021735556 | AD5: 0.015804395 | AG5: =A5 -> AZ | AH5: ='Final-2'!B$41+'Final-2'!B$42*M5+'Final-2'!B$43*N5+'Final-2'!B$44*O5+'Final-2'!B$45*P5 -> -0.0087985576 | AI5: =C5 -> 0 | AJ5: =1/ABS(AH5-AI5) -> 113.65499 | AK5: 0.48957601 | AL5: 0.0063479542 | AM5: 0.44367851 | AO5: 0.016210755 | AQ5: 0 | AR5: 11.640808 | AS5: 15.254857 | AT5: 10.907075 | AV5: 10895 | AW5: 10450 | AX5: 10895 | AY5: 8689 | BA5: 0.51042399 | BB5: 0.55632149 | BC5: AZ | BD5: AZ | BE5: Arizona | BF5: 3665228 | BG5: 1535826 | BH5: 38831 | BI5: 25947 | BJ5: 0.016210755 | BL5: 0.0063479542 | BM5: AZ | BO5: arizona | BP5: 0.98879281 | BQ5: 0.98419561 | BT5: arizona | BU5: 0.0011052052 | BV5: 0.021735556 | BW5: 41.534 | BX5: Arizona | BZ5: Arizona | CA5: 0 | CD5: 1250 | CE5: 0 | CG5: AZ | CH5: ARIZONA | CI5: AZ | CJ5: 81 | CK5: 178 | CL5: 991
A6: AR | B6: ARKANSAS | C6: =F6/E6 -> 0 | D6: 1 | E6: 691210 | F6: 0 | G6: 398785 | H6: 292425 | J6: 52075 | K6: 47.695996 | L6: =BG6+BH6+BI6 -> 988712 | M6: 2483769 | N6: 0 | O6: 0.040294187 | P6: =BU6^4 -> 8.7885835e-13 | Q6: =S6/M6 -> 0.11878641 | R6: 665735 | S6: 295038 | T6: =AH6 -> 0.0091626078 | U6: =LN(M6) -> 14.725288 | V6: =LN(N6+1) -> 0 | W6: =LN(O6) -> -3.2115481 | X6: =LN(P6) -> -27.760153 | Z6: =(AB6*AD6)^4 -> 1.8360986e-13 | AA6: 0.08266 | AB6: =BV6 -> 0.020268432 | AD6: 0.03229638 | AG6: =A6 -> AR | AH6: ='Final-2'!B$41+'Final-2'!B$42*M6+'Final-2'!B$43*N6+'Final-2'!B$44*O6+'Final-2'!B$45*P6 -> 0.0091626078 | AI6: =C6 -> 0 | AJ6: =1/ABS(AH6-AI6) -> 109.13923 | AK6: 0.56712673 | AL6: 0.018853929 | AM6: 0.56628953 | AO6: 0.033518355 | AQ6: 0 | AR6: 10.86044 | AS6: 14.725288 | AT6: 11.25444 | AV6: 4485 | AW6: 5876 | AX6: 4485 | AY6: 5856 | BA6: 0.43287327 | BB6: 0.43371047 | BC6: AR | BD6: AR | BE6: Arkansas | BF6: 2350725 | BG6: 799075 | BH6: 156497 | BI6: 33140 | BJ6: 0.033518355 | BL6: 0.018853929 | BM6: AR | BO6: arkansas | BP6: 0.95970581 | BQ6: 0.96770362 | BT6: arkansas | BU6: 0.00096823265 | BV6: 0.020268432 | BW6: 8.266 | BX6: Arkansas | BZ6: Arkansas | CA6: 0 | CD6: 646 | CE6: 0 | CG6: AR | CH6: ARKANSAS | CI6: AR | CJ6: 102 | CK6: 144 | CL6: 400
A7: CA | B7: CALIFORNIA | C7: =F7/E7 -> 0.021141521 | D7: 1 | E7: 8955505 | F7: 189333 | G7: 6268932 | H7: 2497240 | J7: 155973 | K7: 202.52962 | L7: =BG7+BH7+BI7 -> 13940250 | M7: 31589153 | N7: 0 | O7: 0.0045230302 | P7: =BU7^4 -> 1.1583812e-12 | Q7: =S7/M7 -> 0.11454581 | R7: 5966475 | S7: 3618405 | T7: =AH7 -> 0.090395311 | U7: =LN(M7) -> 17.268324 | V7: =LN(N7+1) -> 0 | W7: =LN(O7) -> -5.3985731 | X7: =LN(P7) -> -27.483998 | Z7: =(AB7*AD7)^4 -> 8.5083149e-16 | AA7: 0.44598 | AB7: =BV7 -> 0.046286746 | AD7: 0.003689812 | AG7: =A7 -> CA | AH7: ='Final-2'!B$41+'Final-2'!B$42*M7+'Final-2'!B$43*N7+'Final-2'!B$44*O7+'Final-2'!B$45*P7 -> 0.090395311 | AI7: =C7 -> 0.021141521 | AJ7: =1/ABS(AH7-AI7) -> 14.439643 | AK7: 0.27374446 | AL7: 0.088973952 | AM7: 0.36657582 | AO7: 0.0045763885 | AQ7: 0.02092114 | AR7: 11.957438 | AS7: 17.268324 | AT7: 12.045839 | AV7: 64843 | AW7: 24441 | AX7: 64843 | AY7: 37526 | BA7: 0.72625554 | BB7: 0.63342418 | BC7: CA | BD7: CA | BE7: California | BF7: 29760021 | BG7: 11796527 | BH7: 2079927 | BI7: 63796 | BJ7: 0.0045763885 | BL7: 0.088973952 | BM7: CA | BO7: califo~1 | BP7: 0.99547697 | BQ7: 0.99631019 | BT7: califo~1 | BU7: 0.0010374397 | BV7: 0.046286746 | BW7: 44.598 | BX7: California | BZ7: California | CA7: 0 | CD7: 3750 | CE7: 0 | CG7: CA | CH7: CALIFORNIA | CI7: CA | CJ7: 1328 | CK7: 1076 | CL7: 1346
A8: CO | B8: COLORADO | C8: =F8/E8 -> 0.0029577777 | D8: 1 | E8: 848272 | F8: 2509 | G8: 570477 | H8: 275286 | J8: 103730 | K8: 36.118625 | L8: =BG8+BH8+BI8 -> 1637440 | M8: 3746585 | N8: 0.014786325 | O8: 0.0079445411 | P8: =BU8^4 -> 6.5829148e-13 | Q8: =S8/M8 -> 0.14506784 | R8: 922112 | S8: 543509 | T8: =AH8 -> -0.0089372041 | U8: =LN(M8) -> 15.136355 | V8: =LN(N8+1) -> 0.014678073 | W8: =LN(O8) -> -4.8352702 | X8: =LN(P8) -> -28.049129 | Z8: =(AB8*AD8)^4 -> 2.4398562e-14 | AA8: 0.35954 | AB8: =BV8 -> 0.038557176 | AD8: 0.010250283 | AG8: =A8 -> CO | AH8: ='Final-2'!B$41+'Final-2'!B$42*M8+'Final-2'!B$43*N8+'Final-2'!B$44*O8+'Final-2'!B$45*P8 -> -0.0089372041 | AI8: =C8 -> 0.0029577777 | AJ8: =1/ABS(AH8-AI8) -> 84.069065 | AK8: 0.61254162 | AL8: 0.032917876 | AM8: 0.56444167 | AO8: 0.010797342 | AQ8: 0.0029534121 | AR8: 11.549547 | AS8: 15.136355 | AT8: 11.344495 | AV8: 6982 | AW8: 11038 | AX8: 6982 | AY8: 9048 | BA8: 0.38745838 | BB8: 0.43555833 | BC8: CO | BD8: CO | BE8: Colorado | BF8: 3294394 | BG8: 1124306 | BH8: 495454 | BI8: 17680 | BJ8: 0.010797342 | BL8: 0.032917876 | BM8: CO | BO8: colorado | BP8: 0.99205546 | BQ8: 0.98974972 | BT8: colorado | BU8: 0.0009007506 | BV8: 0.038557176 | BW8: 35.954 | BX8: Colorado | BZ8: Colorado | CA8: 17.3 | CB8: 6237 | CC8: 1952 | CD8: 1170 | CE8: 0.014786325 | CG8: CO | CH8: COLORADO | CI8: CO | CJ8: 217 | CK8: 185 | CL8: 768
A9: CT | B9: CONNECTICUT | C9: =F9/E9 -> 0.00025988579 | D9: 1 | E9: 888852 | F9: 231 | G9: 646754 | H9: 241867 | J9: 4845 | K9: 675.88483 | L9: =BG9+BH9+BI9 -> 1673442 | M9: 3274662 | N9: 0.35774908 | O9: 0.045612423 | P9: =BU9^4 -> 2.6797815e-08 | Q9: =S9/M9 -> 0.16994456 | R9: 1153096 | S9: 556511 | T9: =AH9 -> 0.12620393 | U9: =LN(M9) -> 15.001725 | V9: =LN(N9+1) -> 0.30582824 | W9: =LN(O9) -> -3.0875752 | X9: =LN(P9) -> -17.434945 | Z9: =(AB9*AD9)^4 -> 2.3237808e-08 | AA9: 0.00238 | AB9: =BV9 -> 0.26023043 | AD9: 0.047445028 | AG9: =A9 -> CT | AH9: ='Final-2'!B$41+'Final-2'!B$42*M9+'Final-2'!B$43*N9+'Final-2'!B$44*O9+'Final-2'!B$45*P9 -> 0.12620393 | AI9: =C9 -> 0.00025988579 | AJ9: =1/ABS(AH9-AI9) -> 7.9400339 | AK9: 0.97583618 | AL9: 0.29125218 | AM9: 0.98529412 | AO9: 0.04834706 | AQ9: 0.00025985202 | AR9: 8.4857025 | AS9: 15.001725 | AT9: 9.9281802 | AV9: 177 | AW9: 7148 | AX9: 177 | AY9: 11859 | BA9: 0.024163823 | BB9: 0.014705882 | BC9: CT | BD9: CT | BE9: Connecticut | BF9: 3287116 | BG9: 1308624 | BH9: 283912 | BI9: 80906 | BJ9: 0.04834706 | BL9: 0.29125218 | BM9: CT | BO9: connec~1 | BP9: 0.95438758 | BQ9: 0.95255497 | BT9: connec~1 | BU9: 0.012794545 | BV9: 0.26023043 | BW9: 0.238 | BX9: Connecticut | BZ9: Connecticut | CA9: 193.9 | CB9: 502092 | CC9: 1940-59 | CD9: 542 | CE9: 0.35774908 | CG9: CT | CH9: CONNECTICUT | CI9: CT | CJ9: 196 | CK9: 245 | CL9: 101
A10: DE | B10: DELAWARE | C10: =F10/E10 -> 0.25259005 | D10: 1 | E10: 262833 | F10: 66389 | G10: 132272 | H10: 64172 | J10: 1955 | K10: 366.85269 | L10: =BG10+BH10+BI10 -> 334126 | M10: 717197 | N10: 0.21960784 | O10: 0.13832888 | P10: =BU10^4 -> 2.0408282e-08 | Q10: =S10/M10 -> 0.27999281 | R10: 441222 | S10: 200810 | T10: =AH10 -> 0.15290266 | U10: =LN(M10) -> 13.483106 | V10: =LN(N10+1) -> 0.19852937 | W10: =LN(O10) -> -1.9781213 | X10: =LN(P10) -> -17.707325 | Z10: =(AB10*AD10)^4 -> 1.6215259e-08 | AA10: 0.02219 | AB10: =BV10 -> 0.11872671 | AD10: 0.095045716 | AG10: =A10 -> DE | AH10: ='Final-2'!B$41+'Final-2'!B$42*M10+'Final-2'!B$43*N10+'Final-2'!B$44*O10+'Final-2'!B$45*P10 -> 0.15290266 | AI10: =C10 -> 0.25259005 | AJ10: =1/ABS(AH10-AI10) -> 10.031359 | AK10: 0.98427311 | AL10: 0.0070425912 | AM10: 0.96403509 | AO10: 0.096870642 | AQ10: 0.22521345 | AR10: 7.5781455 | AS10: 13.483106 | AT10: 8.6360423 | AV10: 82 | AW10: 5132 | AX10: 82 | AY10: 2198 | BA10: 0.015726889 | BB10: 0.035964912 | BC10: DE | BD10: DE | BE10: Delaware | BF10: 666168 | BG10: 287659 | BH10: 14100 | BI10: 32367 | BJ10: 0.096870642 | BL10: 0.0070425912 | BM10: DE | BO10: deleware | BP10: 0.86167112 | BQ10: 0.90495428 | BT10: deleware | BU10: 0.011952304 | BV10: 0.11872671 | BW10: 2.219 | BX10: Delaware | BZ10: Delaware | CA10: 11.2 | CB10: 30000 | CC10: 1963 | CD10: 51 | CE10: 0.21960784 | CG10: DE | CH10: DELAWARE | CI10: DE | CJ10: 11 | CK10: 40 | CL10: 0
A11: FL | B11: FLORIDA | C11: =F11/E11 -> 0.077833555 | D11: 1 | E11: 3867792 | F11: 301044 | G11: 2453078 | H11: 1113670 | J11: 53997 | K11: 262.33994 | L11: =BG11+BH11+BI11 -> 5794452 | M11: 14165570 | N11: 0.11101558 | O11: 0.0079942105 | P11: =BU11^4 -> 3.6552342e-12 | Q11: =S11/M11 -> 0.093013977 | R11: 3421260 | S11: 1317596 | T11: =AH11 -> 0.059825541 | U11: =LN(M11) -> 16.466325 | V11: =LN(N11+1) -> 0.10527454 | W11: =LN(O11) -> -4.8290377 | X11: =LN(P11) -> -26.334861 | Z11: =(AB11*AD11)^4 -> 1.5346772e-13 | AA11: 0.07562 | AB11: =BV11 -> 0.062671969 | AD11: 0.009986905 | AG11: =A11 -> FL | AH11: ='Final-2'!B$41+'Final-2'!B$42*M11+'Final-2'!B$43*N11+'Final-2'!B$44*O11+'Final-2'!B$45*P11 -> 0.059825541 | AI11: =C11 -> 0.077833555 | AJ11: =1/ABS(AH11-AI11) -> 55.530833 | AK11: 0.59280739 | AL11: 0.28741478 | AM11: 0.43893859 | AO11: 0.010658989 | AQ11: 0.074953059 | AR11: 10.896684 | AS11: 16.466325 | AT11: 11.642004 | AV11: 24083 | AW11: 35061 | AX11: 24083 | AY11: 18841 | BA11: 0.40719261 | BB11: 0.56106141 | BC11: FL | BD11: FL | BE11: Florida | BF11: 12937926 | BG11: 4956240 | BH11: 776449 | BI11: 61763 | BJ11: 0.010658989 | BL11: 0.28741478 | BM11: FL | BO11: florida | BP11: 0.99200579 | BQ11: 0.9900131 | BT11: florida | BU11: 0.0013827027 | BV11: 0.062671969 | BW11: 7.562 | BX11: Florida | BZ11: Florida | CA11: 206.6 | CB11: 171783 | CC11: 1950-64 | CD11: 1861 | CE11: 0.11101558 | CG11: FL | CH11: FLORIDA | CI11: FL | CJ11: 389 | CK11: 526 | CL11: 946
A12: GA | B12: GEORGIA | C12: =F12/E12 -> 0.0041858291 | D12: 1 | E12: 1343342 | F12: 5623 | G12: 576266 | H12: 761453 | J12: 57919 | K12: 124.32677 | L12: =BG12+BH12+BI12 -> 3106393 | M12: 7200882 | N12: 0.0078556263 | O12: 0.028137824 | P12: =BU12^4 -> 9.9588679e-13 | Q12: =S12/M12 -> 0.077122775 | R12: 1436829 | S12: 555352 | T12: =AH12 -> 0.019300974 | U12: =LN(M12) -> 15.789714 | V12: =LN(N12+1) -> 0.0078249315 | W12: =LN(O12) -> -3.5706406 | X12: =LN(P12) -> -27.635143 | Z12: =(AB12*AD12)^4 -> 5.8857317e-14 | AA12: 0.03892 | AB12: =BV12 -> 0.02061609 | AD12: 0.023891522 | AG12: =A12 -> GA | AH12: ='Final-2'!B$41+'Final-2'!B$42*M12+'Final-2'!B$43*N12+'Final-2'!B$44*O12+'Final-2'!B$45*P12 -> 0.019300974 | AI12: =C12 -> 0.0041858291 | AJ12: =1/ABS(AH12-AI12) -> 66.158812 | AK12: 0.67003108 | AL12: 0.17099586 | AM12: 0.65996041 | AO12: 0.024595729 | AQ12: 0.0041770929 | AR12: 10.966801 | AS12: 15.789714 | AT12: 11.619742 | AV12: 9448 | AW12: 19185 | AX12: 9448 | AY12: 18337 | BA12: 0.32996892 | BB12: 0.34003959 | BC12: GA | BD12: GA | BE12: Georgia | BF12: 6478216 | BG12: 1935479 | BH12: 1094510 | BI12: 76404 | BJ12: 0.024595729 | BL12: 0.17099586 | BM12: GA | BO12: georgia | BP12: 0.97186218 | BQ12: 0.97610848 | BT12: georgia | BU12: 0.00099897011 | BV12: 0.02061609 | BW12: 3.892 | BX12: Georgia | BZ12: Georgia | CA12: 11.1 | CB12: 3150 | CC12: 1924 | CD12: 1413 | CE12: 0.0078556263 | CG12: GA | CH12: GEORGIA | CI12: GA | CJ12: 171 | CK12: 435 | CL12: 807
A13: HI | B13: HAWAII | C13: =F13/E13 -> 0 | D13: 1 | E13: 229449 | F13: 0 | G13: 168101 | H13: 61348 | J13: 6423 | K13: 184.77581 | L13: =BG13+BH13+BI13 -> 567765 | M13: 1186815 | N13: 0 | O13: 0.0095240957 | P13: =BU13^4 -> 4.1177025e-11 | Q13: =S13/M13 -> 0.12272511 | R13: 359706 | S13: 145652 | T13: =AH13 -> -0.021829682 | U13: =LN(M13) -> 13.986784 | V13: =LN(N13+1) -> 0 | W13: =LN(O13) -> -4.6539303 | X13: =LN(P13) -> -23.913141 | Z13: =(AB13*AD13)^4 -> 7.4759228e-16 | AA13: 0.08548 | AB13: =BV13 -> 0.035368224 | AD13: 0.0046752296 | AG13: =A13 -> HI | AH13: ='Final-2'!B$41+'Final-2'!B$42*M13+'Final-2'!B$43*N13+'Final-2'!B$44*O13+'Final-2'!B$45*P13 -> -0.021829682 | AI13: =C13 -> 0 | AJ13: =1/ABS(AH13-AI13) -> 45.809187 | AK13: 0.71428571 | AL13: 0.0010718635 | AM13: 0.36655486 | AO13: 0.0070328393 | AQ13: 0 | AR13: 8.7676406 | AS13: 13.986784 | AT13: 8.3267588 | AV13: 1322 | AW13: 3305 | AX13: 1322 | AY13: 765 | BA13: 0.28571429 | BB13: 0.63344514 | BC13: HI | BD13: HI | BE13: Hawaii | BF13: 1108229 | BG13: 560286 | BH13: 3486 | BI13: 3993 | BJ13: 0.0070328393 | BL13: 0.0010718635 | BM13: HI | BO13: hawaii | BP13: 0.9904759 | BQ13: 0.99532477 | BT13: hawaii | BU13: 0.0025331665 | BV13: 0.035368224 | BW13: 8.548 | BX13: Hawaii | BZ13: Hawaii | CA13: 0 | CD13: 77 | CE13: 0 | CG13: HI | CH13: HAWAII | CI13: HI | CJ13: 34 | CK13: 43 | CL13: 0
A14: ID | B14: IDAHO | C14: =F14/E14 -> 0 | D14: 1 | E14: 335569 | F14: 0 | G14: 231352 | H14: 104217 | J14: 82751 | K14: 14.057365 | L14: =BG14+BH14+BI14 -> 5351411 | M14: 1163261 | N14: 0 | O14: 0.026148588 | P14: =BU14^4 -> 1.7154896e-12 | Q14: =S14/M14 -> 0.15856717 | R14: 349964 | S14: 184455 | T14: =AH14 -> -0.0078611245 | U14: =LN(M14) -> 13.966738 | V14: =LN(N14+1) -> 0 | W14: =LN(O14) -> -3.6439601 | X14: =LN(P14) -> -27.091323 | Z14: =(AB14*AD14)^4 -> 1.0629398e-12 | AA14: 0.60588 | AB14: =BV14 -> 0.025523251 | AD14: 0.039782418 | AG14: =A14 -> ID | AH14: ='Final-2'!B$41+'Final-2'!B$42*M14+'Final-2'!B$43*N14+'Final-2'!B$44*O14+'Final-2'!B$45*P14 -> -0.0078611245 | AI14: =C14 -> 0 | AJ14: =1/ABS(AH14-AI14) -> 127.20826 | AK14: 0.63846247 | AL14: 0.15619768 | AM14: 0.69903401 | AO14: 0.028546303 | AQ14: 0 | AR14: 11.323591 | AS14: 13.966738 | AT14: 10.99764 | AV14: 11964 | AW14: 21128 | AX14: 11964 | AY14: 27788 | BA14: 0.36153753 | BB14: 0.30096599 | BC14: ID | BD14: ID | BE14: Idaho | BF14: 11430602 | BG14: 4200428 | BH14: 998220 | BI14: 152763 | BJ14: 0.028546303 | BL14: 0.15619768 | BM14: ID | BO14: idaho | BP14: 0.97385141 | BQ14: 0.96021758 | BT14: idaho | BU14: 0.0011444505 | BV14: 0.025523251 | BW14: 60.588 | BX14: Idaho | BZ14: Idaho | CA14: 0 | CD14: 613 | CE14: 0 | CG14: ID | CH14: IDAHO | CI14: ID | CJ14: 0 | CK14: 81 | CL14: 532
A15: IL | B15: ILLINOIS | C15: =F15/E15 -> 0.092502027 | D15: 1 | E15: 3099878 | F15: 286745 | G15: 1985634 | H15: 827499 | J15: 55593 | K15: 212.7955 | L15: =BG15+BH15+BI15 -> 2587182 | M15: 11829940 | N15: 0.082538976 | O15: 0.028193774 | P15: =BU15^4 -> 2.0427933e-13 | Q15: =S15/M15 -> 0.12092251 | R15: 3006384 | S15: 1430506 | T15: =AH15 -> 0.059439332 | U15: =LN(M15) -> 16.286144 | V15: =LN(N15+1) -> 0.079309185 | W15: =LN(O15) -> -3.5686541 | X15: =LN(P15) -> -29.219288 | Z15: =(AB15*AD15)^4 -> 2.5760392e-14 | AA15: 0.01266 | AB15: =BV15 -> 0.013967169 | AD15: 0.02868334 | AG15: =A15 -> IL | AH15: ='Final-2'!B$41+'Final-2'!B$42*M15+'Final-2'!B$43*N15+'Final-2'!B$44*O15+'Final-2'!B$45*P15 -> 0.059439332 | AI15: =C15 -> 0.092502027 | AJ15: =1/ABS(AH15-AI15) -> 30.245568 | AK15: 0.58667865 | AL15: 0.050957173 | AM15: 0.62541291 | AO15: 0.048286514 | AQ15: 0.088470504 | AR15: 10.925813 | AS15: 16.286144 | AT15: 11.830746 | AV15: 8278 | AW15: 11750 | AX15: 8278 | AY15: 13821 | BA15: 0.41332135 | BB15: 0.37458709 | BC15: IL | BD15: IL | BE15: Illinois | BF15: 5544159 | BG15: 1947671 | BH15: 514585 | BI15: 124926 | BJ15: 0.048286514 | BL15: 0.050957173 | BM15: IL | BO15: illinois | BP15: 0.97180623 | BQ15: 0.97131666 | BT15: illinois | BU15: 0.00067228915 | BV15: 0.013967169 | BW15: 1.266 | BX15: Illinois | BZ15: Illinois | CA15: 185.3 | CB15: 445623 | CC15: 1958-59 | CD15: 2245 | CE15: 0.082538976 | CG15: IL | CH15: ILLINOIS | CI15: IL | CJ15: 82 | CK15: 635 | CL15: 1528
A16: IN | B16: INDIANA | C16: =F16/E16 -> 0.042572953 | D16: 1 | E16: 1449183 | F16: 61696 | G16: 827514 | H16: 559973 | J16: 35870 | K16: 161.79178 | L16: =BG16+BH16+BI16 -> 1322064 | M16: 5803471 | N16: 0.12041443 | O16: 0.032808242 | P16: =BU16^4 -> 4.7533684e-11 | Q16: =S16/M16 -> 0.13494097 | R16: 1433178 | S16: 783126 | T16: =AH16 -> 0.051601285 | U16: =LN(M16) -> 15.573967 | V16: =LN(N16+1) -> 0.11369864 | W16: =LN(O16) -> -3.4170755 | X16: =LN(P16) -> -23.769583 | Z16: =(AB16*AD16)^4 -> 3.5166619e-11 | AA16: 0.01725 | AB16: =BV16 -> 0.050428579 | AD16: 0.048289858 | AG16: =A16 -> IN | AH16: ='Final-2'!B$41+'Final-2'!B$42*M16+'Final-2'!B$43*N16+'Final-2'!B$44*O16+'Final-2'!B$45*P16 -> 0.051601285 | AI16: =C16 -> 0.042572953 | AJ16: =1/ABS(AH16-AI16) -> 110.76243 | AK16: 0.52333689 | AL16: 0.011856963 | AM16: 0.54423529 | AO16: 0.042302793 | AQ16: 0.041691651 | AR16: 10.487657 | AS16: 15.573967 | AT16: 11.437986 | AV16: 5811 | AW16: 6380 | AX16: 5811 | AY16: 6939 | BA16: 0.47666311 | BB16: 0.45576471 | BC16: IN | BD16: IN | BE16: Indiana | BF16: 2776755 | BG16: 1096619 | BH16: 169518 | BI16: 55927 | BJ16: 0.042302793 | BL16: 0.011856963 | BM16: IN | BO16: indiana | BP16: 0.96719176 | BQ16: 0.95171014 | BT16: indiana | BU16: 0.0026257318 | BV16: 0.050428579 | BW16: 1.725 | BX16: Indiana | BZ16: Indiana | CA16: 156.9 | CB16: 280000 | CC16: 1956 | CD16: 1303 | CE16: 0.12041443 | CG16: IN | CH16: INDIANA | CI16: IN | CJ16: 132 | CK16: 319 | CL16: 852
A17: IA | B17: IOWA | C17: =F17/E17 -> 0.001073349 | D17: 1 | E17: 858062 | F17: 921 | G17: 604505 | H17: 252636 | J17: 55875 | K17: 50.859311 | L17: =BG17+BH17+BI17 -> 440809 | M17: 2841764 | N17: 0 | O17: 0.036918432 | P17: =BU17^4 -> 9.382972e-12 | Q17: =S17/M17 -> 0.21758387 | R17: 1077704 | S17: 618322 | T17: =AH17 -> 0.0076792201 | U17: =LN(M17) -> 14.859936 | V17: =LN(N17+1) -> 0 | W17: =LN(O17) -> -3.2990443 | X17: =LN(P17) -> -25.392125 | Z17: =(AB17*AD17)^4 -> 6.4762692e-12 | AA17: 0.00187 | AB17: =BV17 -> 0.037112103 | AD17: 0.042984874 | AG17: =A17 -> IA | AH17: ='Final-2'!B$41+'Final-2'!B$42*M17+'Final-2'!B$43*N17+'Final-2'!B$44*O17+'Final-2'!B$45*P17 -> 0.0076792201 | AI17: =C17 -> 0.001073349 | AJ17: =1/ABS(AH17-AI17) -> 151.38049 | AK17: 0.54488981 | AL17: 0.0046318287 | AM17: 0.55001462 | AO17: 0.039840384 | AQ17: 0.0010727734 | AR17: 10.930872 | AS17: 14.859936 | AT17: 11.632502 | AV17: 3077 | AW17: 3684 | AX17: 3077 | AY17: 3761 | BA17: 0.45511019 | BB17: 0.44998538 | BC17: IA | BD17: IA | BE17: Iowa | BF17: 1006749 | BG17: 372922 | BH17: 50325 | BI17: 17562 | BJ17: 0.039840384 | BL17: 0.0046318287 | BM17: IA | BO17: iowa | BP17: 0.96308157 | BQ17: 0.95701513 | BT17: iowa | BU17: 0.0017501896 | BV17: 0.037112103 | BW17: 0.187 | BX17: Iowa | BZ17: Iowa | CA17: 0 | CD17: 781 | CE17: 0 | CG17: IA | CH17: IOWA | CI17: IA | CJ17: 0 | CK17: 147 | CL17: 634
A18: KS | B18: KANSAS | C18: =F18/E18 -> 0.064564023 | D18: 1 | E18: 687008 | F18: 44356 | G18: 402483 | H18: 240169 | J18: 81823 | K18: 31.352163 | L18: =BG18+BH18+BI18 -> 1178931 | M18: 2565328 | N18: 0.2389881 | O18: 0.070626087 | P18: =BU18^4 -> 8.3954224e-14 | Q18: =S18/M18 -> 0.14940312 | R18: 1019160 | S18: 383268 | T18: =AH18 -> 0.10668157 | U18: =LN(M18) -> 14.757597 | V18: =LN(N18+1) -> 0.21429499 | W18: =LN(O18) -> -2.6503557 | X18: =LN(P18) -> -30.108505 | Z18: =(AB18*AD18)^4 -> 1.606636e-14 | AA18: 0.00539 | AB18: =BV18 -> 0.0047015825 | AD18: 0.075724309 | AG18: =A18 -> KS | AH18: ='Final-2'!B$41+'Final-2'!B$42*M18+'Final-2'!B$43*N18+'Final-2'!B$44*O18+'Final-2'!B$45*P18 -> 0.10668157 | AI18: =C18 -> 0.064564023 | AJ18: =1/ABS(AH18-AI18) -> 23.74307 | AK18: 0.5635946 | AL18: 0.016156134 | AM18: 0.6248766 | AO18: 0.075464128 | AQ18: 0.062565347 | AR18: 11.312314 | AS18: 14.757597 | AT18: 11.80053 | AV18: 4560 | AW18: 5889 | AX18: 4560 | AY18: 7596 | BA18: 0.4364054 | BB18: 0.3751234 | BC18: KS | BD18: KS | BE18: Kansas | BF18: 2477574 | BG18: 941626 | BH18: 148338 | BI18: 88967 | BJ18: 0.075464128 | BL18: 0.016156134 | BM18: KS | BO18: kansas | BP18: 0.92937391 | BQ18: 0.92427569 | BT18: kansas | BU18: 0.00053828297 | BV18: 0.0047015825 | BW18: 0.539 | BX18: Kansas | BZ18: Kansas | CA18: 240.9 | CB18: 179500 | CC18: 1956-59 | CD18: 1008 | CE18: 0.2389881 | CG18: KS | CH18: KANSAS | CI18: KS | CJ18: 136 | CK18: 174 | CL18: 698
A19: KY | B19: KENTUCKY | C19: =F19/E19 -> 0.008453283 | D19: 1 | E19: 1219053 | F19: 10305 | G19: 803739 | H19: 405009 | J19: 39732 | K19: 97.156423 | L19: =BG19+BH19+BI19 -> 1565711 | M19: 3860219 | N19: 0.2394152 | O19: 0.062560236 | P19: =BU19^4 -> 4.6168544e-11 | Q19: =S19/M19 -> 0.18910715 | R19: 1396789 | S19: 729995 | T19: =AH19 -> 0.10495104 | U19: =LN(M19) -> 15.166234 | V19: =LN(N19+1) -> 0.21463966 | W19: =LN(O19) -> -2.7716254 | X19: =LN(P19) -> -23.798722 | Z19: =(AB19*AD19)^4 -> 2.7808103e-11 | AA19: 0.04206 | AB19: =BV19 -> 0.034216326 | AD19: 0.067113436 | AG19: =A19 -> KY | AH19: ='Final-2'!B$41+'Final-2'!B$42*M19+'Final-2'!B$43*N19+'Final-2'!B$44*O19+'Final-2'!B$45*P19 -> 0.10495104 | AI19: =C19 -> 0.008453283 | AJ19: =1/ABS(AH19-AI19) -> 10.362935 | AK19: 0.60437221 | AL19: 0.027568786 | AM19: 0.64394762 | AO19: 0.066583808 | AQ19: 0.0084177541 | AR19: 10.589912 | AS19: 15.166234 | AT19: 11.198187 | AV19: 5574 | AW19: 8515 | AX19: 5574 | AY19: 10081 | BA19: 0.39562779 | BB19: 0.35605238 | BC19: KY | BD19: KY | BE19: Kentucky | BF19: 3685296 | BG19: 1160660 | BH19: 300800 | BI19: 104251 | BJ19: 0.066583808 | BL19: 0.027568786 | BM19: KY | BO19: kentucky | BP19: 0.93743976 | BQ19: 0.93288656 | BT19: kentucky | BU19: 0.0026066729 | BV19: 0.034216326 | BW19: 4.206 | BX19: Kentucky | BZ19: Kentucky | CA19: 204.7 | CB19: 185500 | CC19: 1956-64 | CD19: 855 | CE19: 0.2394152 | CG19: KY | CH19: KENTUCKY | CI19: KY | CJ19: 93 | CK19: 226 | CL19: 536
A20: LA | B20: LOUISIANA | C20: =F20/E20 -> 0.029383964 | D20: 1 | E20: 1019876 | F20: 29968 | G20: 625294 | H20: 364614 | J20: 43566 | K20: 99.672543 | L20: =BG20+BH20+BI20 -> 1645690 | M20: 4342334 | N20: 0 | O20: 0.02111473 | P20: =BU20^4 -> 2.56823e-12 | Q20: =S20/M20 -> 0.14867742 | R20: 1197890 | S20: 645607 | T20: =AH20 -> 5.8636344e-05 | U20: =LN(M20) -> 15.283923 | V20: =LN(N20+1) -> 0 | W20: =LN(O20) -> -3.8577844 | X20: =LN(P20) -> -26.687804 | Z20: =(AB20*AD20)^4 -> 4.7847545e-14 | AA20: 0.02757 | AB20: =BV20 -> 0.024366276 | AD20: 0.019194454 | AG20: =A20 -> LA | AH20: ='Final-2'!B$41+'Final-2'!B$42*M20+'Final-2'!B$43*N20+'Final-2'!B$44*O20+'Final-2'!B$45*P20 -> 5.8636344e-05 | AI20: =C20 -> 0.029383964 | AJ20: =1/ABS(AH20-AI20) -> 34.100215 | AK20: 0.63027674 | AL20: 0.02355587 | AM20: 0.58336775 | AO20: 0.01958206 | AQ20: 0.02896053 | AR20: 10.682032 | AS20: 15.283923 | AT20: 11.004081 | AV20: 6052 | AW20: 10317 | AX20: 6052 | AY20: 8474 | BA20: 0.36972326 | BB20: 0.41663225 | BC20: LA | BD20: LA | BE20: Louisiana | BF20: 4219973 | BG20: 1217736 | BH20: 395728 | BI20: 32226 | BJ20: 0.01958206 | BL20: 0.02355587 | BM20: LA | BO20: louisi~1 | BP20: 0.97888527 | BQ20: 0.98080555 | BT20: louisi~1 | BU20: 0.0012659265 | BV20: 0.024366276 | BW20: 2.757 | BX20: Louisiana | BZ20: Louisiana | CA20: 0 | CD20: 929 | CE20: 0 | CG20: LA | CH20: LOUISIANA | CI20: LA | CJ20: 45 | CK20: 272 | CL20: 612
A21: ME | B21: MAINE | C21: =F21/E21 -> 0.10508832 | D21: 1 | E21: 355815 | F21: 37392 | G21: 200836 | H21: 117587 | J21: 30865 | K21: 40.219731 | L21: =BG21+BH21+BI21 -> 570883 | M21: 1241382 | N21: 0.29295039 | O21: 0.020612175 | P21: =BU21^4 -> 2.6582764e-10 | Q21: =S21/M21 -> 0.17563006 | R21: 379282 | S21: 218024 | T21: =AH21 -> 0.075483687 | U21: =LN(M21) -> 14.031736 | V21: =LN(N21+1) -> 0.25692673 | W21: =LN(O21) -> -3.8818734 | X21: =LN(P21) -> -22.048173 | Z21: =(AB21*AD21)^4 -> 1.6154741e-10 | AA21: 0.00942 | AB21: =BV21 -> 0.11374676 | AD21: 0.031342669 | AG21: =A21 -> ME | AH21: ='Final-2'!B$41+'Final-2'!B$42*M21+'Final-2'!B$43*N21+'Final-2'!B$44*O21+'Final-2'!B$45*P21 -> 0.075483687 | AI21: =C21 -> 0.10508832 | AJ21: =1/ABS(AH21-AI21) -> 33.778499 | AK21: 0.76583661 | AL21: 0.030008796 | AM21: 0.57720371 | AO21: 0.033726701 | AQ21: 0.099925258 | AR21: 10.337378 | AS21: 14.031736 | AT21: 10.024687 | AV21: 2144 | AW21: 7012 | AX21: 2144 | AY21: 2927 | BA21: 0.23416339 | BB21: 0.42279629 | BC21: ME | BD21: ME | BE21: Maine | BF21: 1227928 | BG21: 464593 | BH21: 87036 | BI21: 19254 | BJ21: 0.033726701 | BL21: 0.030008796 | BM21: ME | BO21: maine | BP21: 0.97938783 | BQ21: 0.96865733 | BT21: maine | BU21: 0.0040378486 | BV21: 0.11374676 | BW21: 0.942 | BX21: Maine | BZ21: Maine | CA21: 112.2 | CB21: 79406 | CC21: 1955-57 | CD21: 383 | CE21: 0.29295039 | CG21: ME | CH21: MAINE | CI21: ME | CJ21: 18 | CK21: 55 | CL21: 310
A22: MD | B22: MARYLAND | C22: =F22/E22 -> 0.070257916 | D22: 1 | E22: 1689774 | F22: 118720 | G22: 1175070 | H22: 395984 | J22: 9775 | K22: 515.85043 | L22: =BG22+BH22+BI22 -> 2482462 | M22: 5042438 | N22: 0.059493671 | O22: 0.069779778 | P22: =BU22^4 -> 7.3736343e-10 | Q22: =S22/M22 -> 0.14763811 | R22: 1289354 | S22: 744456 | T22: =AH22 -> 0.061782808 | U22: =LN(M22) -> 15.4334 | V22: =LN(N22+1) -> 0.057791125 | W22: =LN(O22) -> -2.662411 | X22: =LN(P22) -> -21.02794 | Z22: =(AB22*AD22)^4 -> 5.1502388e-10 | AA22: 0.03139 | AB22: =BV22 -> 0.027478196 | AD22: 0.17336787 | AG22: =A22 -> MD | AH22: ='Final-2'!B$41+'Final-2'!B$42*M22+'Final-2'!B$43*N22+'Final-2'!B$44*O22+'Final-2'!B$45*P22 -> 0.061782808 | AI22: =C22 -> 0.070257916 | AJ22: =1/ABS(AH22-AI22) -> 117.9926 | AK22: 0.73098143 | AL22: 0.18447966 | AM22: 0.83234867 | AO22: 0.17402442 | AQ22: 0.067899663 | AR22: 9.1875834 | AS22: 15.4334 | AT22: 10.298229 | AV22: 3462 | AW22: 9407 | AX22: 3462 | AY22: 17188 | BA22: 0.26901857 | BB22: 0.16765133 | BC22: MD | BD22: MD | BE22: Maryland | BF22: 4781468 | BG22: 1363948 | BH22: 686505 | BI22: 432009 | BJ22: 0.17402442 | BL22: 0.18447966 | BM22: MD | BO22: maryland | BP22: 0.93022022 | BQ22: 0.82663213 | BT22: maryland | BU22: 0.0052109919 | BV22: 0.027478196 | BW22: 3.139 | BX22: Maryland | BZ22: Maryland | CA22: 42.3 | CB22: 74000 | CC22: 1963 | CD22: 711 | CE22: 0.059493671 | CG22: MD | CH22: MARYLAND | CI22: MD | CJ22: 229 | CK22: 255 | CL22: 227
A23: MA | B23: MASSACHUSETTS | C23: =F23/E23 -> 0.10394482 | D23: 1 | E23: 1454339 | F23: 151171 | G23: 890623 | H23: 412545 | J23: 7838 | K23: 774.88517 | L23: =BG23+BH23+BI23 -> 2979594 | M23: 6073550 | N23: 0.16325459 | O23: 0.050208226 | P23: =BU23^4 -> 2.6015021e-11 | Q23: =S23/M23 -> 0.16803352 | R23: 2500788 | S23: 1020560 | T23: =AH23 -> 0.080177921 | U23: =LN(M23) -> 15.619454 | V23: =LN(N23+1) -> 0.15122176 | W23: =LN(O23) -> -2.9915764 | X23: =LN(P23) -> -24.372347 | Z23: =(AB23*AD23)^4 -> 1.2999074e-11 | AA23: 0.012 | AB23: =BV23 -> 0.06131232 | AD23: 0.030969226 | AG23: =A23 -> MA | AH23: ='Final-2'!B$41+'Final-2'!B$42*M23+'Final-2'!B$43*N23+'Final-2'!B$44*O23+'Final-2'!B$45*P23 -> 0.080177921 | AI23: =C23 -> 0.10394482 | AJ23: =1/ABS(AH23-AI23) -> 42.075332 | AK23: 0.83625098 | AL23: 0.27257368 | AM23: 0.85823655 | AO23: 0.031393539 | AQ23: 0.098889961 | AR23: 8.966739 | AS23: 15.619454 | AT23: 10.333678 | AV23: 2722 | AW23: 13901 | AX23: 2722 | AY23: 16479 | BA23: 0.16374902 | BB23: 0.14176345 | BC23: MA | BD23: MA | BE23: Massachusetts | BF23: 6016425 | BG23: 2063962 | BH23: 822092 | BI23: 93540 | BJ23: 0.031393539 | BL23: 0.27257368 | BM23: MA | BO23: massac~1 | BP23: 0.94979177 | BQ23: 0.96903077 | BT23: massac~1 | BU23: 0.0022584269 | BV23: 0.06131232 | BW23: 1.2 | BX23: Massachusetts | BZ23: Massachusetts | CA23: 124.4 | CB23: 239000 | CC23: 1957 | CD23: 762 | CE23: 0.16325459 | CG23: MA | CH23: MASSACHUSETTS | CI23: MA | CJ23: 197 | CK23: 403 | CL23: 162
A24: MI | B24: MICHIGAN | C24: =F24/E24 -> 0.0073878771 | D24: 1 | E24: 2027240 | F24: 14977 | G24: 1262280 | H24: 749983 | J24: 56809 | K24: 168.09578 | L24: =BG24+BH24+BI24 -> 4082403 | M24: 9549353 | N24: 0 | O24: 0.0079692585 | P24: =BU24^4 -> 9.2327047e-13 | Q24: =S24/M24 -> 0.12927064 | R24: 1973894 | S24: 1234451 | T24: =AH24 -> 0.0088849483 | U24: =LN(M24) -> 16.071984 | V24: =LN(N24+1) -> 0 | W24: =LN(O24) -> -4.8321638 | X24: =LN(P24) -> -27.710854 | Z24: =(AB24*AD24)^4 -> 1.5346705e-13 | AA24: 0.10085 | AB24: =BV24 -> 0.041963314 | AD24: 0.014915369 | AG24: =A24 -> MI | AH24: ='Final-2'!B$41+'Final-2'!B$42*M24+'Final-2'!B$43*N24+'Final-2'!B$44*O24+'Final-2'!B$45*P24 -> 0.0088849483 | AI24: =C24 -> 0.0073878771 | AJ24: =1/ABS(AH24-AI24) -> 667.9709 | AK24: 0.36278059 | AL24: 0.045330919 | AM24: 0.44884257 | AO24: 0.015132019 | AQ24: 0.0073607204 | AR24: 10.94745 | AS24: 16.071984 | AT24: 11.675138 | AV24: 22000 | AW24: 12525 | AX24: 22000 | AY24: 17916 | BA24: 0.63721941 | BB24: 0.55115743 | BC24: MI | BD24: MI | BE24: Michigan | BF24: 9295297 | BG24: 3014822 | BH24: 1005806 | BI24: 61775 | BJ24: 0.015132019 | BL24: 0.045330919 | BM24: MI | BO24: michigan | BP24: 0.99203074 | BQ24: 0.98508463 | BT24: michigan | BU24: 0.00098023958 | BV24: 0.041963314 | BW24: 10.085 | BX24: Michigan | BZ24: Michigan | CA24: 0 | CD24: 1458 | CE24: 0 | CG24: MI | CH24: MICHIGAN | CI24: MI | CJ24: 218 | CK24: 500 | CL24: 740
A25: MN | B25: MINNESOTA | C25: =F25/E25 -> 0 | D25: 1 | E25: 1255956 | F25: 0 | G25: 898242 | H25: 357714 | J25: 79617 | K25: 57.89653 | L25: =BG25+BH25+BI25 -> 2158733 | M25: 4609548 | N25: 0 | O25: 0.023117161 | P25: =BU25^4 -> 3.9141652e-14 | Q25: =S25/M25 -> 0.15177041 | R25: 1210014 | S25: 699593 | T25: =AH25 -> 0.0027758126 | U25: =LN(M25) -> 15.34364 | V25: =LN(N25+1) -> 0 | W25: =LN(O25) -> -3.7671801 | X25: =LN(P25) -> -30.871589 | Z25: =(AB25*AD25)^4 -> 2.3465754e-15 | AA25: 0.03055 | AB25: =BV25 -> 0.012429222 | AD25: 0.017707803 | AG25: =A25 -> MN | AH25: ='Final-2'!B$41+'Final-2'!B$42*M25+'Final-2'!B$43*N25+'Final-2'!B$44*O25+'Final-2'!B$45*P25 -> 0.0027758126 | AI25: =C25 -> 0 | AJ25: =1/ABS(AH25-AI25) -> 360.25487 | AK25: 0.37985403 | AL25: 0.029435921 | AM25: 0.40499865 | AO25: 0.018670211 | AQ25: 0 | AR25: 11.284983 | AS25: 15.34364 | AT25: 11.778293 | AV25: 15379 | AW25: 9420 | AX25: 15379 | AY25: 10468 | BA25: 0.62014597 | BB25: 0.59500135 | BC25: MN | BD25: MN | BE25: Minnesota | BF25: 4375099 | BG25: 1533077 | BH25: 585352 | BI25: 40304 | BJ25: 0.018670211 | BL25: 0.029435921 | BM25: MN | BO25: minnes~1 | BP25: 0.97688284 | BQ25: 0.9822922 | BT25: minnes~1 | BU25: 0.00044479489 | BV25: 0.012429222 | BW25: 3.055 | BX25: Minnesota | BZ25: Minnesota | CA25: 0 | CD25: 1042 | CE25: 0 | CG25: MN | CH25: MINNESOTA | CI25: MN | CJ25: 128 | CK25: 233 | CL25: 681
A26: MS | B26: MISSISSIPPI | C26: =F26/E26 -> 0 | D26: 1 | E26: 688870 | F26: 0 | G26: 407456 | H26: 281414 | J26: 46914 | K26: 57.49335 | L26: =BG26+BH26+BI26 -> 1028014 | M26: 2697243 | N26: 0 | O26: 0.03050287 | P26: =BU26^4 -> 3.3172813e-12 | Q26: =S26/M26 -> 0.09602064 | R26: 661610 | S26: 258991 | T26: =AH26 -> 0.0016982769 | U26: =LN(M26) -> 14.807741 | V26: =LN(N26+1) -> 0 | W26: =LN(O26) -> -3.4899345 | X26: =LN(P26) -> -26.431876 | Z26: =(AB26*AD26)^4 -> 2.2912169e-13 | AA26: 0.04286 | AB26: =BV26 -> 0.011786146 | AD26: 0.058700899 | AG26: =A26 -> MS | AH26: ='Final-2'!B$41+'Final-2'!B$42*M26+'Final-2'!B$43*N26+'Final-2'!B$44*O26+'Final-2'!B$45*P26 -> 0.0016982769 | AI26: =C26 -> 0 | AJ26: =1/ABS(AH26-AI26) -> 588.83213 | AK26: 0.60656716 | AL26: 0.0082683846 | AM26: 0.57686663 | AO26: 0.057509917 | AQ26: 0 | AR26: 10.756071 | AS26: 14.807741 | AT26: 11.199611 | AV26: 4613 | AW26: 7112 | AX26: 4613 | AY26: 6289 | BA26: 0.39343284 | BB26: 0.42313337 | BC26: MS | BD26: MS | BE26: Mississippi | BF26: 2573216 | BG26: 761316 | BH26: 207577 | BI26: 59121 | BJ26: 0.057509917 | BL26: 0.0082683846 | BM26: MS | BO26: missis~1 | BP26: 0.96949713 | BQ26: 0.9412991 | BT26: missis~1 | BU26: 0.0013495705 | BV26: 0.011786146 | BW26: 4.286 | BX26: Mississippi | BZ26: Mississippi | CA26: 0 | CD26: 726 | CE26: 0 | CG26: MS | CH26: MISSISSIPPI | CI26: MS | CJ26: 41 | CK26: 127 | CL26: 558
A27: MO | B27: MISSOURI | C27: =F27/E27 -> 0.0007596858 | D27: 1 | E27: 1270262 | F27: 965 | G27: 697662 | H27: 571635 | J27: 68898 | K27: 77.266728 | L27: =BG27+BH27+BI27 -> 2345816 | M27: 5323523 | N27: 0 | O27: 0.072427275 | P27: =BU27^4 -> 1.1583528e-10 | Q27: =S27/M27 -> 0.121639 | R27: 1313107 | S27: 647548 | T27: =AH27 -> 0.047231618 | U27: =LN(M27) -> 15.487646 | V27: =LN(N27+1) -> 0 | W27: =LN(O27) -> -2.6251723 | X27: =LN(P27) -> -22.878852 | Z27: =(AB27*AD27)^4 -> 7.2790686e-11 | AA27: 0.03808 | AB27: =BV27 -> 0.060895414 | AD27: 0.047966095 | AG27: =A27 -> MO | AH27: ='Final-2'!B$41+'Final-2'!B$42*M27+'Final-2'!B$43*N27+'Final-2'!B$44*O27+'Final-2'!B$45*P27 -> 0.047231618 | AI27: =C27 -> 0.0007596858 | AJ27: =1/ABS(AH27-AI27) -> 21.518365 | AK27: 0.56273155 | AL27: 0.13087163 | AM27: 0.51438066 | AO27: 0.047386922 | AQ27: 0.00075939738 | AR27: 11.140382 | AS27: 15.487646 | AT27: 11.716813 | AV27: 12275 | AW27: 15797 | AX27: 12275 | AY27: 13002 | BA27: 0.43726845 | BB27: 0.48561934 | BC27: MO | BD27: MO | BE27: Missouri | BF27: 5117073 | BG27: 1614411 | BH27: 620244 | BI27: 111161 | BJ27: 0.047386922 | BL27: 0.13087163 | BM27: MO | BO27: missouri | BP27: 0.92757273 | BQ27: 0.95203391 | BT27: missouri | BU27: 0.0032806524 | BV27: 0.060895414 | BW27: 3.808 | BX27: Missouri | BZ27: Missouri | CA27: 0 | CD27: 1460 | CE27: 0 | CG27: MO | CH27: MISSOURI | CI27: MO | CJ27: 282 | CK27: 368 | CL27: 810
A28: MT | B28: MONTANA | C28: =F28/E28 -> 0 | D28: 1 | E28: 268149 | F28: 0 | G28: 169678 | H28: 98471 | J28: 145556 | K28: 5.9790115 | L28: =BG28+BH28+BI28 -> 349184 | M28: 870281 | N28: 0 | O28: 0.0079640954 | P28: =BU28^4 -> 3.4731989e-14 | Q28: =S28/M28 -> 0.23563654 | R28: 388416 | S28: 205070 | T28: =AH28 -> -0.024365466 | U28: =LN(M28) -> 13.676571 | V28: =LN(N28+1) -> 0 | W28: =LN(O28) -> -4.8328119 | X28: =LN(P28) -> -30.991115 | Z28: =(AB28*AD28)^4 -> 3.6413647e-15 | AA28: 0.27542 | AB28: =BV28 -> 0.019838618 | AD28: 0.012382394 | AG28: =A28 -> MT | AH28: ='Final-2'!B$41+'Final-2'!B$42*M28+'Final-2'!B$43*N28+'Final-2'!B$44*O28+'Final-2'!B$45*P28 -> -0.024365466 | AI28: =C28 -> 0 | AJ28: =1/ABS(AH28-AI28) -> 41.041695 | AK28: 0.43198124 | AL28: 0.014118514 | AM28: 0.30980721 | AO28: 0.011750252 | AQ28: 0 | AR28: 11.888316 | AS28: 13.676571 | AT28: 11.149614 | AV28: 4117 | AW28: 3131 | AX28: 4117 | AY28: 1848 | BA28: 0.56801876 | BB28: 0.69019279 | BC28: MT | BD28: MT | BE28: Montana | BF28: 799065 | BG28: 326038 | BH28: 19043 | BI28: 4103 | BJ28: 0.011750252 | BL28: 0.014118514 | BM28: MT | BO28: montana | BP28: 0.9920359 | BQ28: 0.98761761 | BT28: montana | BU28: 0.00043170036 | BV28: 0.019838618 | BW28: 27.542 | BX28: Montana | BZ28: Montana | CA28: 0 | CD28: 1190 | CE28: 0 | CG28: MT | CH28: MONTANA | CI28: MT | CJ28: 0 | CK28: 53 | CL28: 1137
A29: NE | B29: NEBRASKA | C29: =F29/E29 -> 0.0019950831 | D29: 1 | E29: 466146 | F29: 930 | G29: 308350 | H29: 156866 | J29: 76878 | K29: 21.294935 | L29: =BG29+BH29+BI29 -> 775085 | M29: 1637112 | N29: 0 | O29: 0.042505329 | P29: =BU29^4 -> 1.2776603e-13 | Q29: =S29/M29 -> 0.17883505 | R29: 578157 | S29: 292773 | T29: =AH29 -> 0.0077897061 | U29: =LN(M29) -> 14.308444 | V29: =LN(N29+1) -> 0 | W29: =LN(O29) -> -3.1581258 | X29: =LN(P29) -> -29.688576 | Z29: =(AB29*AD29)^4 -> 5.190386e-15 | AA29: 0.01188 | AB29: =BV29 -> 0.011502119 | AD29: 0.023335767 | AG29: =A29 -> NE | AH29: ='Final-2'!B$41+'Final-2'!B$42*M29+'Final-2'!B$43*N29+'Final-2'!B$44*O29+'Final-2'!B$45*P29 -> 0.0077897061 | AI29: =C29 -> 0.0019950831 | AJ29: =1/ABS(AH29-AI29) -> 172.57378 | AK29: 0.50761558 | AL29: 0.0066746455 | AM29: 0.57616893 | AO29: 0.021782127 | AQ29: 0.0019930956 | AR29: 11.249975 | AS29: 14.308444 | AT29: 11.437717 | AV29: 3653 | AW29: 3766 | AX29: 3653 | AY29: 4966 | BA29: 0.49238442 | BB29: 0.42383107 | BC29: NE | BD29: NE | BE29: Nebraska | BF29: 1578385 | BG29: 656998 | BH29: 101204 | BI29: 16883 | BJ29: 0.021782127 | BL29: 0.0066746455 | BM29: NE | BO29: nebraska | BP29: 0.95749467 | BQ29: 0.97666423 | BT29: nebraska | BU29: 0.00059786599 | BV29: 0.011502119 | BW29: 1.188 | BX29: Nebraska | BZ29: Nebraska | CA29: 0 | CD29: 497 | CE29: 0 | CG29: NE | CH29: NEBRASKA | CI29: NE | CJ29: 17 | CK29: 43 | CL29: 437
A30: NV | B30: NEVADA | C30: =F30/E30 -> 0 | D30: 1 | E30: 480760 | F30: 0 | G30: 342433 | H30: 138327 | J30: 109806 | K30: 13.934648 | L30: =BG30+BH30+BI30 -> 604609 | M30: 1530108 | N30: 0 | O30: 0.043349743 | P30: =BU30^4 -> 1.7620846e-13 | Q30: =S30/M30 -> 0.12502843 | R30: 484112 | S30: 191307 | T30: =AH30 -> 0.0080940945 | U30: =LN(M30) -> 14.240849 | V30: =LN(N30+1) -> 0 | W30: =LN(O30) -> -3.1384545 | X30: =LN(P30) -> -29.367109 | Z30: =(AB30*AD30)^4 -> 1.6437627e-14 | AA30: 0.7708 | AB30: =BV30 -> 0.028908072 | AD30: 0.012386273 | AG30: =A30 -> NV | AH30: ='Final-2'!B$41+'Final-2'!B$42*M30+'Final-2'!B$43*N30+'Final-2'!B$44*O30+'Final-2'!B$45*P30 -> 0.0080940945 | AI30: =C30 -> 0 | AJ30: =1/ABS(AH30-AI30) -> 123.54686 | AK30: 0.95546697 | AL30: 0.0048999883 | AM30: 0.8243223 | AO30: 0.013195305 | AQ30: 0 | AR30: 11.60647 | AS30: 14.240849 | AT30: 10.712995 | AV30: 1173 | AW30: 25167 | AX30: 1173 | AY30: 5504 | BA30: 0.04453303 | BB30: 0.1756777 | BC30: NV | BD30: NV | BE30: Nevada | BF30: 1201833 | BG30: 572290 | BH30: 24341 | BI30: 7978 | BJ30: 0.013195305 | BL30: 0.0048999883 | BM30: NV | BO30: nevada | BP30: 0.95665026 | BQ30: 0.98761373 | BT30: nevada | BU30: 0.00064789807 | BV30: 0.028908072 | BW30: 77.08 | BX30: Nevada | BZ30: Nevada | CA30: 0 | CD30: 586 | CE30: 0 | CG30: NV | CH30: NEVADA | CI30: NV | CJ30: 23 | CK30: 83 | CL30: 480
A31: NH | B31: NEW-HAMPSHIRE | C31: =F31/E31 -> 0.11777737 | D31: 1 | E31: 385957 | F31: 45457 | G31: 251579 | H31: 88921 | J31: 8969 | K31: 128.02464 | L31: =BG31+BH31+BI31 -> 566589 | M31: 1148253 | N31: 0.29022556 | O31: 0.085135719 | P31: =BU31^4 -> 7.50551e-08 | Q31: =S31/M31 -> 0.16467538 | R31: 328027 | S31: 189089 | T31: =AH31 -> 0.13561219 | U31: =LN(M31) -> 13.953752 | V31: =LN(N31+1) -> 0.25481706 | W31: =LN(O31) -> -2.4635086 | X31: =LN(P31) -> -16.405043 | Z31: =(AB31*AD31)^4 -> 6.6750007e-08 | AA31: 0.12758 | AB31: =BV31 -> 0.095689887 | AD31: 0.16797583 | AG31: =A31 -> NH | AH31: ='Final-2'!B$41+'Final-2'!B$42*M31+'Final-2'!B$43*N31+'Final-2'!B$44*O31+'Final-2'!B$45*P31 -> 0.13561219 | AI31: =C31 -> 0.11777737 | AJ31: =1/ABS(AH31-AI31) -> 56.070097 | AK31: 0.88259051 | AL31: 0.080484015 | AM31: 0.83090985 | AO31: 0.16681404 | AQ31: 0.11134222 | AR31: 9.1015295 | AS31: 13.953752 | AT31: 9.6215224 | AV31: 814 | AW31: 6119 | AX31: 814 | AY31: 4000 | BA31: 0.11740949 | BB31: 0.16909015 | BC31: NH | BD31: NH | BE31: New-Hampshire | BF31: 1109252 | BG31: 388368 | BH31: 83706 | BI31: 94515 | BJ31: 0.16681404 | BL31: 0.080484015 | BM31: NH | BO31: new-ha~1 | BP31: 0.91486428 | BQ31: 0.83202417 | BT31: new-ha~1 | BU31: 0.016551793 | BV31: 0.095689887 | BW31: 12.758 | BX31: New_Hampshire | BZ31: New_Hampshire | CA31: 77.2 | CB31: 43524 | CC31: 1950-57 | CD31: 266 | CE31: 0.29022556 | CG31: NH | CH31: NEW-HAMPSHIRE | CI31: NH | CJ31: 42 | CK31: 48 | CL31: 176
A32: NJ | B32: NEW-JERSEY | C32: =F32/E32 -> 0.27330336 | D32: 1 | E32: 2015332 | F32: 550797 | G32: 888912 | H32: 575623 | J32: 7419 | K32: 1070.9392 | L32: =BG32+BH32+BI32 -> 3812684 | M32: 7945298 | N32: 0.42472527 | O32: 0.070452296 | P32: =BU32^4 -> 9.7857405e-07 | Q32: =S32/M32 -> 0.16232267 | R32: 2101667 | S32: 1289702 | T32: =AH32 -> 0.27070103 | U32: =LN(M32) -> 15.888091 | V32: =LN(N32+1) -> 0.35397901 | W32: =LN(O32) -> -2.6528195 | X32: =LN(P32) -> -13.837169 | Z32: =(AB32*AD32)^4 -> 9.261788e-07 | AA32: 0.03332 | AB32: =BV32 -> 0.26496767 | AD32: 0.11707949 | AG32: =A32 -> NJ | AH32: ='Final-2'!B$41+'Final-2'!B$42*M32+'Final-2'!B$43*N32+'Final-2'!B$44*O32+'Final-2'!B$45*P32 -> 0.27070103 | AI32: =C32 -> 0.27330336 | AJ32: =1/ABS(AH32-AI32) -> 384.27173 | AK32: 0.83213464 | AL32: 0.084908341 | AM32: 0.85231868 | AO32: 0.11689088 | AQ32: 0.24161459 | AR32: 8.9117996 | AS32: 15.888091 | AT32: 10.481392 | AV32: 3431 | AW32: 17008 | AX32: 3431 | AY32: 19801.458 | BA32: 0.16786536 | BB32: 0.14768132 | BC32: NJ | BD32: NJ | BE32: New-Jersey | BF32: 7730188 | BG32: 2235202 | BH32: 1131814 | BI32: 445668 | BJ32: 0.11689088 | BL32: 0.084908341 | BM32: NJ | BO32: new-je~1 | BP32: 0.9295477 | BQ32: 0.88292051 | BT32: new-je~1 | BU32: 0.031452011 | BV32: 0.26496767 | BW32: 3.332 | BX32: New_Jersey | BZ32: New_Jersey | CA32: 309.2 | CB32: 821200 | CC32: 1952-57 | CD32: 728 | CE32: 0.42472527 | CG32: NJ | CH32: NEW-JERSEY | CI32: NJ | CJ32: 308 | CK32: 303 | CL32: 117
A33: NM | B33: NEW-MEXICO | C33: =F33/E33 -> 0 | D33: 1 | E33: 540397 | F33: 0 | G33: 362571 | H33: 177826 | J33: 121365 | K33: 13.887043 | L33: =BG33+BH33+BI33 -> 633135 | M33: 1685401 | N33: 0 | O33: 0.019095798 | P33: =BU33^4 -> 3.2675814e-12 | Q33: =S33/M33 -> 0.11759397 | R33: 534803 | S33: 198193 | T33: =AH33 -> -0.011826697 | U33: =LN(M33) -> 14.337514 | V33: =LN(N33+1) -> 0 | W33: =LN(O33) -> -3.958287 | X33: =LN(P33) -> -26.446971 | Z33: =(AB33*AD33)^4 -> 1.4007357e-13 | AA33: 0.33853 | AB33: =BV33 -> 0.024310879 | AD33: 0.025164504 | AG33: =A33 -> NM | AH33: ='Final-2'!B$41+'Final-2'!B$42*M33+'Final-2'!B$43*N33+'Final-2'!B$44*O33+'Final-2'!B$45*P33 -> -0.011826697 | AI33: =C33 -> 0 | AJ33: =1/ABS(AH33-AI33) -> 84.554463 | AK33: 0.47049085 | AL33: 0.0035662244 | AM33: 0.46194953 | AO33: 0.026424064 | AQ33: 0 | AR33: 11.706558 | AS33: 14.337514 | AT33: 11.023356 | AV33: 5437 | AW33: 4831 | AX33: 5437 | AY33: 4668 | BA33: 0.52950915 | BB33: 0.53805047 | BC33: NM | BD33: NM | BE33: New-Mexico | BF33: 1515069 | BG33: 555843 | BH33: 60562 | BI33: 16730 | BJ33: 0.026424064 | BL33: 0.0035662244 | BM33: NM | BO33: new-me~1 | BP33: 0.9809042 | BQ33: 0.9748355 | BT33: new-me~1 | BU33: 0.001344487 | BV33: 0.024310879 | BW33: 33.853 | BX33: New_Mexico | BZ33: New_Mexico | CA33: 0 | CD33: 1003 | CE33: 0 | CG33: NM | CH33: NEW-MEXICO | CI33: NM | CJ33: 3 | CK33: 108 | CL33: 892
A34: NY | B34: NEW-YORK | C34: =F34/E34 -> 0.33182204 | D34: 1 | E34: 4885872 | F34: 1621240 | G34: 2236452 | H34: 1028180 | J34: 47224 | K34: 384.04373 | L34: =BG34+BH34+BI34 -> 8220613 | M34: 18136081 | N34: 0.27010309 | O34: 0.050987802 | P34: =BU34^4 -> 6.1403053e-10 | Q34: =S34/M34 -> 0.13520446 | R34: 4584271 | S34: 2452079 | T34: =AH34 -> 0.15908565 | U34: =LN(M34) -> 16.713414 | V34: =LN(N34+1) -> 0.23909807 | W34: =LN(O34) -> -2.9761689 | X34: =LN(P34) -> -21.210976 | Z34: =(AB34*AD34)^4 -> 4.1881386e-10 | AA34: 0.00686 | AB34: =BV34 -> 0.18576987 | AD34: 0.024351739 | AG34: =A34 -> NY | AH34: ='Final-2'!B$41+'Final-2'!B$42*M34+'Final-2'!B$43*N34+'Final-2'!B$44*O34+'Final-2'!B$45*P34 -> 0.15908565 | AI34: =C34 -> 0.33182204 | AJ34: =1/ABS(AH34-AI34) -> 5.7891683 | AK34: 0.60830781 | AL34: 0.3469042 | AM34: 0.65210483 | AO34: 0.024343683 | AQ34: 0.28654796 | AR34: 10.762658 | AS34: 16.713414 | AT34: 11.627976 | AV34: 15983 | AW34: 24822 | AX34: 15983 | AY34: 29959 | BA34: 0.39169219 | BB34: 0.34789517 | BC34: NY | BD34: NY | BE34: New-York | BF34: 17990455 | BG34: 5426325 | BH34: 2594168 | BI34: 200120 | BJ34: 0.024343683 | BL34: 0.3469042 | BM34: NY | BO34: new-york | BP34: 0.9490122 | BQ34: 0.97564826 | BT34: new-york | BU34: 0.0049779152 | BV34: 0.18576987 | BW34: 0.686 | BX34: New_York | BZ34: New_York | CA34: 628.8 | CB34: 1130951 | CC34: 1926-60 | CD34: 2328 | CE34: 0.27010309 | CG34: NY | CH34: NEW-YORK | CI34: NY | CJ34: 830 | CK34: 702 | CL34: 796
A35: NC | B35: NORTH-CAROLINA | C35: =F35/E35 -> 0.00073844304 | D35: 1 | E35: 1849838 | F35: 1366 | G35: 1196985 | H35: 651487 | J35: 48718 | K35: 147.68952 | L35: =BG35+BH35+BI35 -> 3300481 | M35: 7195138 | N35: 0 | O35: 0.022130387 | P35: =BU35^4 -> 1.7329087e-12 | Q35: =S35/M35 -> 0.1196779 | R35: 1871498 | S35: 861099 | T35: =AH35 -> 0.011845608 | U35: =LN(M35) -> 15.788916 | V35: =LN(N35+1) -> 0 | W35: =LN(O35) -> -3.8108036 | X35: =LN(P35) -> -27.08122 | Z35: =(AB35*AD35)^4 -> 1.7085043e-13 | AA35: 0.0687 | AB35: =BV35 -> 0.0363048 | AD35: 0.017708834 | AG35: =A35 -> NC | AH35: ='Final-2'!B$41+'Final-2'!B$42*M35+'Final-2'!B$43*N35+'Final-2'!B$44*O35+'Final-2'!B$45*P35 -> 0.011845608 | AI35: =C35 -> 0.00073844304 | AJ35: =1/ABS(AH35-AI35) -> 90.031979 | AK35: 0.57831125 | AL35: 0.17711987 | AM35: 0.5687483 | AO35: 0.018277033 | AQ35: 0.00073817053 | AR35: 10.793804 | AS35: 15.788916 | AT35: 11.480495 | AV35: 12665 | AW35: 17369 | AX35: 12665 | AY35: 16703 | BA35: 0.42168875 | BB35: 0.4312517 | BC35: NC | BD35: NC | BE35: North-Carolina | BF35: 6628637 | BG35: 2582675 | BH35: 657483 | BI35: 60323 | BJ35: 0.018277033 | BL35: 0.17711987 | BM35: NC | BO35: north-~1 | BP35: 0.97786961 | BQ35: 0.98229117 | BT35: north-~1 | BU35: 0.0011473447 | BV35: 0.0363048 | BW35: 6.87 | BX35: North_Carolina | BZ35: North_Carolina | CA35: 0 | CD35: 1237 | CE35: 0 | CG35: NC | CH35: NORTH-CAROLINA | CI35: NC | CJ35: 267 | CK35: 339 | CL35: 631
A36: ND | B36: NORTH-DAKOTA | C36: =F36/E36 -> 0 | D36: 1 | E36: 190974 | F36: 0 | G36: 118507 | H36: 72467 | J36: 68994 | K36: 9.2959823 | L36: =BG36+BH36+BI36 -> 293548 | M36: 641367 | N36: 0 | O36: 0.058581713 | P36: =BU36^4 -> 2.8842868e-14 | Q36: =S36/M36 -> 0.18001238 | R36: 270095 | S36: 115454 | T36: =AH36 -> 0.017574102 | U36: =LN(M36) -> 13.371357 | V36: =LN(N36+1) -> 0 | W36: =LN(O36) -> -2.8373327 | X36: =LN(P36) -> -31.176914 | Z36: =(AB36*AD36)^4 -> 1.3378751e-15 | AA36: 0.04025 | AB36: =BV36 -> 0.005211769 | AD36: 0.036696001 | AG36: =A36 -> ND | AH36: ='Final-2'!B$41+'Final-2'!B$42*M36+'Final-2'!B$43*N36+'Final-2'!B$44*O36+'Final-2'!B$45*P36 -> 0.017574102 | AI36: =C36 -> 0 | AJ36: =1/ABS(AH36-AI36) -> 56.901912 | AK36: 0.48099066 | AL36: 0.0018753665 | AM36: 0.41660562 | AO36: 0.037101258 | AQ36: 0 | AR36: 11.141775 | AS36: 13.371357 | AT36: 11.371707 | AV36: 2389 | AW36: 2214 | AX36: 2389 | AY36: 1706 | BA36: 0.51900934 | BB36: 0.58339438 | BC36: ND | BD36: ND | BE36: North-Dakota | BF36: 638800 | BG36: 261956 | BH36: 20701 | BI36: 10891 | BJ36: 0.037101258 | BL36: 0.0018753665 | BM36: ND | BO36: north-~2 | BP36: 0.94141829 | BQ36: 0.963304 | BT36: north-~2 | BU36: 0.00041210664 | BV36: 0.005211769 | BW36: 4.025 | BX36: North_Dakota | BZ36: North_Dakota | CA36: 0 | CD36: 570 | CE36: 0 | CG36: ND | CH36: NORTH-DAKOTA | CI36: ND | CJ36: 0 | CK36: 40 | CL36: 530
A37: OH | B37: OHIO | C37: =F37/E37 -> 0.032875764 | D37: 1 | E37: 2725199 | F37: 89593 | G37: 1772628 | H37: 862978 | J37: 40953 | K37: 272.27568 | L37: =BG37+BH37+BI37 -> 4843205 | M37: 11150506 | N37: 0.1244192 | O37: 0.028268831 | P37: =BU37^4 -> 3.8555392e-12 | Q37: =S37/M37 -> 0.1441826 | R37: 2636791 | S37: 1607709 | T37: =AH37 -> 0.069438831 | U37: =LN(M37) -> 16.226995 | V37: =LN(N37+1) -> 0.11726664 | W37: =LN(O37) -> -3.5659955 | X37: =LN(P37) -> -26.28151 | Z37: =(AB37*AD37)^4 -> 1.7097107e-12 | AA37: 0.0107 | AB37: =BV37 -> 0.051340849 | AD37: 0.022272431 | AG37: =A37 -> OH | AH37: ='Final-2'!B$41+'Final-2'!B$42*M37+'Final-2'!B$43*N37+'Final-2'!B$44*O37+'Final-2'!B$45*P37 -> 0.069438831 | AI37: =C37 -> 0.032875764 | AJ37: =1/ABS(AH37-AI37) -> 27.350004 | AK37: 0.53503063 | AL37: 0.18545034 | AM37: 0.58232376 | AO37: 0.022558203 | AQ37: 0.032346916 | AR37: 10.62018 | AS37: 16.226995 | AT37: 11.64888 | AV37: 15997 | AW37: 18407.417 | AX37: 15997 | AY37: 22303 | BA37: 0.46496937 | BB37: 0.41767624 | BC37: OH | BD37: OH | BE37: Ohio | BF37: 10847115 | BG37: 3719156 | BH37: 1014795 | BI37: 109254 | BJ37: 0.022558203 | BL37: 0.18545034 | BM37: OH | BO37: ohio | BP37: 0.97173117 | BQ37: 0.97772757 | BT37: ohio | BU37: 0.0014012682 | BV37: 0.051340849 | BW37: 1.07 | BX37: Ohio | BZ37: Ohio | CA37: 241 | CB37: 326000 | CC37: 1955 | CD37: 1937 | CE37: 0.1244192 | CG37: OH | CH37: OHIO | CI37: OH | CJ37: 365 | CK37: 742 | CL37: 830
A38: OK | B38: OKLAHOMA | C38: =F38/E38 -> 0.075978257 | D38: 1 | E38: 1106356 | F38: 84059 | G38: 668391 | H38: 353906 | J38: 68679 | K38: 47.724734 | L38: =BG38+BH38+BI38 -> 1374338 | M38: 3277687 | N38: 0.16381579 | O38: 0.010839612 | P38: =BU38^4 -> 8.1818498e-13 | Q38: =S38/M38 -> 0.13807969 | R38: 828008 | S38: 452582 | T38: =AH38 -> 0.036332731 | U38: =LN(M38) -> 15.002649 | V38: =LN(N38+1) -> 0.15170408 | W38: =LN(O38) -> -4.5245481 | X38: =LN(P38) -> -27.831688 | Z38: =(AB38*AD38)^4 -> 8.3384164e-14 | AA38: 0.01454 | AB38: =BV38 -> 0.018373236 | AD38: 0.029247263 | AG38: =A38 -> OK | AH38: ='Final-2'!B$41+'Final-2'!B$42*M38+'Final-2'!B$43*N38+'Final-2'!B$44*O38+'Final-2'!B$45*P38 -> 0.036332731 | AI38: =C38 -> 0.075978257 | AJ38: =1/ABS(AH38-AI38) -> 25.223528 | AK38: 0.49239766 | AL38: 0.0091557019 | AM38: 0.54051193 | AO38: 0.029511663 | AQ38: 0.073230254 | AR38: 11.137199 | AS38: 15.002649 | AT38: 11.63086 | AV38: 7378 | AW38: 7157 | AX38: 7378 | AY38: 8679 | BA38: 0.50760234 | BB38: 0.45948807 | BC38: OK | BD38: OK | BE38: Oklahoma | BF38: 3145585 | BG38: 1087117 | BH38: 246662 | BI38: 40559 | BJ38: 0.029511663 | BL38: 0.0091557019 | BM38: OK | BO38: oklahoma | BP38: 0.98916039 | BQ38: 0.97075274 | BT38: oklahoma | BU38: 0.00095107086 | BV38: 0.018373236 | BW38: 1.454 | BX38: Oklahoma | BZ38: Oklahoma | CA38: 174.3 | CB38: 106714 | CC38: 1953-57 | CD38: 1064 | CE38: 0.16381579 | CG38: OK | CH38: OKLAHOMA | CI38: OK | CJ38: 134 | CK38: 209 | CL38: 721
A39: OR | B39: OREGON | C39: =F39/E39 -> 0.0052990403 | D39: 1 | E39: 900163 | F39: 4770 | G39: 616308 | H39: 279085 | J39: 96003 | K39: 32.713405 | L39: =BG39+BH39+BI39 -> 1294690 | M39: 3140585 | N39: 0 | O39: 0.037243383 | P39: =BU39^4 -> 1.8214548e-12 | Q39: =S39/M39 -> 0.1821425 | R39: 887786 | S39: 572034 | T39: =AH39 -> 0.0090980705 | U39: =LN(M39) -> 14.95992 | V39: =LN(N39+1) -> 0 | W39: =LN(O39) -> -3.290281 | X39: =LN(P39) -> -27.031386 | Z39: =(AB39*AD39)^4 -> 3.360531e-13 | AA39: 0.51837 | AB39: =BV39 -> 0.035970806 | AD39: 0.021166634 | AG39: =A39 -> OR | AH39: ='Final-2'!B$41+'Final-2'!B$42*M39+'Final-2'!B$43*N39+'Final-2'!B$44*O39+'Final-2'!B$45*P39 -> 0.0090980705 | AI39: =C39 -> 0.0052990403 | AJ39: =1/ABS(AH39-AI39) -> 263.22507 | AK39: 0.47980931 | AL39: 0.10161177 | AM39: 0.48968363 | AO39: 0.020572492 | AQ39: 0.0052850498 | AR39: 11.472135 | AS39: 14.95992 | AT39: 11.337905 | AV39: 7420 | AW39: 6844 | AX39: 7420 | AY39: 7120 | BA39: 0.52019069 | BB39: 0.51031637 | BC39: OR | BD39: OR | BE39: Oregon | BF39: 2842321 | BG39: 1012834 | BH39: 255221 | BI39: 26635 | BJ39: 0.020572492 | BL39: 0.10161177 | BM39: OR | BO39: oregon | BP39: 0.96275662 | BQ39: 0.97883337 | BT39: oregon | BU39: 0.0011617284 | BV39: 0.035970806 | BW39: 51.837 | BX39: Oregon | BZ39: Oregon | CA39: 0 | CD39: 780 | CE39: 0 | CG39: OR | CH39: OREGON | CI39: OR | CJ39: 52 | CK39: 146 | CL39: 582
A40: PA | B40: PENNSYLVANIA | C40: =F40/E40 -> 0.11697723 | D40: 1 | E40: 3182380 | F40: 372266 | G40: 1869845 | H40: 940269 | J40: 44820 | K40: 269.34052 | L40: =BG40+BH40+BI40 -> 5348132 | M40: 12071842 | N40: 0.22486823 | O40: 0.03417323 | P40: =BU40^4 -> 7.4232274e-09 | Q40: =S40/M40 -> 0.14165038 | R40: 3153335 | S40: 1709981 | T40: =AH40 -> 0.10870227 | U40: =LN(M40) -> 16.306386 | V40: =LN(N40+1) -> 0.20283327 | W40: =LN(O40) -> -3.3763127 | X40: =LN(P40) -> -18.718652 | Z40: =(AB40*AD40)^4 -> 6.6239639e-09 | AA40: 0.02205 | AB40: =BV40 -> 0.21098324 | AD40: 0.042759394 | AG40: =A40 -> PA | AH40: ='Final-2'!B$41+'Final-2'!B$42*M40+'Final-2'!B$43*N40+'Final-2'!B$44*O40+'Final-2'!B$45*P40 -> 0.10870227 | AI40: =C40 -> 0.11697723 | AJ40: =1/ABS(AH40-AI40) -> 120.84652 | AK40: 0.6501617 | AL40: 0.29525636 | AM40: 0.57465022 | AO40: 0.043268753 | AQ40: 0.11062614 | AR40: 10.71041 | AS40: 16.306386 | AT40: 11.683916 | AV40: 12548 | AW40: 23320 | AX40: 7205 | AY40: 9734 | BA40: 0.3498383 | BB40: 0.42534978 | BC40: PA | BD40: PA | BE40: Pennsylvania | BF40: 11881643 | BG40: 4006525 | BH40: 1110200 | BI40: 231407 | BJ40: 0.043268753 | BL40: 0.29525636 | BM40: PA | BO40: pennsy~1 | BP40: 0.96582677 | BQ40: 0.95724061 | BT40: pennsy~1 | BU40: 0.0092821416 | BV40: 0.21098324 | BW40: 2.205 | BX40: Pennsylvania | BZ40: Pennsylvania | CA40: 469.3 | CB40: 539664 | CC40: 1940-57 | CD40: 2087 | CE40: 0.22486823 | CG40: PA | CH40: PENNSYLVANIA | CI40: PA | CJ40: 499 | CK40: 507 | CL40: 1081
A41: RI | B41: RHODE-ISLAND | C41: =F41/E41 -> 0.037366118 | D41: 1 | E41: 248166 | F41: 9273 | G41: 174520 | H41: 64373 | J41: 1045 | K41: 947.17129 | L41: =BG41+BH41+BI41 -> 481230 | M41: 989794 | N41: 0 | O41: 0.075765241 | P41: =BU41^4 -> 1.3046738e-08 | Q41: =S41/M41 -> 0.090382443 | R41: 290143 | S41: 89460 | T41: =AH41 -> 0.034616586 | U41: =LN(M41) -> 13.805252 | V41: =LN(N41+1) -> 0 | W41: =LN(O41) -> -2.5801157 | X41: =LN(P41) -> -18.154728 | Z41: =(AB41*AD41)^4 -> 1.2143413e-08 | AA41: 0.00681 | AB41: =BV41 -> 0.088329535 | AD41: 0.11884454 | AG41: =A41 -> RI | AH41: ='Final-2'!B$41+'Final-2'!B$42*M41+'Final-2'!B$43*N41+'Final-2'!B$44*O41+'Final-2'!B$45*P41 -> 0.034616586 | AI41: =C41 -> 0.037366118 | AJ41: =1/ABS(AH41-AI41) -> 363.69831 | AK41: 1 | AL41: 0.095711951 | AM41: 1 | AO41: 0.12150115 | AQ41: 0.036684922 | AR41: 6.9517722 | AS41: 13.805252 | AT41: 8.6815205 | AV41: 0 | AW41: 2049 | AX41: 0 | AY41: 2258 | BA41: 0 | BB41: 0 | BC41: RI | BD41: RI | BE41: Rhode- Island | BF41: 1003464 | BG41: 329829 | BH41: 92931 | BI41: 58470 | BJ41: 0.12150115 | BL41: 0.095711951 | BM41: RI | BO41: rhode-~1 | BP41: 0.92423476 | BQ41: 0.88115546 | BT41: rhode-~1 | BU41: 0.010687484 | BV41: 0.088329535 | BW41: 0.681 | BX41: Rhode_Island | BZ41: Rhode_Island | CA41: 0 | CD41: 137 | CE41: 0 | CG41: RI | CH41: RHODE-ISLAND | CI41: RI | CJ41: 68 | CK41: 48 | CL41: 21
A42: SC | B42: SOUTH-CAROLINA | C42: =F42/E42 -> 0 | D42: 1 | E42: 822072 | F42: 0 | G42: 452324 | H42: 369748 | J42: 30111 | K42: 121.99153 | L42: =BG42+BH42+BI42 -> 1636356 | M42: 3673287 | N42: 0 | O42: 0.02121566 | P42: =BU42^4 -> 2.5762505e-14 | Q42: =S42/M42 -> 0.078382386 | R42: 668381 | S42: 287921 | T42: =AH42 -> -0.0024190628 | U42: =LN(M42) -> 15.116597 | V42: =LN(N42+1) -> 0 | W42: =LN(O42) -> -3.8530157 | X42: =LN(P42) -> -31.289856 | Z42: =(AB42*AD42)^4 -> 1.3511322e-16 | AA42: 0.03782 | AB42: =BV42 -> 0.0059124841 | AD42: 0.018234946 | AG42: =A42 -> SC | AH42: ='Final-2'!B$41+'Final-2'!B$42*M42+'Final-2'!B$43*N42+'Final-2'!B$44*O42+'Final-2'!B$45*P42 -> -0.0024190628 | AI42: =C42 -> 0 | AJ42: =1/ABS(AH42-AI42) -> 413.38324 | AK42: 0.68784602 | AL42: 0.01538888 | AM42: 0.59932257 | AO42: 0.041009414 | AQ42: 0 | AR42: 10.312646 | AS42: 15.116597 | AT42: 11.071206 | AV42: 6033 | AW42: 13294 | AX42: 6033 | AY42: 9024 | BA42: 0.31215398 | BB42: 0.40067743 | BC42: SC | BD42: SC | BE42: South-Carolina | BF42: 3486703 | BG42: 1239694 | BH42: 329556 | BI42: 67106 | BJ42: 0.041009414 | BL42: 0.01538888 | BM42: SC | BO42: south-~1 | BP42: 0.97878434 | BQ42: 0.98176505 | BT42: south-~1 | BU42: 0.00040063328 | BV42: 0.0059124841 | BW42: 3.782 | BX42: South_Carolina | BZ42: South_Carolina | CA42: 0 | CD42: 894 | CE42: 0 | CG42: SC | CH42: SOUTH-CAROLINA | CI42: SC | CJ42: 65 | CK42: 158 | CL42: 671
A43: SD | B43: SOUTH-DAKOTA | C43: =F43/E43 -> 0 | D43: 1 | E43: 199865 | F43: 0 | G43: 123080 | H43: 76785 | J43: 75898 | K43: 9.6054441 | L43: =BG43+BH43+BI43 -> 324122 | M43: 729034 | N43: 0 | O43: 0.029576162 | P43: =BU43^4 -> 8.5109626e-12 | Q43: =S43/M43 -> 0.13487025 | R43: 285683 | S43: 98325 | T43: =AH43 -> -0.0066245422 | U43: =LN(M43) -> 13.499476 | V43: =LN(N43+1) -> 0 | W43: =LN(O43) -> -3.5207866 | X43: =LN(P43) -> -25.489666 | Z43: =(AB43*AD43)^4 -> 3.7189847e-14 | AA43: 0.05487 | AB43: =BV43 -> 0.010935721 | AD43: 0.04015676 | AG43: =A43 -> SD | AH43: ='Final-2'!B$41+'Final-2'!B$42*M43+'Final-2'!B$43*N43+'Final-2'!B$44*O43+'Final-2'!B$45*P43 -> -0.0066245422 | AI43: =C43 -> 0 | AJ43: =1/ABS(AH43-AI43) -> 150.95383 | AK43: 0.28592666 | AL43: 0.0012204312 | AM43: 0.43938462 | AO43: 0.019282863 | AQ43: 0 | AR43: 11.237146 | AS43: 13.499476 | AT43: 11.330924 | AV43: 7205 | AW43: 2885 | AX43: 2733 | AY43: 2142 | BA43: 0.71407334 | BB43: 0.56061538 | BC43: SD | BD43: SD | BE43: South-Dakota | BF43: 696004 | BG43: 283710 | BH43: 34162 | BI43: 6250 | BJ43: 0.019282863 | BL43: 0.0012204312 | BM43: SD | BO43: south-~2 | BP43: 0.97042384 | BQ43: 0.95984324 | BT43: south-~2 | BU43: 0.0017080268 | BV43: 0.010935721 | BW43: 5.487 | BX43: South_Dakota | BZ43: South_Dakota | CA43: 0 | CD43: 681 | CE43: 0 | CG43: SD | CH43: SOUTH-DAKOTA | CI43: SD | CJ43: 3 | CK43: 49 | CL43: 629
A44: TN | B44: TENNESSEE | C44: =F44/E44 -> 5.8005165e-05 | D44: 1 | E44: 1327468 | F44: 77 | G44: 810176 | H44: 517215 | J44: 41220 | K44: 127.51215 | L44: =BG44+BH44+BI44 -> 2239256 | M44: 5256051 | N44: 0 | O44: 0.045863087 | P44: =BU44^4 -> 2.9434141e-13 | Q44: =S44/M44 -> 0.11797983 | R44: 1229518 | S44: 620108 | T44: =AH44 -> 0.024492654 | U44: =LN(M44) -> 15.474891 | V44: =LN(N44+1) -> 0 | W44: =LN(O44) -> -3.0820947 | X44: =LN(P44) -> -28.854036 | Z44: =(AB44*AD44)^4 -> 9.0086854e-14 | AA44: 0.05741 | AB44: =BV44 -> 0.016602629 | AD44: 0.032998066 | AG44: =A44 -> TN | AH44: ='Final-2'!B$41+'Final-2'!B$42*M44+'Final-2'!B$43*N44+'Final-2'!B$44*O44+'Final-2'!B$45*P44 -> 0.024492654 | AI44: =C44 -> 5.8005165e-05 | AJ44: =1/ABS(AH44-AI44) -> 40.925492 | AK44: 0.74211707 | AL44: 0.061441398 | AM44: 0.70391315 | AO44: 0.034057741 | AQ44: 5.8003482e-05 | AR44: 10.626679 | AS44: 15.474891 | AT44: 11.357429 | AV44: 5864 | AW44: 16875 | AX44: 5864 | AY44: 13941 | BA44: 0.25788293 | BB44: 0.29608685 | BC44: TN | BD44: TN | BE44: Tennessee | BF44: 4877185 | BG44: 1748489 | BH44: 414503 | BI44: 76264 | BJ44: 0.034057741 | BL44: 0.061441398 | BM44: TN | BO44: tennes~1 | BP44: 0.95413691 | BQ44: 0.96700193 | BT44: tennes~1 | BU44: 0.00073656799 | BV44: 0.016602629 | BW44: 5.741 | BX44: Tennessee | BZ44: Tennessee | CA44: 0 | CD44: 1176 | CE44: 0 | CG44: TN | CH44: TENNESSEE | CI44: TN | CJ44: 114 | CK44: 323 | CL44: 739
A45: TX | B45: TEXAS | C45: =F45/E45 -> 0.024747469 | D45: 1 | E45: 6279713 | F45: 155407 | G45: 4463068 | H45: 1661238 | J45: 261914 | K45: 71.48908 | L45: =BG45+BH45+BI45 -> 7610487 | M45: 18723991 | N45: 0.0067277604 | O45: 0.0091052427 | P45: =BU45^4 -> 2.3845837e-12 | Q45: =S45/M45 -> 0.095590304 | R45: 3592957 | S45: 1789832 | T45: =AH45 -> 0.047004454 | U45: =LN(M45) -> 16.745316 | V45: =LN(N45+1) -> 0.00670523 | W45: =LN(O45) -> -4.6989049 | X45: =LN(P45) -> -26.761997 | Z45: =(AB45*AD45)^4 -> 7.3539052e-15 | AA45: 0.01395 | AB45: =BV45 -> 0.036645965 | AD45: 0.0079910407 | AG45: =A45 -> TX | AH45: ='Final-2'!B$41+'Final-2'!B$42*M45+'Final-2'!B$43*N45+'Final-2'!B$44*O45+'Final-2'!B$45*P45 -> 0.047004454 | AI45: =C45 -> 0.024747469 | AJ45: =1/ABS(AH45-AI45) -> 44.929715 | AK45: 0.25227051 | AL45: 0.059239773 | AM45: 0.29258816 | AO45: 0.0088600112 | AQ45: 0.02444621 | AR45: 12.475771 | AS45: 16.745316 | AT45: 12.598743 | AV45: 56808 | AW45: 19166 | AX45: 56808 | AY45: 23496 | BA45: 0.74772949 | BB45: 0.70741184 | BC45: TX | BD45: TX | BE45: Texas | BF45: 16986510 | BG45: 6312264 | BH45: 1230794 | BI45: 67429 | BJ45: 0.0088600112 | BL45: 0.059239773 | BM45: TX | BO45: texas | BP45: 0.99089476 | BQ45: 0.99200896 | BT45: texas | BU45: 0.0012426624 | BV45: 0.036645965 | BW45: 1.395 | BX45: Texas | BZ45: Texas | CA45: 30.1 | CB45: 58500 | CC45: 1957 | CD45: 4474 | CE45: 0.0067277604 | CG45: TX | CH45: TEXAS | CI45: TX | CJ45: 1240 | CK45: 1031 | CL45: 2203
A46: UT | B46: UTAH | C46: =F46/E46 -> 0.0006229862 | D46: 1 | E46: 401293 | F46: 250 | G46: 239945 | H46: 161098 | J46: 82168 | K46: 23.749002 | L46: =BG46+BH46+BI46 -> 732376 | M46: 1951408 | N46: 0 | O46: 0.0099134387 | P46: =BU46^4 -> 4.1676036e-13 | Q46: =S46/M46 -> 0.10180547 | R46: 431264 | S46: 198664 | T46: =AH46 -> -0.018575166 | U46: =LN(M46) -> 14.484062 | V46: =LN(N46+1) -> 0 | W46: =LN(O46) -> -4.613864 | X46: =LN(P46) -> -28.506265 | Z46: =(AB46*AD46)^4 -> 1.7169434e-15 | AA46: 0.63112 | AB46: =BV46 -> 0.015303121 | AD46: 0.013301756 | AG46: =A46 -> UT | AH46: ='Final-2'!B$41+'Final-2'!B$42*M46+'Final-2'!B$43*N46+'Final-2'!B$44*O46+'Final-2'!B$45*P46 -> -0.018575166 | AI46: =C46 -> 0.0006229862 | AJ46: =1/ABS(AH46-AI46) -> 52.088347 | AK46: 0.53501603 | AL46: 0.014392472 | AM46: 0.5799458 | AO46: 0.013484877 | AQ46: 0.00062279222 | AR46: 11.316521 | AS46: 14.484062 | AT46: 10.6224 | AV46: 4495 | AW46: 5172 | AX46: 4495 | AY46: 6206 | BA46: 0.46498397 | BB46: 0.4200542 | BC46: UT | BD46: UT | BE46: Utah | BF46: 1722850 | BG46: 620236 | BH46: 102264 | BI46: 9876 | BJ46: 0.013484877 | BL46: 0.014392472 | BM46: UT | BO46: utah | BP46: 0.99008656 | BQ46: 0.98669824 | BT46: utah | BU46: 0.00080347358 | BV46: 0.015303121 | BW46: 63.112 | BX46: Utah | BZ46: Utah | CA46: 0 | CD46: 948 | CE46: 0 | CG46: UT | CH46: UTAH | CI46: UT | CJ46: 8 | CK46: 169 | CL46: 771
A47: VT | B47: VERMONT | C47: =F47/E47 -> 0 | D47: 1 | E47: 197087 | F47: 0 | G47: 138217 | H47: 58870 | J47: 9249 | K47: 63.225322 | L47: =BG47+BH47+BI47 -> 276765 | M47: 584771 | N47: 0 | O47: 0.049495607 | P47: =BU47^4 -> 5.2865925e-09 | Q47: =S47/M47 -> 0.19002481 | R47: 194205 | S47: 111121 | T47: =AH47 -> 0.010146688 | U47: =LN(M47) -> 13.278976 | V47: =LN(N47+1) -> 0 | W47: =LN(O47) -> -3.0058714 | X47: =LN(P47) -> -19.058092 | Z47: =(AB47*AD47)^4 -> 4.5873442e-09 | AA47: 0.06407 | AB47: =BV47 -> 0.1410405 | AD47: 0.058350757 | AG47: =A47 -> VT | AH47: ='Final-2'!B$41+'Final-2'!B$42*M47+'Final-2'!B$43*N47+'Final-2'!B$44*O47+'Final-2'!B$45*P47 -> 0.010146688 | AI47: =C47 -> 0 | AJ47: =1/ABS(AH47-AI47) -> 98.55433 | AK47: 0.93785532 | AL47: 0.030891023 | AM47: 0.88931564 | AO47: 0.06002204 | AQ47: 0 | AR47: 9.1322707 | AS47: 13.278976 | AT47: 9.5598698 | AV47: 317 | AW47: 4784 | AX47: 317 | AY47: 2547 | BA47: 0.062144678 | BB47: 0.11068436 | BC47: VT | BD47: VT | BE47: Vermont | BF47: 562758 | BG47: 227512 | BH47: 32641 | BI47: 16612 | BJ47: 0.06002204 | BL47: 0.030891023 | BM47: VT | BO47: vermont | BP47: 0.95050439 | BQ47: 0.94164924 | BT47: vermont | BU47: 0.0085269548 | BV47: 0.1410405 | BW47: 6.407 | BX47: Vermont | BZ47: Vermont | CA47: 0 | CD47: 1329 | CE47: 0 | CG47: VT | CH47: VERMONT | CI47: VA | CJ47: 223 | CK47: 398 | CL47: 708
A48: VA | B48: VIRGINIA | C48: =F48/E48 -> 0.046528368 | D48: 1 | E48: 1942170 | F48: 90366 | G48: 1251465 | H48: 600339 | J48: 39598 | K48: 167.13869 | L48: =BG48+BH48+BI48 -> 3146858 | M48: 6618358 | N48: 0.1020649 | O48: 0.064609801 | P48: =BU48^4 -> 2.1699895e-10 | Q48: =S48/M48 -> 0.1810925 | R48: 2107426 | S48: 1198535 | T48: =AH48 -> 0.07614475 | U48: =LN(M48) -> 15.705358 | V48: =LN(N48+1) -> 0.097185599 | W48: =LN(O48) -> -2.7393892 | X48: =LN(P48) -> -22.251129 | Z48: =(AB48*AD48)^4 -> 1.3171224e-11 | AA48: 0.0939 | AB48: =BV48 -> 0.020499083 | AD48: 0.092933458 | AG48: =A48 -> VA | AH48: ='Final-2'!B$41+'Final-2'!B$42*M48+'Final-2'!B$43*N48+'Final-2'!B$44*O48+'Final-2'!B$45*P48 -> 0.07614475 | AI48: =C48 -> 0.046528368 | AJ48: =1/ABS(AH48-AI48) -> 33.765097 | AK48: 0.6123871 | AL48: 0.15629345 | AM48: 0.67760169 | AO48: 0.09395022 | AQ48: 0.04547837 | AR48: 10.586534 | AS48: 15.705358 | AT48: 11.143918 | AV48: 9012 | AW48: 14238 | AX48: 9012 | AY48: 18941 | BA48: 0.3876129 | BB48: 0.32239831 | BC48: VA | BD48: VA | BE48: Virginia | BF48: 6187358 | BG48: 1627940 | BH48: 1223270 | BI48: 295648 | BJ48: 0.09395022 | BL48: 0.15629345 | BM48: VA | BO48: virginia | BP48: 0.9353902 | BQ48: 0.90706654 | BT48: virginia | BU48: 0.0038380834 | BV48: 0.020499083 | BW48: 9.39 | BX48: Virginia | BZ48: Virginia | CA48: 34.6 | CB48: 75150 | CC48: 1958 | CD48: 339 | CE48: 0.1020649 | CG48: VA | CH48: VIRGINIA | CI48: VT | CJ48: 19 | CK48: 40 | CL48: 280
A49: WA | B49: WASHINGTON | C49: =F49/E49 -> 0.04142763 | D49: 1 | E49: 1970931 | F49: 81651 | G49: 1466547 | H49: 422733 | J49: 66582 | K49: 81.567691 | L49: =BG49+BH49+BI49 -> 2302666 | M49: 5430940 | N49: 0 | O49: 0.015269423 | P49: =BU49^4 -> 4.6818222e-12 | Q49: =S49/M49 -> 0.20997801 | R49: 1908715 | S49: 1140378 | T49: =AH49 -> -0.00071560084 | U49: =LN(M49) -> 15.507623 | V49: =LN(N49+1) -> 0 | W49: =LN(O49) -> -4.181903 | X49: =LN(P49) -> -26.087334 | Z49: =(AB49*AD49)^4 -> 1.280179e-14 | AA49: 0.24061 | AB49: =BV49 -> 0.012440747 | AD49: 0.027037792 | AG49: =A49 -> WA | AH49: ='Final-2'!B$41+'Final-2'!B$42*M49+'Final-2'!B$43*N49+'Final-2'!B$44*O49+'Final-2'!B$45*P49 -> -0.00071560084 | AI49: =C49 -> 0.04142763 | AJ49: =1/ABS(AH49-AI49) -> 23.728603 | AK49: 0.3627301 | AL49: 0.028097166 | AM49: 0.43440329 | AO49: 0.02855299 | AQ49: 0.040592493 | AR49: 11.10619 | AS49: 15.507623 | AT49: 11.28615 | AV49: 13744 | AW49: 7823 | AX49: 13744 | AY49: 10556 | BA49: 0.6372699 | BB49: 0.56559671 | BC49: WA | BD49: WA | BE49: Washington | BF49: 4866692 | BG49: 1932957 | BH49: 303961 | BI49: 65748 | BJ49: 0.02855299 | BL49: 0.028097166 | BM49: WA | BO49: washin~1 | BP49: 0.98473058 | BQ49: 0.97296221 | BT49: washin~1 | BU49: 0.0014709697 | BV49: 0.012440747 | BW49: 24.061 | BX49: Washington | BZ49: Washington | CA49: 0 | CD49: 1079 | CE49: 0 | CG49: WA | CH49: WASHINGTON | CI49: WA | CJ49: 316 | CK49: 262 | CL49: 501
A50: WV | B50: WEST-VIRGINIA | C50: =F50/E50 -> 0.065724566 | D50: 1 | E50: 642819 | F50: 42249 | G50: 425486 | H50: 175084 | J50: 24087 | K50: 75.897372 | L50: =BG50+BH50+BI50 -> 659136 | M50: 1828140 | N50: 0.15410714 | O50: 0.083450811 | P50: =BU50^4 -> 6.8521448e-10 | Q50: =S50/M50 -> 0.17702966 | R50: 780879 | S50: 323635 | T50: =AH50 -> 0.089355379 | U50: =LN(M50) -> 14.41881 | V50: =LN(N50+1) -> 0.14332701 | W50: =LN(O50) -> -2.4834979 | X50: =LN(P50) -> -21.101289 | Z50: =(AB50*AD50)^4 -> 6.1131009e-10 | AA50: 0.07007 | AB50: =BV50 -> 0.051171166 | AD50: 0.097171763 | AG50: =A50 -> WV | AH50: ='Final-2'!B$41+'Final-2'!B$42*M50+'Final-2'!B$43*N50+'Final-2'!B$44*O50+'Final-2'!B$45*P50 -> 0.089355379 | AI50: =C50 -> 0.065724566 | AJ50: =1/ABS(AH50-AI50) -> 42.31763 | AK50: 0.78066958 | AL50: 0.033797224 | AM50: 0.69253731 | AO50: 0.094739174 | AQ50: 0.063654912 | AR50: 10.089428 | AS50: 14.41881 | AT50: 10.466241 | AV50: 1854 | AW50: 6599 | AX50: 1854 | AY50: 4176 | BA50: 0.21933042 | BB50: 0.30746269 | BC50: WV | BD50: WV | BE50: West-Virginia | BF50: 1793477 | BG50: 486317 | BH50: 110373 | BI50: 62446 | BJ50: 0.094739174 | BL50: 0.033797224 | BM50: WV | BO50: west-v~1 | BP50: 0.91654919 | BQ50: 0.90282824 | BT50: west-v~1 | BU50: 0.0051163074 | BV50: 0.051171166 | BW50: 7.007 | BX50: West_Virginia | BZ50: West_Virginia | CA50: 86.3 | CB50: 133000 | CC50: 1954 | CD50: 560 | CE50: 0.15410714 | CG50: WV | CH50: WEST-VIRGINIA | CI50: WV | CJ50: 10 | CK50: 91 | CL50: 459
A51: WI | B51: WISCONSIN | C51: =F51/E51 -> 1.1333251e-05 | D51: 1 | E51: 1323539 | F51: 15 | G51: 890071 | H51: 433453 | J51: 54314 | K51: 94.319531 | L51: =BG51+BH51+BI51 -> 2349691 | M51: 5122871 | N51: 0 | O51: 0.013707909 | P51: =BU51^4 -> 6.2297067e-12 | Q51: =S51/M51 -> 0.12104911 | R51: 1251993 | S51: 620119 | T51: =AH51 -> -0.0032164016 | U51: =LN(M51) -> 15.449226 | V51: =LN(N51+1) -> 0 | W51: =LN(O51) -> -4.2897823 | X51: =LN(P51) -> -25.801692 | Z51: =(AB51*AD51)^4 -> 3.8703487e-12 | AA51: 0.05291 | AB51: =BV51 -> 0.043589838 | AD51: 0.032177498 | AG51: =A51 -> WI | AH51: ='Final-2'!B$41+'Final-2'!B$42*M51+'Final-2'!B$43*N51+'Final-2'!B$44*O51+'Final-2'!B$45*P51 -> -0.0032164016 | AI51: =C51 -> 1.1333251e-05 | AJ51: =1/ABS(AH51-AI51) -> 309.81479 | AK51: 0.4623289 | AL51: 0.019022588 | AM51: 0.4566203 | AO51: 0.033231604 | AQ51: 1.1333187e-05 | AR51: 10.902537 | AS51: 15.449226 | AT51: 11.621681 | AV51: 14023 | AW51: 12058 | AX51: 14023 | AY51: 11784 | BA51: 0.5376711 | BB51: 0.5433797 | BC51: WI | BD51: WI | BE51: Wisconsin | BF51: 4891769 | BG51: 1846382 | BH51: 425225 | BI51: 78084 | BJ51: 0.033231604 | BL51: 0.019022588 | BM51: WI | BO51: wiscon~1 | BP51: 0.98629209 | BQ51: 0.9678225 | BT51: wiscon~1 | BU51: 0.0015798538 | BV51: 0.043589838 | BW51: 5.291 | BX51: Wisconsin | BZ51: Wisconsin | CA51: 0 | CD51: 830 | CE51: 0 | CG51: WI | CH51: WISCONSIN | CI51: WI | CJ51: 191 | CK51: 149 | CL51: 490
A52: WY | B52: WYOMING | C52: =F52/E52 -> 0 | D52: 1 | E52: 169944 | F52: 0 | G52: 80882 | H52: 89062 | J52: 97105 | K52: 4.9449977 | L52: =BG52+BH52+BI52 -> 208374 | M52: 480184 | N52: 0 | O52: 0.025620995 | P52: =BU52^4 -> 2.0686308e-13 | Q52: =S52/M52 -> 0.232615 | R52: 271998 | S52: 111698 | T52: =AH52 -> -0.010924129 | U52: =LN(M52) -> 13.081925 | V52: =LN(N52+1) -> 0 | W52: =LN(O52) -> -3.6643431 | X52: =LN(P52) -> -29.206719 | Z52: =(AB52*AD52)^4 -> 2.8461025e-15 | AA52: 0.48452 | AB52: =BV52 -> 0.011513892 | AD52: 0.020060442 | AG52: =A52 -> WY | AH52: ='Final-2'!B$41+'Final-2'!B$42*M52+'Final-2'!B$43*N52+'Final-2'!B$44*O52+'Final-2'!B$45*P52 -> -0.010924129 | AI52: =C52 -> 0 | AJ52: =1/ABS(AH52-AI52) -> 91.540482 | AK52: 0.63534392 | AL52: 0.0055484992 | AM52: 0.57883158 | AO52: 0.019786538 | AQ52: 0 | AR52: 11.483548 | AS52: 13.081925 | AT52: 10.476189 | AV52: 1723 | AW52: 3002 | AX52: 1723 | AY52: 2368 | BA52: 0.36465608 | BB52: 0.42116842 | BC52: WY | BD52: WY | BE52: Wyoming | BF52: 453588 | BG52: 196211 | BH52: 8040 | BI52: 4123 | BJ52: 0.019786538 | BL52: 0.0055484992 | BM52: WY | BO52: wyoming | BP52: 0.974379 | BQ52: 0.97993956 | BT52: wyoming | BU52: 0.00067440495 | BV52: 0.011513892 | BW52: 48.452 | BX52: Wyoming | BZ52: Wyoming | CA52: 0 | CD52: 916 | CE52: 0 | CG52: WY | CH52: WYOMING | CI52: WY | CJ52: 3 | CK52: 87 | CL52: 826
